Workbook

Sheet интро
C3: Исследование выполнил: Александр Глебвский
C4: Данные сгенерированы ChatGPT и не являются NDA
C6: Задачи исследования | D6: № | E6: Декомпозиция | F6: Выводы исследования
C7: Анализ продаж продуктовых сетей | D7: 1 | E7: Динамика продаж по магазинам | F7: Проанализирован период с января 2023 по май 2024. Наблюдается общее снижение продаж в октябре 2023. По магазинам продаж: в Ашане видим рост продаж после июля 2023. В Дикси - провал воктябре 2023. В Пятерочке - максимум в августе 2023, а спады заметны в мае и декабре 2023
D8: 2 | E8: Анализ цен внутри товарной категории по магазинам | F8: В Пятерочке - наибольший дисконт - 10%, в Ленте наценка 13%
D9: 3 | E9: Суммарные продажи по магазинам | F9: По сумме продаж лидирует O'Key, отстает Билла
C10: Сравнение поставщиков по объемам закупок | D10: 4 | E10: Анализ цен внутри категории по поставщикам | F10: Максимальная цена макарон в ПастаЗара
D11: 5 | E11: Суммарные продажи по поставщикам | F11: Лидирует Паста Зара, отстает Вим БильДан
C12: Изучение продаж по категориям товаров | D12: 6 | E12: Суммарные продажи по категориям | F12: Лидируют макароны и конфты, отстает колбаса
D13: 7 | E13: Среднее кол-во по категориям (что покупают чаще) | F13: В чеке в среднем 3 штуки в каждой категории
C14: Изучение клиентов по географии и лайфтайму | D14: 8 | E14: Аналитика географии клиентов | F14: Большинство клиентов из России, меньшинство из Беларси
D15: 9 | E15: Кол-во дней с момента регистрациидо покупки | F15: среднее - 1.5 гола (450 - 550 дней)
D16: 10 | E16: Лайфтайм клиента | F16: Средий лайфтайм - около 3-х лет
D17: 11 | E17: Частотность имен для рекламной компании | F17: 70% имен использутся по 5 раз
D18: 12 | E18: Платежеспособность по странам | F18: Россия показывает наибольшую платежжеспособность, Белорусь - наименьшую
C20: Отработка Hard Skills
C21: Преобразование типов и визуальное форматирование
C22: Условное форматирование данных
C23: Умные таблицы и работа с абсолютными и относительными ссылками
C24: Математические и текстовые функции
C25: Функции для работы с датой и временем
C26: Функции поиска и извлечения данных
C27: Сводные таблицы и срезы данных
C28: Построение диаграмм

Sheet Гафики

Sheet Динамика продаж
A1: магазин покупки | B1: Пятерочка
A3: Названия строк | B3: Сумма по полю сумма чека
A4: 2023 | B4: 19503
A5: янв | B5: 963
A6: фев | B6: 1185
A7: мар | B7: 2444
A8: апр | B8: 448
A9: май | B9: 460
A10: июн | B10: 2898
A11: июл | B11: 2715
A12: авг | B12: 3967
A13: сен | B13: 2378
A14: окт | B14: 1397
A15: дек | B15: 648
... A21: Общий итог | B21: 27662
D24: Проанализирован период с января 2023 по май 2024. Наблюдается общее снижение продаж в октябре 2023.
D25: По магазинам продаж: в Ашане видим рост продаж после июля 2023
D26: В Дикси - провал в октябре 2023
D27: В Пятерочке - максимум в августе 2023, а спады заметны в мае и декабре 2023

Sheet Выгода клиента
A3: Названия строк | B3: Среднее по полю Выгода клиента
A4: Лента | B4: 0.13314535
A5: Городской Супермаркет | B5: 0.065458688
A6: Метро | B6: 0.047852649
A7: Билла | B7: 0.04577719
A8: Азбука Вкуса | B8: 0.04213556
A9: Седьмой Континент | B9: 0.039584188
A10: Ароматный Мир | B10: 0.026621364
A11: Мосмарт | B11: 0.019548995
A12: Мираторг | B12: 0.0043236685
A13: Ашан | B13: -0.0089704365
A14: Бристоль | B14: -0.011007391
A15: Магнит | B15: -0.024982716
... A23: Спар | B23: -0.066618319
D25: В Пятерочке - наибольший дисконт - 10%, в Ленте наценка 10%

Sheet GMV Продажи по магазинам
A3: Названия строк | B3: GMV
A4: О'кей | B4: 52844
A5: Гиперглобус | B5: 51789
A6: Мосмарт | B6: 49580
A7: Спар | B7: 48746
A8: Верный | B8: 47028
A9: Городской Супермаркет | B9: 43098
A10: Ароматный Мир | B10: 42837
A11: Седьмой Континент | B11: 41106
A12: Бристоль | B12: 41010
A13: Мираторг | B13: 40029
A14: Метро | B14: 39168
A15: Лента | B15: 38312
... A24: Общий итог | B24: 800433
D25: По сумме продаж лидирует O'Key, отстает Билла

Sheet Подробности2
A1: Сведения о Среднее по полю средняя стоимость в категории по поставщику. - Выгода для клиента внутри поставщика.: -0.991794471036436
A3: id чека | B3: id товара | C3: цена за шт в рублях | D3: кол-во штук в чеке | E3: сумма чека | F3: дата создания чека | G3: магазин покупки | H3: id клиента | I3: Категория товара | J3: Поставщик | K3: Средняя цена в категории за штуку | L3: Выгода клиента | M3: средняя стоимость в категории по поставщику. | N3: Выгода для клиента внутри поставщика.
A4: 682 | B4: 110 | C4: 84 | D4: 5 | E4: 420 | F4: 45029 | G4: Карусель | H4: 225 | I4: Макароны | J4: Паста Зара | K4: 265.47674 | L4: -0.6835881 | M4: 10237 | N4: -0.99179447

Sheet Средн. стоим в кат по поставщ. 
A1: Категория товара | B1: (Все)
A3: Названия строк | B3: Среднее по полю средняя стоимость в категории по поставщику.
A4: Estrella | B4: 2929
A5: Green Garden | B5: 1846
A6: Greenfield | B6: 6412
A7: Hochland | B7: 504
A8: Jacobs | B8: 5248
A9: Lay's | B9: 2244
A10: Lipton | B10: 4943
A11: Nescafe | B11: 2569
A12: President | B12: 3935
A13: Pringles | B13: 5885
A14: Rich | B14: 1089
A15: Tchibo | B15: 420
... A26: Борилла | B26: 6852
A27: Вимм-Билль-Данн | B27: 387 | C27: Максимальная цена макарон в ПастаЗара
A28: Гавриш | B28: 2229
A29: Дарница | B29: 1848
A30: Добрый | B30: 2671
A31: Домик в деревне | B31: 4946
A32: Дымов | B32: 2814
A33: Зеленая грядка | B33: 796
A34: Илецкая | B34: 4287
A35: Каравай | B35: 3974
A36: Карат | B36: 2802
A37: КДВ | B37: 4200
A38: Красный Октябрь | B38: 2189
A39: Макфа | B39: 3622
... A82: Общий итог | B82: 4445.66

Sheet Выгода для клиента внутри поста
A1: Категория товара | B1: (Все)
A3: Названия строк | B3: Среднее по полю Выгода для клиента внутри поставщика.
A4: Микоян | B4: 0
A5: Вимм-Билль-Данн | B5: -0.5
A6: Русское море | B6: -0.66666667
A7: Hochland | B7: -0.66666667
A8: Tchibo | B8: -0.66666667
A9: Черкизово | B9: -0.75
A10: Националь | B10: -0.75
A11: Rich | B11: -0.75
A12: Тесс | B12: -0.75
A13: Green Garden | B13: -0.8
A14: Зеленая грядка | B14: -0.8
A15: Активиа | B15: -0.83333333
... A82: Общий итог | B82: -0.92

Sheet Суммарные продажи по поставщика
A3: Названия строк | B3: Сумма по полю сумма чека
A4: Паста Зара | B4: 29430
A5: Фруктовый сад | B5: 24872
A6: Сырная долина | B6: 24200
A7: Greenfield | B7: 21191
A8: Бабаевский | B8: 20462
A9: Борилла | B9: 20345
A10: Домик в деревне | B10: 18739
A11: Pringles | B11: 18368
A12: Белый Злат | B12: 17471
A13: Рот Фронт | B13: 16874
A14: Jacobs | B14: 15751
A15: Овощной ряд | B15: 15581
... A21: Русский сахар | B21: 13106
A22: Хлебный Дом | B22: 13056 | E22: Лидирует Паста Зара, отстает Вим БильДан
A23: Мираторг | B23: 12899
A24: Эрманн | B24: 12851
A25: Илецкая | B25: 12813
A26: Русский Хлеб | B26: 12712
A27: Белогорье | B27: 12474
A28: Сладов | B28: 12078
A29: Экстра | B29: 11937
A30: President | B30: 11845
A31: Беллакт | B31: 11630
A32: Экзотик | B32: 11100
A33: Салта | B33: 10813
A34: Простоквашино | B34: 10714
... A82: Общий итог | B82: 800433

Sheet Подробности3
A1: Сведения о Среднее по полю кол-во штук в чеке - Категория товара: Йогурт
A3: id чека | B3: id товара | C3: цена за шт в рублях | D3: кол-во штук в чеке | E3: сумма чека | F3: дата создания чека | G3: магазин покупки | H3: id клиента | I3: Категория товара | J3: Поставщик | K3: Средняя цена в категории за штуку | L3: Выгода клиента | M3: средняя стоимость в категории по поставщику. | N3: Выгода для клиента внутри поставщика.
A4: 984 | B4: 404 | C4: 304 | D4: 5 | E4: 1520 | F4: 45288 | G4: Верный | H4: 17 | I4: Йогурт | J4: Ростагроэкспорт | K4: 263.25424 | L4: 0.15477723 | M4: 5929 | N4: -0.9487266
A5: 964 | B5: 448 | C5: 484 | D5: 1 | E5: 484 | F5: 45301 | G5: Городской Супермаркет | H5: 404 | I5: Йогурт | J5: Ростагроэкспорт | K5: 263.25424 | L5: 0.83852691 | M5: 5929 | N5: -0.91836735
A6: 943 | B6: 447 | C6: 118 | D6: 3 | E6: 354 | F6: 45337 | G6: Перекресток | H6: 9 | I6: Йогурт | J6: Эрманн | K6: 263.25424 | L6: -0.5517641 | M6: 4970 | N6: -0.97625755
A7: 935 | B7: 9 | C7: 321 | D7: 1 | E7: 321 | F7: 45173 | G7: Ароматный Мир | H7: 217 | I7: Йогурт | J7: Чудо | K7: 263.25424 | L7: 0.21935359 | M7: 2871 | N7: -0.88819227
A8: 925 | B8: 46 | C8: 290 | D8: 3 | E8: 870 | F8: 45059 | G8: Карусель | H8: 460 | I8: Йогурт | J8: Активиа | K8: 263.25424 | L8: 0.1015967 | M8: 1762 | N8: -0.8354143
A9: 923 | B9: 465 | C9: 71 | D9: 5 | E9: 355 | F9: 45253 | G9: Перекресток | H9: 321 | I9: Йогурт | J9: Ростагроэкспорт | K9: 263.25424 | L9: -0.73029874 | M9: 5929 | N9: -0.98802496
A10: 913 | B10: 465 | C10: 177 | D10: 1 | E10: 177 | F10: 45122 | G10: Перекресток | H10: 167 | I10: Йогурт | J10: Ростагроэкспорт | K10: 263.25424 | L10: -0.32764615 | M10: 5929 | N10: -0.97014674
A11: 902 | B11: 444 | C11: 328 | D11: 3 | E11: 984 | F11: 45102 | G11: Азбука Вкуса | H11: 292 | I11: Йогурт | J11: Эрманн | K11: 263.25424 | L11: 0.24594386 | M11: 4970 | N11: -0.93400402
A12: 855 | B12: 239 | C12: 397 | D12: 2 | E12: 794 | F12: 45398 | G12: Мираторг | H12: 65 | I12: Йогурт | J12: Эрманн | K12: 263.25424 | L12: 0.5080479 | M12: 4970 | N12: -0.92012072
A13: 10 | B13: 100 | C13: 449 | D13: 2 | E13: 898 | F13: 45032 | G13: Карусель | H13: 413 | I13: Йогурт | J13: Ростагроэкспорт | K13: 263.25424 | L13: 0.70557559 | M13: 5929 | N13: -0.92427053
A14: 848 | B14: 319 | C14: 193 | D14: 1 | E14: 193 | F14: 45396 | G14: Мосмарт | H14: 43 | I14: Йогурт | J14: Эрманн | K14: 263.25424 | L14: -0.2668684 | M14: 4970 | N14: -0.961167
A15: 837 | B15: 104 | C15: 420 | D15: 2 | E15: 840 | F15: 45427 | G15: Городской Супермаркет | H15: 26 | I15: Йогурт | J15: Ростагроэкспорт | K15: 263.25424 | L15: 0.59541592 | M15: 5929 | N15: -0.92916175
... A62: 62 | B62: 465 | C62: 311 | D62: 2 | E62: 622 | F62: 44934 | G62: Дикси | H62: 14 | I62: Йогурт | J62: Ростагроэкспорт | K62: 263.25424 | L62: 0.1813675 | M62: 5929 | N62: -0.94754596

Sheet Средн_кол-во_штук_в_чеке_по_кат
A3: Названия строк | B3: Среднее по полю кол-во штук в чеке
A4: Йогурт | B4: 2.7627119
A5: Колбаса | B5: 2.8846154
A6: Конфеты | B6: 2.983871
A7: Кофе | B7: 3.047619
A8: Крупа | B8: 2.7209302
A9: Макароны | B9: 2.9418605
A10: Молоко | B10: 3.2380952
A11: Мясо | B11: 3.1272727
A12: Овощи | B12: 3.1463415
A13: Печенье | B13: 3.0638298
A14: Рис | B14: 3.1875
A15: Рыба | B15: 3.1282051
... A20: Фрукты | B20: 2.9534884
A21: Хлеб | B21: 3.0909091 | F21: В чеке в среднем 3 штуки в каждой категории
A22: Чай | B22: 2.9272727
A23: Чипсы | B23: 3.0588235
A24: Общий итог | B24: 2.99

Sheet продажи по категориям
A3: Названия строк | B3: Сумма по полю сумма чека
A4: Макароны | B4: 66945
A5: Конфеты | B5: 48797
A6: Мясо | B6: 47223
A7: Сок | B7: 45862
A8: Чипсы | B8: 44539
A9: Сахар | B9: 44513
A10: Соль | B10: 44468
A11: Сыр | B11: 43903
A12: Чай | B12: 43626
A13: Хлеб | B13: 42352
A14: Молоко | B14: 42165
A15: Йогурт | B15: 41745
... A21: Крупа | B21: 28053
A22: Рис | B22: 27375 | D22: Лидируют макароны и конфты, отстает колбаса
A23: Колбаса | B23: 21313
A24: Общий итог | B24: 800433

Sheet Платежеспособность по странам
A3: Названия строк | B3: Сумма по полю сумма чека
A4: Россия | B4: 251330
A5: Узбекистан | B5: 163294
A6: Украина | B6: 147543
A7: Таджикистан | B7: 139473
A8: Беларусь | B8: 98793
A9: Общий итог | B9: 800433
D20: Россия показывает наибольшую платежжеспособность
D21: Белорус - наименьшую

Sheet Кол-во дней с момента регистр

Sheet Лайфтайм клиента

Sheet продажи
A1: id чека | B1: id товара | C1: цена за шт в рублях | D1: кол-во штук в чеке | E1: сумма чека | F1: дата создания чека | G1: магазин покупки | H1: id клиента | I1: Категория товара | J1: Поставщик | K1: Средняя цена в категории за штуку | L1: Выгода клиента | M1: средняя стоимость в категории по поставщику. | N1: Выгода для клиента внутри поставщика. | O1: Дата регистрации клента | P1: Кол-во дней с момента регистрации | Q1: Текущая дата | R1: Лайфтайм клиента | S1: Страна | T1: Столбец2
A2: 1 | B2: 300 | C2: 103 | D2: 4 | E2: 412 | F2: 45187 | G2: Бристоль | H2: 315 | I2: =VLOOKUP(продажи!$B2,товар!$A$1:$C$433,2) -> Сахар | J2: =VLOOKUP(B2,товар!$A$1:$C$433,3) -> Продимекс | K2: =AVERAGEIF(продажи!$I$2:$I$1001,продажи!$I$2:$I$1001,продажи!$C$2:$C$1001) -> 254.58333 | L2: =продажи!$C2/продажи!$K2-1 -> -0.59541735 | M2: =SUMIFS($C$2:$C$1001,$I$2:$I$1001,I2,$J$2:$J$1001,J2) -> 5172 | N2: =Таблица1[[#This Row],[цена за шт в рублях]]/Таблица1[[#This Row],[средняя стоимость в категории по поставщику.]]-1 -> -0.98008507 | O2: =VLOOKUP(Таблица1[[#This Row],[id клиента]],клиенты!$A$2:$E$435,5,0) -> 44747 | P2: =Таблица1[[#This Row],[дата создания чека]]-Таблица1[[#This Row],[Дата регистрации клента]] -> 440 | Q2: =TODAY() -> 46059 | R2: =(TODAY()-Таблица1[[#This Row],[Дата регистрации клента]])/30 -> 43.733333 | S2: =VLOOKUP(Таблица1[[#This Row],[id клиента]],Таблица8[[id клиента]:[Страна]],7,0) -> Узбекистан
A3: 2 | B3: 486 | C3: 296 | D3: 3 | E3: 888 | F3: 45083 | G3: Дикси | H3: 253 | I3: =VLOOKUP(продажи!$B3,товар!$A$1:$C$433,2) -> Соль | J3: =VLOOKUP(B3,товар!$A$1:$C$433,3) -> Илецкая | K3: =AVERAGEIF(продажи!$I$2:$I$1001,продажи!$I$2:$I$1001,продажи!$C$2:$C$1001) -> 264.86792 | L3: =продажи!$C3/продажи!$K3-1 -> 0.11753811 | M3: =SUMIFS($C$2:$C$1001,$I$2:$I$1001,I3,$J$2:$J$1001,J3) -> 4287 | N3: =Таблица1[[#This Row],[цена за шт в рублях]]/Таблица1[[#This Row],[средняя стоимость в категории по поставщику.]]-1 -> -0.93095405 | O3: =VLOOKUP(Таблица1[[#This Row],[id клиента]],клиенты!$A$2:$E$435,5,0) -> 44750 | P3: =Таблица1[[#This Row],[дата создания чека]]-Таблица1[[#This Row],[Дата регистрации клента]] -> 333 | Q3: =TODAY() -> 46059 | R3: =(TODAY()-Таблица1[[#This Row],[Дата регистрации клента]])/30 -> 43.633333 | S3: =VLOOKUP(Таблица1[[#This Row],[id клиента]],Таблица8[[id клиента]:[Страна]],7,0) -> Беларусь
A4: 3 | B4: 76 | C4: 139 | D4: 5 | E4: 695 | F4: 45363 | G4: Городской Супермаркет | H4: 12 | I4: =VLOOKUP(продажи!$B4,товар!$A$1:$C$433,2) -> Печенье | J4: =VLOOKUP(B4,товар!$A$1:$C$433,3) -> Юбилейное | K4: =AVERAGEIF(продажи!$I$2:$I$1001,продажи!$I$2:$I$1001,продажи!$C$2:$C$1001) -> 283.46809 | L4: =продажи!$C4/продажи!$K4-1 -> -0.50964497 | M4: =SUMIFS($C$2:$C$1001,$I$2:$I$1001,I4,$J$2:$J$1001,J4) -> 2092 | N4: =Таблица1[[#This Row],[цена за шт в рублях]]/Таблица1[[#This Row],[средняя стоимость в категории по поставщику.]]-1 -> -0.93355641 | O4: =VLOOKUP(Таблица1[[#This Row],[id клиента]],клиенты!$A$2:$E$435,5,0) -> 44842 | P4: =Таблица1[[#This Row],[дата создания чека]]-Таблица1[[#This Row],[Дата регистрации клента]] -> 521 | Q4: =TODAY() -> 46059 | R4: =(TODAY()-Таблица1[[#This Row],[Дата регистрации клента]])/30 -> 40.566667 | S4: =VLOOKUP(Таблица1[[#This Row],[id клиента]],Таблица8[[id клиента]:[Страна]],7,0) -> Беларусь
A5: 4 | B5: 240 | C5: 141 | D5: 5 | E5: 705 | F5: 45262 | G5: Верный | H5: 116 | I5: =VLOOKUP(продажи!$B5,товар!$A$1:$C$433,2) -> Макароны | J5: =VLOOKUP(B5,товар!$A$1:$C$433,3) -> Борилла | K5: =AVERAGEIF(продажи!$I$2:$I$1001,продажи!$I$2:$I$1001,продажи!$C$2:$C$1001) -> 265.47674 | L5: =продажи!$C5/продажи!$K5-1 -> -0.46888003 | M5: =SUMIFS($C$2:$C$1001,$I$2:$I$1001,I5,$J$2:$J$1001,J5) -> 6852 | N5: =Таблица1[[#This Row],[цена за шт в рублях]]/Таблица1[[#This Row],[средняя стоимость в категории по поставщику.]]-1 -> -0.97942207 | O5: =VLOOKUP(Таблица1[[#This Row],[id клиента]],клиенты!$A$2:$E$435,5,0) -> 44643 | P5: =Таблица1[[#This Row],[дата создания чека]]-Таблица1[[#This Row],[Дата регистрации клента]] -> 619 | Q5: =TODAY() -> 46059 | R5: =(TODAY()-Таблица1[[#This Row],[Дата регистрации клента]])/30 -> 47.2 | S5: =VLOOKUP(Таблица1[[#This Row],[id клиента]],Таблица8[[id клиента]:[Страна]],7,0) -> Россия
A6: 5 | B6: 32 | C6: 123 | D6: 2 | E6: 246 | F6: 45151 | G6: Спар | H6: 471 | I6: =VLOOKUP(продажи!$B6,товар!$A$1:$C$433,2) -> Овощи | J6: =VLOOKUP(B6,товар!$A$1:$C$433,3) -> Зеленая грядка | K6: =AVERAGEIF(продажи!$I$2:$I$1001,продажи!$I$2:$I$1001,продажи!$C$2:$C$1001) -> 250.4878 | L6: =продажи!$C6/продажи!$K6-1 -> -0.50895813 | M6: =SUMIFS($C$2:$C$1001,$I$2:$I$1001,I6,$J$2:$J$1001,J6) -> 796 | N6: =Таблица1[[#This Row],[цена за шт в рублях]]/Таблица1[[#This Row],[средняя стоимость в категории по поставщику.]]-1 -> -0.84547739 | O6: =VLOOKUP(Таблица1[[#This Row],[id клиента]],клиенты!$A$2:$E$435,5,0) -> 44577 | P6: =Таблица1[[#This Row],[дата создания чека]]-Таблица1[[#This Row],[Дата регистрации клента]] -> 574 | Q6: =TODAY() -> 46059 | R6: =(TODAY()-Таблица1[[#This Row],[Дата регистрации клента]])/30 -> 49.4 | S6: =VLOOKUP(Таблица1[[#This Row],[id клиента]],Таблица8[[id клиента]:[Страна]],7,0) -> Украина
A7: 6 | B7: 162 | C7: 452 | D7: 2 | E7: 904 | F7: 45281 | G7: Бристоль | H7: 374 | I7: =VLOOKUP(продажи!$B7,товар!$A$1:$C$433,2) -> Сок | J7: =VLOOKUP(B7,товар!$A$1:$C$433,3) -> Фруктовый сад | K7: =AVERAGEIF(продажи!$I$2:$I$1001,продажи!$I$2:$I$1001,продажи!$C$2:$C$1001) -> 268.60345 | L7: =продажи!$C7/продажи!$K7-1 -> 0.6827781 | M7: =SUMIFS($C$2:$C$1001,$I$2:$I$1001,I7,$J$2:$J$1001,J7) -> 9023 | N7: =Таблица1[[#This Row],[цена за шт в рублях]]/Таблица1[[#This Row],[средняя стоимость в категории по поставщику.]]-1 -> -0.9499058 | O7: =VLOOKUP(Таблица1[[#This Row],[id клиента]],клиенты!$A$2:$E$435,5,0) -> 44582 | P7: =Таблица1[[#This Row],[дата создания чека]]-Таблица1[[#This Row],[Дата регистрации клента]] -> 699 | Q7: =TODAY() -> 46059 | R7: =(TODAY()-Таблица1[[#This Row],[Дата регистрации клента]])/30 -> 49.233333 | S7: =VLOOKUP(Таблица1[[#This Row],[id клиента]],Таблица8[[id клиента]:[Страна]],7,0) -> Украина
A8: 7 | B8: 323 | C8: 149 | D8: 5 | E8: 745 | F8: 45349 | G8: Карусель | H8: 477 | I8: =VLOOKUP(продажи!$B8,товар!$A$1:$C$433,2) -> Рыба | J8: =VLOOKUP(B8,товар!$A$1:$C$433,3) -> Меридиан | K8: =AVERAGEIF(продажи!$I$2:$I$1001,продажи!$I$2:$I$1001,продажи!$C$2:$C$1001) -> 258.51282 | L8: =продажи!$C8/продажи!$K8-1 -> -0.42362626 | M8: =SUMIFS($C$2:$C$1001,$I$2:$I$1001,I8,$J$2:$J$1001,J8) -> 4431 | N8: =Таблица1[[#This Row],[цена за шт в рублях]]/Таблица1[[#This Row],[средняя стоимость в категории по поставщику.]]-1 -> -0.96637328 | O8: =VLOOKUP(Таблица1[[#This Row],[id клиента]],клиенты!$A$2:$E$435,5,0) -> 44738 | P8: =Таблица1[[#This Row],[дата создания чека]]-Таблица1[[#This Row],[Дата регистрации клента]] -> 611 | Q8: =TODAY() -> 46059 | R8: =(TODAY()-Таблица1[[#This Row],[Дата регистрации клента]])/30 -> 44.033333 | S8: =VLOOKUP(Таблица1[[#This Row],[id клиента]],Таблица8[[id клиента]:[Страна]],7,0) -> Узбекистан
A9: 8 | B9: 60 | C9: 489 | D9: 4 | E9: 1956 | F9: 45327 | G9: Мираторг | H9: 335 | I9: =VLOOKUP(продажи!$B9,товар!$A$1:$C$433,2) -> Кофе | J9: =VLOOKUP(B9,товар!$A$1:$C$433,3) -> Jacobs | K9: =AVERAGEIF(продажи!$I$2:$I$1001,продажи!$I$2:$I$1001,продажи!$C$2:$C$1001) -> 249.02381 | L9: =продажи!$C9/продажи!$K9-1 -> 0.96366765 | M9: =SUMIFS($C$2:$C$1001,$I$2:$I$1001,I9,$J$2:$J$1001,J9) -> 5248 | N9: =Таблица1[[#This Row],[цена за шт в рублях]]/Таблица1[[#This Row],[средняя стоимость в категории по поставщику.]]-1 -> -0.90682165 | O9: =VLOOKUP(Таблица1[[#This Row],[id клиента]],клиенты!$A$2:$E$435,5,0) -> 44619 | P9: =Таблица1[[#This Row],[дата создания чека]]-Таблица1[[#This Row],[Дата регистрации клента]] -> 708 | Q9: =TODAY() -> 46059 | R9: =(TODAY()-Таблица1[[#This Row],[Дата регистрации клента]])/30 -> 48 | S9: =VLOOKUP(Таблица1[[#This Row],[id клиента]],Таблица8[[id клиента]:[Страна]],7,0) -> Узбекистан
A10: 9 | B10: 401 | C10: 416 | D10: 5 | E10: 2080 | F10: 45376 | G10: Мосмарт | H10: 350 | I10: =VLOOKUP(продажи!$B10,товар!$A$1:$C$433,2) -> Чай | J10: =VLOOKUP(B10,товар!$A$1:$C$433,3) -> Greenfield | K10: =AVERAGEIF(продажи!$I$2:$I$1001,продажи!$I$2:$I$1001,продажи!$C$2:$C$1001) -> 271.18182 | L10: =продажи!$C10/продажи!$K10-1 -> 0.53402615 | M10: =SUMIFS($C$2:$C$1001,$I$2:$I$1001,I10,$J$2:$J$1001,J10) -> 6412 | N10: =Таблица1[[#This Row],[цена за шт в рублях]]/Таблица1[[#This Row],[средняя стоимость в категории по поставщику.]]-1 -> -0.93512165 | O10: =VLOOKUP(Таблица1[[#This Row],[id клиента]],клиенты!$A$2:$E$435,5,0) -> 44684 | P10: =Таблица1[[#This Row],[дата создания чека]]-Таблица1[[#This Row],[Дата регистрации клента]] -> 692 | Q10: =TODAY() -> 46059 | R10: =(TODAY()-Таблица1[[#This Row],[Дата регистрации клента]])/30 -> 45.833333 | S10: =VLOOKUP(Таблица1[[#This Row],[id клиента]],Таблица8[[id клиента]:[Страна]],7,0) -> Украина
A11: 10 | B11: 100 | C11: 449 | D11: 2 | E11: 898 | F11: 45032 | G11: Карусель | H11: 413 | I11: =VLOOKUP(продажи!$B11,товар!$A$1:$C$433,2) -> Йогурт | J11: =VLOOKUP(B11,товар!$A$1:$C$433,3) -> Ростагроэкспорт | K11: =AVERAGEIF(продажи!$I$2:$I$1001,продажи!$I$2:$I$1001,продажи!$C$2:$C$1001) -> 263.25424 | L11: =продажи!$C11/продажи!$K11-1 -> 0.70557559 | M11: =SUMIFS($C$2:$C$1001,$I$2:$I$1001,I11,$J$2:$J$1001,J11) -> 5929 | N11: =Таблица1[[#This Row],[цена за шт в рублях]]/Таблица1[[#This Row],[средняя стоимость в категории по поставщику.]]-1 -> -0.92427053 | O11: =VLOOKUP(Таблица1[[#This Row],[id клиента]],клиенты!$A$2:$E$435,5,0) -> 44699 | P11: =Таблица1[[#This Row],[дата создания чека]]-Таблица1[[#This Row],[Дата регистрации клента]] -> 333 | Q11: =TODAY() -> 46059 | R11: =(TODAY()-Таблица1[[#This Row],[Дата регистрации клента]])/30 -> 45.333333 | S11: =VLOOKUP(Таблица1[[#This Row],[id клиента]],Таблица8[[id клиента]:[Страна]],7,0) -> Россия
A12: 11 | B12: 217 | C12: 296 | D12: 2 | E12: 592 | F12: 45136 | G12: Карусель | H12: 495 | I12: =VLOOKUP(продажи!$B12,товар!$A$1:$C$433,2) -> Мясо | J12: =VLOOKUP(B12,товар!$A$1:$C$433,3) -> Агрокомплекс | K12: =AVERAGEIF(продажи!$I$2:$I$1001,продажи!$I$2:$I$1001,продажи!$C$2:$C$1001) -> 271.74545 | L12: =продажи!$C12/продажи!$K12-1 -> 0.08925465 | M12: =SUMIFS($C$2:$C$1001,$I$2:$I$1001,I12,$J$2:$J$1001,J12) -> 3112 | N12: =Таблица1[[#This Row],[цена за шт в рублях]]/Таблица1[[#This Row],[средняя стоимость в категории по поставщику.]]-1 -> -0.90488432 | O12: =VLOOKUP(Таблица1[[#This Row],[id клиента]],клиенты!$A$2:$E$435,5,0) -> 44654 | P12: =Таблица1[[#This Row],[дата создания чека]]-Таблица1[[#This Row],[Дата регистрации клента]] -> 482 | Q12: =TODAY() -> 46059 | R12: =(TODAY()-Таблица1[[#This Row],[Дата регистрации клента]])/30 -> 46.833333 | S12: =VLOOKUP(Таблица1[[#This Row],[id клиента]],Таблица8[[id клиента]:[Страна]],7,0) -> Узбекистан
A13: 12 | B13: 445 | C13: 109 | D13: 5 | E13: 545 | F13: 45394 | G13: Мираторг | H13: 353 | I13: =VLOOKUP(продажи!$B13,товар!$A$1:$C$433,2) -> Сахар | J13: =VLOOKUP(B13,товар!$A$1:$C$433,3) -> Сладов | K13: =AVERAGEIF(продажи!$I$2:$I$1001,продажи!$I$2:$I$1001,продажи!$C$2:$C$1001) -> 254.58333 | L13: =продажи!$C13/продажи!$K13-1 -> -0.57184943 | M13: =SUMIFS($C$2:$C$1001,$I$2:$I$1001,I13,$J$2:$J$1001,J13) -> 3604 | N13: =Таблица1[[#This Row],[цена за шт в рублях]]/Таблица1[[#This Row],[средняя стоимость в категории по поставщику.]]-1 -> -0.96975583 | O13: =VLOOKUP(Таблица1[[#This Row],[id клиента]],клиенты!$A$2:$E$435,5,0) -> 44656 | P13: =Таблица1[[#This Row],[дата создания чека]]-Таблица1[[#This Row],[Дата регистрации клента]] -> 738 | Q13: =TODAY() -> 46059 | R13: =(TODAY()-Таблица1[[#This Row],[Дата регистрации клента]])/30 -> 46.766667 | S13: =VLOOKUP(Таблица1[[#This Row],[id клиента]],Таблица8[[id клиента]:[Страна]],7,0) -> Таджикистан
... A25: 24 | B25: 451 | C25: 161 | D25: 4 | E25: 644 | F25: 44966 | G25: Мосмарт | H25: 39 | I25: =VLOOKUP(продажи!$B25,товар!$A$1:$C$433,2) -> Рис | J25: =VLOOKUP(B25,товар!$A$1:$C$433,3) -> Белый Злат | K25: =AVERAGEIF(продажи!$I$2:$I$1001,продажи!$I$2:$I$1001,продажи!$C$2:$C$1001) -> 258.375 | L25: =продажи!$C25/продажи!$K25-1 -> -0.3768747 | M25: =SUMIFS($C$2:$C$1001,$I$2:$I$1001,I25,$J$2:$J$1001,J25) -> 4585 | N25: =Таблица1[[#This Row],[цена за шт в рублях]]/Таблица1[[#This Row],[средняя стоимость в категории по поставщику.]]-1 -> -0.9648855 | O25: =VLOOKUP(Таблица1[[#This Row],[id клиента]],клиенты!$A$2:$E$435,5,0) -> 44653 | P25: =Таблица1[[#This Row],[дата создания чека]]-Таблица1[[#This Row],[Дата регистрации клента]] -> 313 | Q25: =TODAY() -> 46059 | R25: =(TODAY()-Таблица1[[#This Row],[Дата регистрации клента]])/30 -> 46.866667 | S25: =VLOOKUP(Таблица1[[#This Row],[id клиента]],Таблица8[[id клиента]:[Страна]],7,0) -> Беларусь
A26: 25 | B26: 7 | C26: 362 | D26: 1 | E26: 362 | F26: 45326 | G26: Спар | H26: 303 | I26: =VLOOKUP(B2,товар!$A$1:$C$433,2) -> Сахар | J26: =VLOOKUP(B2,товар!$A$1:$C$433,3) -> Продимекс | K26: =AVERAGEIF(продажи!$I$2:$I$1001,продажи!$I$2:$I$1001,продажи!$C$2:$C$1001) -> 254.58333 | L26: =продажи!$C26/продажи!$K26-1 -> 0.42193126 | M26: =SUMIFS($C$2:$C$1001,$I$2:$I$1001,I26,$J$2:$J$1001,J26) -> 5172 | N26: =Таблица1[[#This Row],[цена за шт в рублях]]/Таблица1[[#This Row],[средняя стоимость в категории по поставщику.]]-1 -> -0.93000773 | O26: =VLOOKUP(Таблица1[[#This Row],[id клиента]],клиенты!$A$2:$E$435,5,0) -> 44689 | P26: =Таблица1[[#This Row],[дата создания чека]]-Таблица1[[#This Row],[Дата регистрации клента]] -> 637 | Q26: =TODAY() -> 46059 | R26: =(TODAY()-Таблица1[[#This Row],[Дата регистрации клента]])/30 -> 45.666667 | S26: =VLOOKUP(Таблица1[[#This Row],[id клиента]],Таблица8[[id клиента]:[Страна]],7,0) -> Узбекистан
A27: 26 | B27: 495 | C27: 312 | D27: 1 | E27: 312 | F27: 45174 | G27: Перекресток | H27: 422 | I27: =VLOOKUP(продажи!$B27,товар!$A$1:$C$433,2) -> Чай | J27: =VLOOKUP(B27,товар!$A$1:$C$433,3) -> Greenfield | K27: =AVERAGEIF(продажи!$I$2:$I$1001,продажи!$I$2:$I$1001,продажи!$C$2:$C$1001) -> 271.18182 | L27: =продажи!$C27/продажи!$K27-1 -> 0.15051961 | M27: =SUMIFS($C$2:$C$1001,$I$2:$I$1001,I27,$J$2:$J$1001,J27) -> 6412 | N27: =Таблица1[[#This Row],[цена за шт в рублях]]/Таблица1[[#This Row],[средняя стоимость в категории по поставщику.]]-1 -> -0.95134124 | O27: =VLOOKUP(Таблица1[[#This Row],[id клиента]],клиенты!$A$2:$E$435,5,0) -> 44784 | P27: =Таблица1[[#This Row],[дата создания чека]]-Таблица1[[#This Row],[Дата регистрации клента]] -> 390 | Q27: =TODAY() -> 46059 | R27: =(TODAY()-Таблица1[[#This Row],[Дата регистрации клента]])/30 -> 42.5 | S27: =VLOOKUP(Таблица1[[#This Row],[id клиента]],Таблица8[[id клиента]:[Страна]],7,0) -> Украина
A28: 27 | B28: 415 | C28: 311 | D28: 5 | E28: 1555 | F28: 45099 | G28: Метро | H28: 24 | I28: =VLOOKUP(продажи!$B28,товар!$A$1:$C$433,2) -> Чипсы | J28: =VLOOKUP(B28,товар!$A$1:$C$433,3) -> Pringles | K28: =AVERAGEIF(продажи!$I$2:$I$1001,продажи!$I$2:$I$1001,продажи!$C$2:$C$1001) -> 273.72549 | L28: =продажи!$C28/продажи!$K28-1 -> 0.13617479 | M28: =SUMIFS($C$2:$C$1001,$I$2:$I$1001,I28,$J$2:$J$1001,J28) -> 5885 | N28: =Таблица1[[#This Row],[цена за шт в рублях]]/Таблица1[[#This Row],[средняя стоимость в категории по поставщику.]]-1 -> -0.94715378 | O28: =VLOOKUP(Таблица1[[#This Row],[id клиента]],клиенты!$A$2:$E$435,5,0) -> 44609 | P28: =Таблица1[[#This Row],[дата создания чека]]-Таблица1[[#This Row],[Дата регистрации клента]] -> 490 | Q28: =TODAY() -> 46059 | R28: =(TODAY()-Таблица1[[#This Row],[Дата регистрации клента]])/30 -> 48.333333 | S28: =VLOOKUP(Таблица1[[#This Row],[id клиента]],Таблица8[[id клиента]:[Страна]],7,0) -> Узбекистан
A29: 28 | B29: 176 | C29: 220 | D29: 1 | E29: 220 | F29: 45368 | G29: Бристоль | H29: 112 | I29: =VLOOKUP(продажи!$B29,товар!$A$1:$C$433,2) -> Сахар | J29: =VLOOKUP(B29,товар!$A$1:$C$433,3) -> Продимекс | K29: =AVERAGEIF(продажи!$I$2:$I$1001,продажи!$I$2:$I$1001,продажи!$C$2:$C$1001) -> 254.58333 | L29: =продажи!$C29/продажи!$K29-1 -> -0.13584288 | M29: =SUMIFS($C$2:$C$1001,$I$2:$I$1001,I29,$J$2:$J$1001,J29) -> 5172 | N29: =Таблица1[[#This Row],[цена за шт в рублях]]/Таблица1[[#This Row],[средняя стоимость в категории по поставщику.]]-1 -> -0.95746326 | O29: =VLOOKUP(Таблица1[[#This Row],[id клиента]],клиенты!$A$2:$E$435,5,0) -> 44652 | P29: =Таблица1[[#This Row],[дата создания чека]]-Таблица1[[#This Row],[Дата регистрации клента]] -> 716 | Q29: =TODAY() -> 46059 | R29: =(TODAY()-Таблица1[[#This Row],[Дата регистрации клента]])/30 -> 46.9 | S29: =VLOOKUP(Таблица1[[#This Row],[id клиента]],Таблица8[[id клиента]:[Страна]],7,0) -> Россия
A30: 845 | B30: 474 | C30: 405 | D30: 2 | E30: 810 | F30: 45390 | G30: Перекресток | H30: 18 | I30: =VLOOKUP(продажи!$B846,товар!$A$1:$C$433,2) -> Молоко | J30: =VLOOKUP(B30,товар!$A$1:$C$433,3) -> Простоквашино | K30: =AVERAGEIF(продажи!$I$2:$I$1001,продажи!$I$2:$I$1001,продажи!$C$2:$C$1001) -> 294.95238 | L30: =продажи!$C846/продажи!$K846-1 -> 0.48837585 | M30: =SUMIFS($C$2:$C$1001,$I$2:$I$1001,I30,$J$2:$J$1001,J30) -> 3507 | N30: =Таблица1[[#This Row],[цена за шт в рублях]]/Таблица1[[#This Row],[средняя стоимость в категории по поставщику.]]-1 -> -0.88451668 | O30: =VLOOKUP(Таблица1[[#This Row],[id клиента]],клиенты!$A$2:$E$435,5,0) -> 44578 | P30: =Таблица1[[#This Row],[дата создания чека]]-Таблица1[[#This Row],[Дата регистрации клента]] -> 812 | Q30: =TODAY() -> 46059 | R30: =(TODAY()-Таблица1[[#This Row],[Дата регистрации клента]])/30 -> 49.366667 | S30: =VLOOKUP(Таблица1[[#This Row],[id клиента]],Таблица8[[id клиента]:[Страна]],7,0) -> Украина
A31: 30 | B31: 399 | C31: 190 | D31: 1 | E31: 190 | F31: 45414 | G31: Городской Супермаркет | H31: 131 | I31: =VLOOKUP(продажи!$B31,товар!$A$1:$C$433,2) -> Хлеб | J31: =VLOOKUP(B31,товар!$A$1:$C$433,3) -> Хлебный Дом | K31: =AVERAGEIF(продажи!$I$2:$I$1001,продажи!$I$2:$I$1001,продажи!$C$2:$C$1001) -> 300.31818 | L31: =продажи!$C31/продажи!$K31-1 -> -0.36733767 | M31: =SUMIFS($C$2:$C$1001,$I$2:$I$1001,I31,$J$2:$J$1001,J31) -> 4226 | N31: =Таблица1[[#This Row],[цена за шт в рублях]]/Таблица1[[#This Row],[средняя стоимость в категории по поставщику.]]-1 -> -0.95504023 | O31: =VLOOKUP(Таблица1[[#This Row],[id клиента]],клиенты!$A$2:$E$435,5,0) -> 44693 | P31: =Таблица1[[#This Row],[дата создания чека]]-Таблица1[[#This Row],[Дата регистрации клента]] -> 721 | Q31: =TODAY() -> 46059 | R31: =(TODAY()-Таблица1[[#This Row],[Дата регистрации клента]])/30 -> 45.533333 | S31: =VLOOKUP(Таблица1[[#This Row],[id клиента]],Таблица8[[id клиента]:[Страна]],7,0) -> Россия
A32: 31 | B32: 382 | C32: 198 | D32: 5 | E32: 990 | F32: 45125 | G32: Билла | H32: 160 | I32: =VLOOKUP(продажи!$B32,товар!$A$1:$C$433,2) -> Овощи | J32: =VLOOKUP(B32,товар!$A$1:$C$433,3) -> Овощной ряд | K32: =AVERAGEIF(продажи!$I$2:$I$1001,продажи!$I$2:$I$1001,продажи!$C$2:$C$1001) -> 250.4878 | L32: =продажи!$C32/продажи!$K32-1 -> -0.20954236 | M32: =SUMIFS($C$2:$C$1001,$I$2:$I$1001,I32,$J$2:$J$1001,J32) -> 5165 | N32: =Таблица1[[#This Row],[цена за шт в рублях]]/Таблица1[[#This Row],[средняя стоимость в категории по поставщику.]]-1 -> -0.96166505 | O32: =VLOOKUP(Таблица1[[#This Row],[id клиента]],клиенты!$A$2:$E$435,5,0) -> 44649 | P32: =Таблица1[[#This Row],[дата создания чека]]-Таблица1[[#This Row],[Дата регистрации клента]] -> 476 | Q32: =TODAY() -> 46059 | R32: =(TODAY()-Таблица1[[#This Row],[Дата регистрации клента]])/30 -> 47 | S32: =VLOOKUP(Таблица1[[#This Row],[id клиента]],Таблица8[[id клиента]:[Страна]],7,0) -> Узбекистан
A33: 32 | B33: 103 | C33: 254 | D33: 3 | E33: 762 | F33: 45352 | G33: Пятерочка | H33: 408 | I33: =VLOOKUP(продажи!$B33,товар!$A$1:$C$433,2) -> Рыба | J33: =VLOOKUP(B33,товар!$A$1:$C$433,3) -> Санта Бремор | K33: =AVERAGEIF(продажи!$I$2:$I$1001,продажи!$I$2:$I$1001,продажи!$C$2:$C$1001) -> 258.51282 | L33: =продажи!$C33/продажи!$K33-1 -> -0.017456854 | M33: =SUMIFS($C$2:$C$1001,$I$2:$I$1001,I33,$J$2:$J$1001,J33) -> 2164 | N33: =Таблица1[[#This Row],[цена за шт в рублях]]/Таблица1[[#This Row],[средняя стоимость в категории по поставщику.]]-1 -> -0.88262477 | O33: =VLOOKUP(Таблица1[[#This Row],[id клиента]],клиенты!$A$2:$E$435,5,0) -> 44857 | P33: =Таблица1[[#This Row],[дата создания чека]]-Таблица1[[#This Row],[Дата регистрации клента]] -> 495 | Q33: =TODAY() -> 46059 | R33: =(TODAY()-Таблица1[[#This Row],[Дата регистрации клента]])/30 -> 40.066667 | S33: =VLOOKUP(Таблица1[[#This Row],[id клиента]],Таблица8[[id клиента]:[Страна]],7,0) -> Россия
A34: 33 | B34: 104 | C34: 351 | D34: 1 | E34: 351 | F34: 44997 | G34: Билла | H34: 324 | I34: =VLOOKUP(продажи!$B34,товар!$A$1:$C$433,2) -> Йогурт | J34: =VLOOKUP(B34,товар!$A$1:$C$433,3) -> Ростагроэкспорт | K34: =AVERAGEIF(продажи!$I$2:$I$1001,продажи!$I$2:$I$1001,продажи!$C$2:$C$1001) -> 263.25424 | L34: =продажи!$C34/продажи!$K34-1 -> 0.33331187 | M34: =SUMIFS($C$2:$C$1001,$I$2:$I$1001,I34,$J$2:$J$1001,J34) -> 5929 | N34: =Таблица1[[#This Row],[цена за шт в рублях]]/Таблица1[[#This Row],[средняя стоимость в категории по поставщику.]]-1 -> -0.94079946 | O34: =VLOOKUP(Таблица1[[#This Row],[id клиента]],клиенты!$A$2:$E$435,5,0) -> 44761 | P34: =Таблица1[[#This Row],[дата создания чека]]-Таблица1[[#This Row],[Дата регистрации клента]] -> 236 | Q34: =TODAY() -> 46059 | R34: =(TODAY()-Таблица1[[#This Row],[Дата регистрации клента]])/30 -> 43.266667 | S34: =VLOOKUP(Таблица1[[#This Row],[id клиента]],Таблица8[[id клиента]:[Страна]],7,0) -> Узбекистан
A35: 34 | B35: 213 | C35: 387 | D35: 1 | E35: 387 | F35: 45267 | G35: Карусель | H35: 310 | I35: =VLOOKUP(продажи!$B35,товар!$A$1:$C$433,2) -> Сахар | J35: =VLOOKUP(B35,товар!$A$1:$C$433,3) -> Продимекс | K35: =AVERAGEIF(продажи!$I$2:$I$1001,продажи!$I$2:$I$1001,продажи!$C$2:$C$1001) -> 254.58333 | L35: =продажи!$C35/продажи!$K35-1 -> 0.52013093 | M35: =SUMIFS($C$2:$C$1001,$I$2:$I$1001,I35,$J$2:$J$1001,J35) -> 5172 | N35: =Таблица1[[#This Row],[цена за шт в рублях]]/Таблица1[[#This Row],[средняя стоимость в категории по поставщику.]]-1 -> -0.92517401 | O35: =VLOOKUP(Таблица1[[#This Row],[id клиента]],клиенты!$A$2:$E$435,5,0) -> 44807 | P35: =Таблица1[[#This Row],[дата создания чека]]-Таблица1[[#This Row],[Дата регистрации клента]] -> 460 | Q35: =TODAY() -> 46059 | R35: =(TODAY()-Таблица1[[#This Row],[Дата регистрации клента]])/30 -> 41.733333 | S35: =VLOOKUP(Таблица1[[#This Row],[id клиента]],Таблица8[[id клиента]:[Страна]],7,0) -> Таджикистан
A36: 35 | B36: 157 | C36: 55 | D36: 2 | E36: 110 | F36: 45381 | G36: Городской Супермаркет | H36: 179 | I36: =VLOOKUP(продажи!$B36,товар!$A$1:$C$433,2) -> Сыр | J36: =VLOOKUP(B36,товар!$A$1:$C$433,3) -> President | K36: =AVERAGEIF(продажи!$I$2:$I$1001,продажи!$I$2:$I$1001,продажи!$C$2:$C$1001) -> 261.03226 | L36: =продажи!$C36/продажи!$K36-1 -> -0.78929807 | M36: =SUMIFS($C$2:$C$1001,$I$2:$I$1001,I36,$J$2:$J$1001,J36) -> 3935 | N36: =Таблица1[[#This Row],[цена за шт в рублях]]/Таблица1[[#This Row],[средняя стоимость в категории по поставщику.]]-1 -> -0.98602287 | O36: =VLOOKUP(Таблица1[[#This Row],[id клиента]],клиенты!$A$2:$E$435,5,0) -> 44833 | P36: =Таблица1[[#This Row],[дата создания чека]]-Таблица1[[#This Row],[Дата регистрации клента]] -> 548 | Q36: =TODAY() -> 46059 | R36: =(TODAY()-Таблица1[[#This Row],[Дата регистрации клента]])/30 -> 40.866667 | S36: =VLOOKUP(Таблица1[[#This Row],[id клиента]],Таблица8[[id клиента]:[Страна]],7,0) -> Россия
A37: 36 | B37: 237 | C37: 336 | D37: 1 | E37: 336 | F37: 44971 | G37: Гиперглобус | H37: 64 | I37: =VLOOKUP(продажи!$B37,товар!$A$1:$C$433,2) -> Конфеты | J37: =VLOOKUP(B37,товар!$A$1:$C$433,3) -> Рот Фронт | K37: =AVERAGEIF(продажи!$I$2:$I$1001,продажи!$I$2:$I$1001,продажи!$C$2:$C$1001) -> 267.85484 | L37: =продажи!$C37/продажи!$K37-1 -> 0.25441079 | M37: =SUMIFS($C$2:$C$1001,$I$2:$I$1001,I37,$J$2:$J$1001,J37) -> 6053 | N37: =Таблица1[[#This Row],[цена за шт в рублях]]/Таблица1[[#This Row],[средняя стоимость в категории по поставщику.]]-1 -> -0.94449034 | O37: =VLOOKUP(Таблица1[[#This Row],[id клиента]],клиенты!$A$2:$E$435,5,0) -> 44707 | P37: =Таблица1[[#This Row],[дата создания чека]]-Таблица1[[#This Row],[Дата регистрации клента]] -> 264 | Q37: =TODAY() -> 46059 | R37: =(TODAY()-Таблица1[[#This Row],[Дата регистрации клента]])/30 -> 45.066667 | S37: =VLOOKUP(Таблица1[[#This Row],[id клиента]],Таблица8[[id клиента]:[Страна]],7,0) -> Узбекистан
A38: 37 | B38: 8 | C38: 480 | D38: 4 | E38: 1920 | F38: 44947 | G38: О'кей | H38: 318 | I38: =VLOOKUP(продажи!$B38,товар!$A$1:$C$433,2) -> Макароны | J38: =VLOOKUP(B38,товар!$A$1:$C$433,3) -> Паста Зара | K38: =AVERAGEIF(продажи!$I$2:$I$1001,продажи!$I$2:$I$1001,продажи!$C$2:$C$1001) -> 265.47674 | L38: =продажи!$C38/продажи!$K38-1 -> 0.80806798 | M38: =SUMIFS($C$2:$C$1001,$I$2:$I$1001,I38,$J$2:$J$1001,J38) -> 10237 | N38: =Таблица1[[#This Row],[цена за шт в рублях]]/Таблица1[[#This Row],[средняя стоимость в категории по поставщику.]]-1 -> -0.95311126 | O38: =VLOOKUP(Таблица1[[#This Row],[id клиента]],клиенты!$A$2:$E$435,5,0) -> 44892 | P38: =Таблица1[[#This Row],[дата создания чека]]-Таблица1[[#This Row],[Дата регистрации клента]] -> 55 | Q38: =TODAY() -> 46059 | R38: =(TODAY()-Таблица1[[#This Row],[Дата регистрации клента]])/30 -> 38.9 | S38: =VLOOKUP(Таблица1[[#This Row],[id клиента]],Таблица8[[id клиента]:[Страна]],7,0) -> Узбекистан
A39: 38 | B39: 65 | C39: 214 | D39: 3 | E39: 642 | F39: 45129 | G39: Бристоль | H39: 239 | I39: =VLOOKUP(продажи!$B39,товар!$A$1:$C$433,2) -> Хлеб | J39: =VLOOKUP(B39,товар!$A$1:$C$433,3) -> Хлебный Дом | K39: =AVERAGEIF(продажи!$I$2:$I$1001,продажи!$I$2:$I$1001,продажи!$C$2:$C$1001) -> 300.31818 | L39: =продажи!$C39/продажи!$K39-1 -> -0.28742243 | M39: =SUMIFS($C$2:$C$1001,$I$2:$I$1001,I39,$J$2:$J$1001,J39) -> 4226 | N39: =Таблица1[[#This Row],[цена за шт в рублях]]/Таблица1[[#This Row],[средняя стоимость в категории по поставщику.]]-1 -> -0.9493611 | O39: =VLOOKUP(Таблица1[[#This Row],[id клиента]],клиенты!$A$2:$E$435,5,0) -> 44767 | P39: =Таблица1[[#This Row],[дата создания чека]]-Таблица1[[#This Row],[Дата регистрации клента]] -> 362 | Q39: =TODAY() -> 46059 | R39: =(TODAY()-Таблица1[[#This Row],[Дата регистрации клента]])/30 -> 43.066667 | S39: =VLOOKUP(Таблица1[[#This Row],[id клиента]],Таблица8[[id клиента]:[Страна]],7,0) -> Узбекистан
A40: 39 | B40: 45 | C40: 60 | D40: 2 | E40: 120 | F40: 45406 | G40: Ароматный Мир | H40: 194 | I40: =VLOOKUP(продажи!$B40,товар!$A$1:$C$433,2) -> Сок | J40: =VLOOKUP(B40,товар!$A$1:$C$433,3) -> Добрый | K40: =AVERAGEIF(продажи!$I$2:$I$1001,продажи!$I$2:$I$1001,продажи!$C$2:$C$1001) -> 268.60345 | L40: =продажи!$C40/продажи!$K40-1 -> -0.77662238 | M40: =SUMIFS($C$2:$C$1001,$I$2:$I$1001,I40,$J$2:$J$1001,J40) -> 2671 | N40: =Таблица1[[#This Row],[цена за шт в рублях]]/Таблица1[[#This Row],[средняя стоимость в категории по поставщику.]]-1 -> -0.9775365 | O40: =VLOOKUP(Таблица1[[#This Row],[id клиента]],клиенты!$A$2:$E$435,5,0) -> 44924 | P40: =Таблица1[[#This Row],[дата создания чека]]-Таблица1[[#This Row],[Дата регистрации клента]] -> 482 | Q40: =TODAY() -> 46059 | R40: =(TODAY()-Таблица1[[#This Row],[Дата регистрации клента]])/30 -> 37.833333 | S40: =VLOOKUP(Таблица1[[#This Row],[id клиента]],Таблица8[[id клиента]:[Страна]],7,0) -> Россия
A41: 40 | B41: 36 | C41: 414 | D41: 3 | E41: 1242 | F41: 45117 | G41: Мираторг | H41: 267 | I41: =VLOOKUP(продажи!$B41,товар!$A$1:$C$433,2) -> Макароны | J41: =VLOOKUP(B41,товар!$A$1:$C$433,3) -> Роллтон | K41: =AVERAGEIF(продажи!$I$2:$I$1001,продажи!$I$2:$I$1001,продажи!$C$2:$C$1001) -> 265.47674 | L41: =продажи!$C41/продажи!$K41-1 -> 0.55945863 | M41: =SUMIFS($C$2:$C$1001,$I$2:$I$1001,I41,$J$2:$J$1001,J41) -> 2120 | N41: =Таблица1[[#This Row],[цена за шт в рублях]]/Таблица1[[#This Row],[средняя стоимость в категории по поставщику.]]-1 -> -0.80471698 | O41: =VLOOKUP(Таблица1[[#This Row],[id клиента]],клиенты!$A$2:$E$435,5,0) -> 44910 | P41: =Таблица1[[#This Row],[дата создания чека]]-Таблица1[[#This Row],[Дата регистрации клента]] -> 207 | Q41: =TODAY() -> 46059 | R41: =(TODAY()-Таблица1[[#This Row],[Дата регистрации клента]])/30 -> 38.3 | S41: =VLOOKUP(Таблица1[[#This Row],[id клиента]],Таблица8[[id клиента]:[Страна]],7,0) -> Россия
A42: 41 | B42: 443 | C42: 62 | D42: 3 | E42: 186 | F42: 45194 | G42: Спар | H42: 334 | I42: =VLOOKUP(продажи!$B42,товар!$A$1:$C$433,2) -> Кофе | J42: =VLOOKUP(B42,товар!$A$1:$C$433,3) -> Jacobs | K42: =AVERAGEIF(продажи!$I$2:$I$1001,продажи!$I$2:$I$1001,продажи!$C$2:$C$1001) -> 249.02381 | L42: =продажи!$C42/продажи!$K42-1 -> -0.75102782 | M42: =SUMIFS($C$2:$C$1001,$I$2:$I$1001,I42,$J$2:$J$1001,J42) -> 5248 | N42: =Таблица1[[#This Row],[цена за шт в рублях]]/Таблица1[[#This Row],[средняя стоимость в категории по поставщику.]]-1 -> -0.98818598 | O42: =VLOOKUP(Таблица1[[#This Row],[id клиента]],клиенты!$A$2:$E$435,5,0) -> 44881 | P42: =Таблица1[[#This Row],[дата создания чека]]-Таблица1[[#This Row],[Дата регистрации клента]] -> 313 | Q42: =TODAY() -> 46059 | R42: =(TODAY()-Таблица1[[#This Row],[Дата регистрации клента]])/30 -> 39.266667 | S42: =VLOOKUP(Таблица1[[#This Row],[id клиента]],Таблица8[[id клиента]:[Страна]],7,0) -> Украина
... A82: 81 | B82: 116 | C82: 120 | D82: 2 | E82: 240 | F82: 45326 | G82: Ашан | H82: 332 | I82: =VLOOKUP(продажи!$B82,товар!$A$1:$C$433,2) -> Соль | J82: =VLOOKUP(B82,товар!$A$1:$C$433,3) -> Экстра | K82: =AVERAGEIF(продажи!$I$2:$I$1001,продажи!$I$2:$I$1001,продажи!$C$2:$C$1001) -> 264.86792 | L82: =продажи!$C82/продажи!$K82-1 -> -0.54694401 | M82: =SUMIFS($C$2:$C$1001,$I$2:$I$1001,I82,$J$2:$J$1001,J82) -> 4171 | N82: =Таблица1[[#This Row],[цена за шт в рублях]]/Таблица1[[#This Row],[средняя стоимость в категории по поставщику.]]-1 -> -0.97122992 | O82: =VLOOKUP(Таблица1[[#This Row],[id клиента]],клиенты!$A$2:$E$435,5,0) -> 44858 | P82: =Таблица1[[#This Row],[дата создания чека]]-Таблица1[[#This Row],[Дата регистрации клента]] -> 468 | Q82: =TODAY() -> 46059 | R82: =(TODAY()-Таблица1[[#This Row],[Дата регистрации клента]])/30 -> 40.033333 | S82: =VLOOKUP(Таблица1[[#This Row],[id клиента]],Таблица8[[id клиента]:[Страна]],7,0) -> Узбекистан
A83: 150 | B83: 232 | C83: 109 | D83: 4 | E83: 436 | F83: 45387 | G83: Билла | H83: 407 | I83: =VLOOKUP(продажи!$B151,товар!$A$1:$C$433,2) -> Молоко | J83: =VLOOKUP(B83,товар!$A$1:$C$433,3) -> Простоквашино | K83: =AVERAGEIF(продажи!$I$2:$I$1001,продажи!$I$2:$I$1001,продажи!$C$2:$C$1001) -> 294.95238 | L83: =продажи!$C151/продажи!$K151-1 -> -0.1456248 | M83: =SUMIFS($C$2:$C$1001,$I$2:$I$1001,I83,$J$2:$J$1001,J83) -> 3507 | N83: =Таблица1[[#This Row],[цена за шт в рублях]]/Таблица1[[#This Row],[средняя стоимость в категории по поставщику.]]-1 -> -0.9689193 | O83: =VLOOKUP(Таблица1[[#This Row],[id клиента]],клиенты!$A$2:$E$435,5,0) -> 44621 | P83: =Таблица1[[#This Row],[дата создания чека]]-Таблица1[[#This Row],[Дата регистрации клента]] -> 766 | Q83: =TODAY() -> 46059 | R83: =(TODAY()-Таблица1[[#This Row],[Дата регистрации клента]])/30 -> 47.933333 | S83: =VLOOKUP(Таблица1[[#This Row],[id клиента]],Таблица8[[id клиента]:[Страна]],7,0) -> Беларусь
A84: 83 | B84: 345 | C84: 267 | D84: 5 | E84: 1335 | F84: 45004 | G84: Дикси | H84: 287 | I84: =VLOOKUP(продажи!$B84,товар!$A$1:$C$433,2) -> Конфеты | J84: =VLOOKUP(B84,товар!$A$1:$C$433,3) -> Рот Фронт | K84: =AVERAGEIF(продажи!$I$2:$I$1001,продажи!$I$2:$I$1001,продажи!$C$2:$C$1001) -> 267.85484 | L84: =продажи!$C84/продажи!$K84-1 -> -0.0031914253 | M84: =SUMIFS($C$2:$C$1001,$I$2:$I$1001,I84,$J$2:$J$1001,J84) -> 6053 | N84: =Таблица1[[#This Row],[цена за шт в рублях]]/Таблица1[[#This Row],[средняя стоимость в категории по поставщику.]]-1 -> -0.95588964 | O84: =VLOOKUP(Таблица1[[#This Row],[id клиента]],клиенты!$A$2:$E$435,5,0) -> 44608 | P84: =Таблица1[[#This Row],[дата создания чека]]-Таблица1[[#This Row],[Дата регистрации клента]] -> 396 | Q84: =TODAY() -> 46059 | R84: =(TODAY()-Таблица1[[#This Row],[Дата регистрации клента]])/30 -> 48.366667 | S84: =VLOOKUP(Таблица1[[#This Row],[id клиента]],Таблица8[[id клиента]:[Страна]],7,0) -> Россия
A85: 84 | B85: 281 | C85: 371 | D85: 1 | E85: 371 | F85: 44993 | G85: О'кей | H85: 11 | I85: =VLOOKUP(продажи!$B85,товар!$A$1:$C$433,2) -> Чай | J85: =VLOOKUP(B85,товар!$A$1:$C$433,3) -> Lipton | K85: =AVERAGEIF(продажи!$I$2:$I$1001,продажи!$I$2:$I$1001,продажи!$C$2:$C$1001) -> 271.18182 | L85: =продажи!$C85/продажи!$K85-1 -> 0.36808582 | M85: =SUMIFS($C$2:$C$1001,$I$2:$I$1001,I85,$J$2:$J$1001,J85) -> 4943 | N85: =Таблица1[[#This Row],[цена за шт в рублях]]/Таблица1[[#This Row],[средняя стоимость в категории по поставщику.]]-1 -> -0.92494437 | O85: =VLOOKUP(Таблица1[[#This Row],[id клиента]],клиенты!$A$2:$E$435,5,0) -> 44690 | P85: =Таблица1[[#This Row],[дата создания чека]]-Таблица1[[#This Row],[Дата регистрации клента]] -> 303 | Q85: =TODAY() -> 46059 | R85: =(TODAY()-Таблица1[[#This Row],[Дата регистрации клента]])/30 -> 45.633333 | S85: =VLOOKUP(Таблица1[[#This Row],[id клиента]],Таблица8[[id клиента]:[Страна]],7,0) -> Таджикистан
A86: 85 | B86: 276 | C86: 295 | D86: 1 | E86: 295 | F86: 45272 | G86: Гиперглобус | H86: 458 | I86: =VLOOKUP(продажи!$B86,товар!$A$1:$C$433,2) -> Колбаса | J86: =VLOOKUP(B86,товар!$A$1:$C$433,3) -> Дымов | K86: =AVERAGEIF(продажи!$I$2:$I$1001,продажи!$I$2:$I$1001,продажи!$C$2:$C$1001) -> 286.92308 | L86: =продажи!$C86/продажи!$K86-1 -> 0.028150134 | M86: =SUMIFS($C$2:$C$1001,$I$2:$I$1001,I86,$J$2:$J$1001,J86) -> 2814 | N86: =Таблица1[[#This Row],[цена за шт в рублях]]/Таблица1[[#This Row],[средняя стоимость в категории по поставщику.]]-1 -> -0.89516702 | O86: =VLOOKUP(Таблица1[[#This Row],[id клиента]],клиенты!$A$2:$E$435,5,0) -> 44694 | P86: =Таблица1[[#This Row],[дата создания чека]]-Таблица1[[#This Row],[Дата регистрации клента]] -> 578 | Q86: =TODAY() -> 46059 | R86: =(TODAY()-Таблица1[[#This Row],[Дата регистрации клента]])/30 -> 45.5 | S86: =VLOOKUP(Таблица1[[#This Row],[id клиента]],Таблица8[[id клиента]:[Страна]],7,0) -> Россия
A87: 86 | B87: 234 | C87: 75 | D87: 5 | E87: 375 | F87: 44939 | G87: Ароматный Мир | H87: 130 | I87: =VLOOKUP(продажи!$B87,товар!$A$1:$C$433,2) -> Чай | J87: =VLOOKUP(B87,товар!$A$1:$C$433,3) -> Greenfield | K87: =AVERAGEIF(продажи!$I$2:$I$1001,продажи!$I$2:$I$1001,продажи!$C$2:$C$1001) -> 271.18182 | L87: =продажи!$C87/продажи!$K87-1 -> -0.72343279 | M87: =SUMIFS($C$2:$C$1001,$I$2:$I$1001,I87,$J$2:$J$1001,J87) -> 6412 | N87: =Таблица1[[#This Row],[цена за шт в рублях]]/Таблица1[[#This Row],[средняя стоимость в категории по поставщику.]]-1 -> -0.98830318 | O87: =VLOOKUP(Таблица1[[#This Row],[id клиента]],клиенты!$A$2:$E$435,5,0) -> 44863 | P87: =Таблица1[[#This Row],[дата создания чека]]-Таблица1[[#This Row],[Дата регистрации клента]] -> 76 | Q87: =TODAY() -> 46059 | R87: =(TODAY()-Таблица1[[#This Row],[Дата регистрации клента]])/30 -> 39.866667 | S87: =VLOOKUP(Таблица1[[#This Row],[id клиента]],Таблица8[[id клиента]:[Страна]],7,0) -> Таджикистан
A88: 87 | B88: 319 | C88: 247 | D88: 2 | E88: 494 | F88: 45189 | G88: Бристоль | H88: 330 | I88: =VLOOKUP(продажи!$B88,товар!$A$1:$C$433,2) -> Йогурт | J88: =VLOOKUP(B88,товар!$A$1:$C$433,3) -> Эрманн | K88: =AVERAGEIF(продажи!$I$2:$I$1001,продажи!$I$2:$I$1001,продажи!$C$2:$C$1001) -> 263.25424 | L88: =продажи!$C88/продажи!$K88-1 -> -0.061743497 | M88: =SUMIFS($C$2:$C$1001,$I$2:$I$1001,I88,$J$2:$J$1001,J88) -> 4970 | N88: =Таблица1[[#This Row],[цена за шт в рублях]]/Таблица1[[#This Row],[средняя стоимость в категории по поставщику.]]-1 -> -0.95030181 | O88: =VLOOKUP(Таблица1[[#This Row],[id клиента]],клиенты!$A$2:$E$435,5,0) -> 44815 | P88: =Таблица1[[#This Row],[дата создания чека]]-Таблица1[[#This Row],[Дата регистрации клента]] -> 374 | Q88: =TODAY() -> 46059 | R88: =(TODAY()-Таблица1[[#This Row],[Дата регистрации клента]])/30 -> 41.466667 | S88: =VLOOKUP(Таблица1[[#This Row],[id клиента]],Таблица8[[id клиента]:[Страна]],7,0) -> Узбекистан
A89: 88 | B89: 375 | C89: 281 | D89: 2 | E89: 562 | F89: 45079 | G89: Гиперглобус | H89: 167 | I89: =VLOOKUP(продажи!$B89,товар!$A$1:$C$433,2) -> Макароны | J89: =VLOOKUP(B89,товар!$A$1:$C$433,3) -> Борилла | K89: =AVERAGEIF(продажи!$I$2:$I$1001,продажи!$I$2:$I$1001,продажи!$C$2:$C$1001) -> 265.47674 | L89: =продажи!$C89/продажи!$K89-1 -> 0.058473129 | M89: =SUMIFS($C$2:$C$1001,$I$2:$I$1001,I89,$J$2:$J$1001,J89) -> 6852 | N89: =Таблица1[[#This Row],[цена за шт в рублях]]/Таблица1[[#This Row],[средняя стоимость в категории по поставщику.]]-1 -> -0.95899008 | O89: =VLOOKUP(Таблица1[[#This Row],[id клиента]],клиенты!$A$2:$E$435,5,0) -> 44563 | P89: =Таблица1[[#This Row],[дата создания чека]]-Таблица1[[#This Row],[Дата регистрации клента]] -> 516 | Q89: =TODAY() -> 46059 | R89: =(TODAY()-Таблица1[[#This Row],[Дата регистрации клента]])/30 -> 49.866667 | S89: =VLOOKUP(Таблица1[[#This Row],[id клиента]],Таблица8[[id клиента]:[Страна]],7,0) -> Узбекистан
A90: 89 | B90: 443 | C90: 136 | D90: 2 | E90: 272 | F90: 44927 | G90: Седьмой Континент | H90: 140 | I90: =VLOOKUP(продажи!$B90,товар!$A$1:$C$433,2) -> Кофе | J90: =VLOOKUP(B90,товар!$A$1:$C$433,3) -> Jacobs | K90: =AVERAGEIF(продажи!$I$2:$I$1001,продажи!$I$2:$I$1001,продажи!$C$2:$C$1001) -> 249.02381 | L90: =продажи!$C90/продажи!$K90-1 -> -0.45386748 | M90: =SUMIFS($C$2:$C$1001,$I$2:$I$1001,I90,$J$2:$J$1001,J90) -> 5248 | N90: =Таблица1[[#This Row],[цена за шт в рублях]]/Таблица1[[#This Row],[средняя стоимость в категории по поставщику.]]-1 -> -0.97408537 | O90: =VLOOKUP(Таблица1[[#This Row],[id клиента]],клиенты!$A$2:$E$435,5,0) -> 44627 | P90: =Таблица1[[#This Row],[дата создания чека]]-Таблица1[[#This Row],[Дата регистрации клента]] -> 300 | Q90: =TODAY() -> 46059 | R90: =(TODAY()-Таблица1[[#This Row],[Дата регистрации клента]])/30 -> 47.733333 | S90: =VLOOKUP(Таблица1[[#This Row],[id клиента]],Таблица8[[id клиента]:[Страна]],7,0) -> Россия
A91: 90 | B91: 30 | C91: 142 | D91: 5 | E91: 710 | F91: 45226 | G91: Ароматный Мир | H91: 423 | I91: =VLOOKUP(продажи!$B91,товар!$A$1:$C$433,2) -> Чипсы | J91: =VLOOKUP(B91,товар!$A$1:$C$433,3) -> Pringles | K91: =AVERAGEIF(продажи!$I$2:$I$1001,продажи!$I$2:$I$1001,продажи!$C$2:$C$1001) -> 273.72549 | L91: =продажи!$C91/продажи!$K91-1 -> -0.48123209 | M91: =SUMIFS($C$2:$C$1001,$I$2:$I$1001,I91,$J$2:$J$1001,J91) -> 5885 | N91: =Таблица1[[#This Row],[цена за шт в рублях]]/Таблица1[[#This Row],[средняя стоимость в категории по поставщику.]]-1 -> -0.97587086 | O91: =VLOOKUP(Таблица1[[#This Row],[id клиента]],клиенты!$A$2:$E$435,5,0) -> 44841 | P91: =Таблица1[[#This Row],[дата создания чека]]-Таблица1[[#This Row],[Дата регистрации клента]] -> 385 | Q91: =TODAY() -> 46059 | R91: =(TODAY()-Таблица1[[#This Row],[Дата регистрации клента]])/30 -> 40.6 | S91: =VLOOKUP(Таблица1[[#This Row],[id клиента]],Таблица8[[id клиента]:[Страна]],7,0) -> Беларусь
A92: 91 | B92: 24 | C92: 414 | D92: 1 | E92: 414 | F92: 45388 | G92: Спар | H92: 365 | I92: =VLOOKUP(продажи!$B92,товар!$A$1:$C$433,2) -> Йогурт | J92: =VLOOKUP(B92,товар!$A$1:$C$433,3) -> Чудо | K92: =AVERAGEIF(продажи!$I$2:$I$1001,продажи!$I$2:$I$1001,продажи!$C$2:$C$1001) -> 263.25424 | L92: =продажи!$C92/продажи!$K92-1 -> 0.57262426 | M92: =SUMIFS($C$2:$C$1001,$I$2:$I$1001,I92,$J$2:$J$1001,J92) -> 2871 | N92: =Таблица1[[#This Row],[цена за шт в рублях]]/Таблица1[[#This Row],[средняя стоимость в категории по поставщику.]]-1 -> -0.85579937 | O92: =VLOOKUP(Таблица1[[#This Row],[id клиента]],клиенты!$A$2:$E$435,5,0) -> 44841 | P92: =Таблица1[[#This Row],[дата создания чека]]-Таблица1[[#This Row],[Дата регистрации клента]] -> 547 | Q92: =TODAY() -> 46059 | R92: =(TODAY()-Таблица1[[#This Row],[Дата регистрации клента]])/30 -> 40.6 | S92: =VLOOKUP(Таблица1[[#This Row],[id клиента]],Таблица8[[id клиента]:[Страна]],7,0) -> Беларусь
A93: 92 | B93: 357 | C93: 206 | D93: 2 | E93: 412 | F93: 45424 | G93: Ашан | H93: 452 | I93: =VLOOKUP(продажи!$B93,товар!$A$1:$C$433,2) -> Мясо | J93: =VLOOKUP(B93,товар!$A$1:$C$433,3) -> Снежана | K93: =AVERAGEIF(продажи!$I$2:$I$1001,продажи!$I$2:$I$1001,продажи!$C$2:$C$1001) -> 271.74545 | L93: =продажи!$C93/продажи!$K93-1 -> -0.24193764 | M93: =SUMIFS($C$2:$C$1001,$I$2:$I$1001,I93,$J$2:$J$1001,J93) -> 4630 | N93: =Таблица1[[#This Row],[цена за шт в рублях]]/Таблица1[[#This Row],[средняя стоимость в категории по поставщику.]]-1 -> -0.95550756 | O93: =VLOOKUP(Таблица1[[#This Row],[id клиента]],клиенты!$A$2:$E$435,5,0) -> 44769 | P93: =Таблица1[[#This Row],[дата создания чека]]-Таблица1[[#This Row],[Дата регистрации клента]] -> 655 | Q93: =TODAY() -> 46059 | R93: =(TODAY()-Таблица1[[#This Row],[Дата регистрации клента]])/30 -> 43 | S93: =VLOOKUP(Таблица1[[#This Row],[id клиента]],Таблица8[[id клиента]:[Страна]],7,0) -> Россия
A94: 93 | B94: 265 | C94: 66 | D94: 1 | E94: 66 | F94: 45183 | G94: Магнит | H94: 424 | I94: =VLOOKUP(продажи!$B94,товар!$A$1:$C$433,2) -> Мясо | J94: =VLOOKUP(B94,товар!$A$1:$C$433,3) -> Мираторг | K94: =AVERAGEIF(продажи!$I$2:$I$1001,продажи!$I$2:$I$1001,продажи!$C$2:$C$1001) -> 271.74545 | L94: =продажи!$C94/продажи!$K94-1 -> -0.75712565 | M94: =SUMIFS($C$2:$C$1001,$I$2:$I$1001,I94,$J$2:$J$1001,J94) -> 3799 | N94: =Таблица1[[#This Row],[цена за шт в рублях]]/Таблица1[[#This Row],[средняя стоимость в категории по поставщику.]]-1 -> -0.98262701 | O94: =VLOOKUP(Таблица1[[#This Row],[id клиента]],клиенты!$A$2:$E$435,5,0) -> 44585 | P94: =Таблица1[[#This Row],[дата создания чека]]-Таблица1[[#This Row],[Дата регистрации клента]] -> 598 | Q94: =TODAY() -> 46059 | R94: =(TODAY()-Таблица1[[#This Row],[Дата регистрации клента]])/30 -> 49.133333 | S94: =VLOOKUP(Таблица1[[#This Row],[id клиента]],Таблица8[[id клиента]:[Страна]],7,0) -> Россия
A95: 94 | B95: 102 | C95: 452 | D95: 1 | E95: 452 | F95: 45218 | G95: Пятерочка | H95: 75 | I95: =VLOOKUP(продажи!$B95,товар!$A$1:$C$433,2) -> Печенье | J95: =VLOOKUP(B95,товар!$A$1:$C$433,3) -> Белогорье | K95: =AVERAGEIF(продажи!$I$2:$I$1001,продажи!$I$2:$I$1001,продажи!$C$2:$C$1001) -> 283.46809 | L95: =продажи!$C95/продажи!$K95-1 -> 0.59453577 | M95: =SUMIFS($C$2:$C$1001,$I$2:$I$1001,I95,$J$2:$J$1001,J95) -> 3493 | N95: =Таблица1[[#This Row],[цена за шт в рублях]]/Таблица1[[#This Row],[средняя стоимость в категории по поставщику.]]-1 -> -0.87059834 | O95: =VLOOKUP(Таблица1[[#This Row],[id клиента]],клиенты!$A$2:$E$435,5,0) -> 44796 | P95: =Таблица1[[#This Row],[дата создания чека]]-Таблица1[[#This Row],[Дата регистрации клента]] -> 422 | Q95: =TODAY() -> 46059 | R95: =(TODAY()-Таблица1[[#This Row],[Дата регистрации клента]])/30 -> 42.1 | S95: =VLOOKUP(Таблица1[[#This Row],[id клиента]],Таблица8[[id клиента]:[Страна]],7,0) -> Украина
... A119: 118 | B119: 223 | C119: 174 | D119: 2 | E119: 348 | F119: 45338 | G119: Мираторг | H119: 269 | I119: =VLOOKUP(продажи!$B119,товар!$A$1:$C$433,2) -> Чай | J119: =VLOOKUP(B119,товар!$A$1:$C$433,3) -> Greenfield | K119: =AVERAGEIF(продажи!$I$2:$I$1001,продажи!$I$2:$I$1001,продажи!$C$2:$C$1001) -> 271.18182 | L119: =продажи!$C119/продажи!$K119-1 -> -0.35836406 | M119: =SUMIFS($C$2:$C$1001,$I$2:$I$1001,I119,$J$2:$J$1001,J119) -> 6412 | N119: =Таблица1[[#This Row],[цена за шт в рублях]]/Таблица1[[#This Row],[средняя стоимость в категории по поставщику.]]-1 -> -0.97286338 | O119: =VLOOKUP(Таблица1[[#This Row],[id клиента]],клиенты!$A$2:$E$435,5,0) -> 44720 | P119: =Таблица1[[#This Row],[дата создания чека]]-Таблица1[[#This Row],[Дата регистрации клента]] -> 618 | Q119: =TODAY() -> 46059 | R119: =(TODAY()-Таблица1[[#This Row],[Дата регистрации клента]])/30 -> 44.633333 | S119: =VLOOKUP(Таблица1[[#This Row],[id клиента]],Таблица8[[id клиента]:[Страна]],7,0) -> Россия
A120: 569 | B120: 474 | C120: 261 | D120: 2 | E120: 522 | F120: 45382 | G120: Азбука Вкуса | H120: 88 | I120: =VLOOKUP(продажи!$B570,товар!$A$1:$C$433,2) -> Молоко | J120: =VLOOKUP(B120,товар!$A$1:$C$433,3) -> Простоквашино | K120: =AVERAGEIF(продажи!$I$2:$I$1001,продажи!$I$2:$I$1001,продажи!$C$2:$C$1001) -> 294.95238 | L120: =продажи!$C570/продажи!$K570-1 -> 0.1900226 | M120: =SUMIFS($C$2:$C$1001,$I$2:$I$1001,I120,$J$2:$J$1001,J120) -> 3507 | N120: =Таблица1[[#This Row],[цена за шт в рублях]]/Таблица1[[#This Row],[средняя стоимость в категории по поставщику.]]-1 -> -0.92557742 | O120: =VLOOKUP(Таблица1[[#This Row],[id клиента]],клиенты!$A$2:$E$435,5,0) -> 44630 | P120: =Таблица1[[#This Row],[дата создания чека]]-Таблица1[[#This Row],[Дата регистрации клента]] -> 752 | Q120: =TODAY() -> 46059 | R120: =(TODAY()-Таблица1[[#This Row],[Дата регистрации клента]])/30 -> 47.633333 | S120: =VLOOKUP(Таблица1[[#This Row],[id клиента]],Таблица8[[id клиента]:[Страна]],7,0) -> Украина
A121: 120 | B121: 223 | C121: 411 | D121: 5 | E121: 2055 | F121: 45244 | G121: Ароматный Мир | H121: 281 | I121: =VLOOKUP(продажи!$B121,товар!$A$1:$C$433,2) -> Чай | J121: =VLOOKUP(B121,товар!$A$1:$C$433,3) -> Greenfield | K121: =AVERAGEIF(продажи!$I$2:$I$1001,продажи!$I$2:$I$1001,продажи!$C$2:$C$1001) -> 271.18182 | L121: =продажи!$C121/продажи!$K121-1 -> 0.51558833 | M121: =SUMIFS($C$2:$C$1001,$I$2:$I$1001,I121,$J$2:$J$1001,J121) -> 6412 | N121: =Таблица1[[#This Row],[цена за шт в рублях]]/Таблица1[[#This Row],[средняя стоимость в категории по поставщику.]]-1 -> -0.93590143 | O121: =VLOOKUP(Таблица1[[#This Row],[id клиента]],клиенты!$A$2:$E$435,5,0) -> 44711 | P121: =Таблица1[[#This Row],[дата создания чека]]-Таблица1[[#This Row],[Дата регистрации клента]] -> 533 | Q121: =TODAY() -> 46059 | R121: =(TODAY()-Таблица1[[#This Row],[Дата регистрации клента]])/30 -> 44.933333 | S121: =VLOOKUP(Таблица1[[#This Row],[id клиента]],Таблица8[[id клиента]:[Страна]],7,0) -> Узбекистан
A122: 121 | B122: 244 | C122: 245 | D122: 4 | E122: 980 | F122: 44960 | G122: Седьмой Континент | H122: 149 | I122: =VLOOKUP(продажи!$B122,товар!$A$1:$C$433,2) -> Мясо | J122: =VLOOKUP(B122,товар!$A$1:$C$433,3) -> Сава | K122: =AVERAGEIF(продажи!$I$2:$I$1001,продажи!$I$2:$I$1001,продажи!$C$2:$C$1001) -> 271.74545 | L122: =продажи!$C122/продажи!$K122-1 -> -0.098420982 | M122: =SUMIFS($C$2:$C$1001,$I$2:$I$1001,I122,$J$2:$J$1001,J122) -> 3405 | N122: =Таблица1[[#This Row],[цена за шт в рублях]]/Таблица1[[#This Row],[средняя стоимость в категории по поставщику.]]-1 -> -0.92804699 | O122: =VLOOKUP(Таблица1[[#This Row],[id клиента]],клиенты!$A$2:$E$435,5,0) -> 44882 | P122: =Таблица1[[#This Row],[дата создания чека]]-Таблица1[[#This Row],[Дата регистрации клента]] -> 78 | Q122: =TODAY() -> 46059 | R122: =(TODAY()-Таблица1[[#This Row],[Дата регистрации клента]])/30 -> 39.233333 | S122: =VLOOKUP(Таблица1[[#This Row],[id клиента]],Таблица8[[id клиента]:[Страна]],7,0) -> Таджикистан
A123: 122 | B123: 393 | C123: 113 | D123: 5 | E123: 565 | F123: 45433 | G123: Метро | H123: 71 | I123: =VLOOKUP(продажи!$B123,товар!$A$1:$C$433,2) -> Рыба | J123: =VLOOKUP(B123,товар!$A$1:$C$433,3) -> Русское море | K123: =AVERAGEIF(продажи!$I$2:$I$1001,продажи!$I$2:$I$1001,продажи!$C$2:$C$1001) -> 258.51282 | L123: =продажи!$C123/продажи!$K123-1 -> -0.56288435 | M123: =SUMIFS($C$2:$C$1001,$I$2:$I$1001,I123,$J$2:$J$1001,J123) -> 878 | N123: =Таблица1[[#This Row],[цена за шт в рублях]]/Таблица1[[#This Row],[средняя стоимость в категории по поставщику.]]-1 -> -0.87129841 | O123: =VLOOKUP(Таблица1[[#This Row],[id клиента]],клиенты!$A$2:$E$435,5,0) -> 44762 | P123: =Таблица1[[#This Row],[дата создания чека]]-Таблица1[[#This Row],[Дата регистрации клента]] -> 671 | Q123: =TODAY() -> 46059 | R123: =(TODAY()-Таблица1[[#This Row],[Дата регистрации клента]])/30 -> 43.233333 | S123: =VLOOKUP(Таблица1[[#This Row],[id клиента]],Таблица8[[id клиента]:[Страна]],7,0) -> Украина
A124: 123 | B124: 166 | C124: 73 | D124: 4 | E124: 292 | F124: 45316 | G124: Магнит | H124: 126 | I124: =VLOOKUP(продажи!$B124,товар!$A$1:$C$433,2) -> Сок | J124: =VLOOKUP(B124,товар!$A$1:$C$433,3) -> Добрый | K124: =AVERAGEIF(продажи!$I$2:$I$1001,продажи!$I$2:$I$1001,продажи!$C$2:$C$1001) -> 268.60345 | L124: =продажи!$C124/продажи!$K124-1 -> -0.72822389 | M124: =SUMIFS($C$2:$C$1001,$I$2:$I$1001,I124,$J$2:$J$1001,J124) -> 2671 | N124: =Таблица1[[#This Row],[цена за шт в рублях]]/Таблица1[[#This Row],[средняя стоимость в категории по поставщику.]]-1 -> -0.97266941 | O124: =VLOOKUP(Таблица1[[#This Row],[id клиента]],клиенты!$A$2:$E$435,5,0) -> 44822 | P124: =Таблица1[[#This Row],[дата создания чека]]-Таблица1[[#This Row],[Дата регистрации клента]] -> 494 | Q124: =TODAY() -> 46059 | R124: =(TODAY()-Таблица1[[#This Row],[Дата регистрации клента]])/30 -> 41.233333 | S124: =VLOOKUP(Таблица1[[#This Row],[id клиента]],Таблица8[[id клиента]:[Страна]],7,0) -> Узбекистан
A125: 124 | B125: 249 | C125: 368 | D125: 2 | E125: 736 | F125: 45313 | G125: О'кей | H125: 380 | I125: =VLOOKUP(продажи!$B125,товар!$A$1:$C$433,2) -> Чай | J125: =VLOOKUP(B125,товар!$A$1:$C$433,3) -> Lipton | K125: =AVERAGEIF(продажи!$I$2:$I$1001,продажи!$I$2:$I$1001,продажи!$C$2:$C$1001) -> 271.18182 | L125: =продажи!$C125/продажи!$K125-1 -> 0.35702313 | M125: =SUMIFS($C$2:$C$1001,$I$2:$I$1001,I125,$J$2:$J$1001,J125) -> 4943 | N125: =Таблица1[[#This Row],[цена за шт в рублях]]/Таблица1[[#This Row],[средняя стоимость в категории по поставщику.]]-1 -> -0.92555128 | O125: =VLOOKUP(Таблица1[[#This Row],[id клиента]],клиенты!$A$2:$E$435,5,0) -> 44563 | P125: =Таблица1[[#This Row],[дата создания чека]]-Таблица1[[#This Row],[Дата регистрации клента]] -> 750 | Q125: =TODAY() -> 46059 | R125: =(TODAY()-Таблица1[[#This Row],[Дата регистрации клента]])/30 -> 49.866667 | S125: =VLOOKUP(Таблица1[[#This Row],[id клиента]],Таблица8[[id клиента]:[Страна]],7,0) -> Россия
A126: 125 | B126: 83 | C126: 351 | D126: 1 | E126: 351 | F126: 45361 | G126: Мосмарт | H126: 11 | I126: =VLOOKUP(продажи!$B126,товар!$A$1:$C$433,2) -> Сок | J126: =VLOOKUP(B126,товар!$A$1:$C$433,3) -> Сады Придонья | K126: =AVERAGEIF(продажи!$I$2:$I$1001,продажи!$I$2:$I$1001,продажи!$C$2:$C$1001) -> 268.60345 | L126: =продажи!$C126/продажи!$K126-1 -> 0.3067591 | M126: =SUMIFS($C$2:$C$1001,$I$2:$I$1001,I126,$J$2:$J$1001,J126) -> 2796 | N126: =Таблица1[[#This Row],[цена за шт в рублях]]/Таблица1[[#This Row],[средняя стоимость в категории по поставщику.]]-1 -> -0.87446352 | O126: =VLOOKUP(Таблица1[[#This Row],[id клиента]],клиенты!$A$2:$E$435,5,0) -> 44690 | P126: =Таблица1[[#This Row],[дата создания чека]]-Таблица1[[#This Row],[Дата регистрации клента]] -> 671 | Q126: =TODAY() -> 46059 | R126: =(TODAY()-Таблица1[[#This Row],[Дата регистрации клента]])/30 -> 45.633333 | S126: =VLOOKUP(Таблица1[[#This Row],[id клиента]],Таблица8[[id клиента]:[Страна]],7,0) -> Таджикистан
A127: 126 | B127: 242 | C127: 221 | D127: 5 | E127: 1105 | F127: 45025 | G127: Билла | H127: 114 | I127: =VLOOKUP(продажи!$B127,товар!$A$1:$C$433,2) -> Овощи | J127: =VLOOKUP(B127,товар!$A$1:$C$433,3) -> Овощной ряд | K127: =AVERAGEIF(продажи!$I$2:$I$1001,продажи!$I$2:$I$1001,продажи!$C$2:$C$1001) -> 250.4878 | L127: =продажи!$C127/продажи!$K127-1 -> -0.11772152 | M127: =SUMIFS($C$2:$C$1001,$I$2:$I$1001,I127,$J$2:$J$1001,J127) -> 5165 | N127: =Таблица1[[#This Row],[цена за шт в рублях]]/Таблица1[[#This Row],[средняя стоимость в категории по поставщику.]]-1 -> -0.957212 | O127: =VLOOKUP(Таблица1[[#This Row],[id клиента]],клиенты!$A$2:$E$435,5,0) -> 44889 | P127: =Таблица1[[#This Row],[дата создания чека]]-Таблица1[[#This Row],[Дата регистрации клента]] -> 136 | Q127: =TODAY() -> 46059 | R127: =(TODAY()-Таблица1[[#This Row],[Дата регистрации клента]])/30 -> 39 | S127: =VLOOKUP(Таблица1[[#This Row],[id клиента]],Таблица8[[id клиента]:[Страна]],7,0) -> Россия
A128: 127 | B128: 281 | C128: 442 | D128: 5 | E128: 2210 | F128: 45379 | G128: Городской Супермаркет | H128: 381 | I128: =VLOOKUP(продажи!$B128,товар!$A$1:$C$433,2) -> Чай | J128: =VLOOKUP(B128,товар!$A$1:$C$433,3) -> Lipton | K128: =AVERAGEIF(продажи!$I$2:$I$1001,продажи!$I$2:$I$1001,продажи!$C$2:$C$1001) -> 271.18182 | L128: =продажи!$C128/продажи!$K128-1 -> 0.62990278 | M128: =SUMIFS($C$2:$C$1001,$I$2:$I$1001,I128,$J$2:$J$1001,J128) -> 4943 | N128: =Таблица1[[#This Row],[цена за шт в рублях]]/Таблица1[[#This Row],[средняя стоимость в категории по поставщику.]]-1 -> -0.91058062 | O128: =VLOOKUP(Таблица1[[#This Row],[id клиента]],клиенты!$A$2:$E$435,5,0) -> 44714 | P128: =Таблица1[[#This Row],[дата создания чека]]-Таблица1[[#This Row],[Дата регистрации клента]] -> 665 | Q128: =TODAY() -> 46059 | R128: =(TODAY()-Таблица1[[#This Row],[Дата регистрации клента]])/30 -> 44.833333 | S128: =VLOOKUP(Таблица1[[#This Row],[id клиента]],Таблица8[[id клиента]:[Страна]],7,0) -> Узбекистан
A129: 128 | B129: 236 | C129: 465 | D129: 1 | E129: 465 | F129: 45176 | G129: Ашан | H129: 342 | I129: =VLOOKUP(продажи!$B129,товар!$A$1:$C$433,2) -> Печенье | J129: =VLOOKUP(B129,товар!$A$1:$C$433,3) -> Посиделкино | K129: =AVERAGEIF(продажи!$I$2:$I$1001,продажи!$I$2:$I$1001,продажи!$C$2:$C$1001) -> 283.46809 | L129: =продажи!$C129/продажи!$K129-1 -> 0.64039631 | M129: =SUMIFS($C$2:$C$1001,$I$2:$I$1001,I129,$J$2:$J$1001,J129) -> 3538 | N129: =Таблица1[[#This Row],[цена за шт в рублях]]/Таблица1[[#This Row],[средняя стоимость в категории по поставщику.]]-1 -> -0.86856981 | O129: =VLOOKUP(Таблица1[[#This Row],[id клиента]],клиенты!$A$2:$E$435,5,0) -> 44570 | P129: =Таблица1[[#This Row],[дата создания чека]]-Таблица1[[#This Row],[Дата регистрации клента]] -> 606 | Q129: =TODAY() -> 46059 | R129: =(TODAY()-Таблица1[[#This Row],[Дата регистрации клента]])/30 -> 49.633333 | S129: =VLOOKUP(Таблица1[[#This Row],[id клиента]],Таблица8[[id клиента]:[Страна]],7,0) -> Таджикистан
A130: 129 | B130: 379 | C130: 380 | D130: 1 | E130: 380 | F130: 45260 | G130: Ашан | H130: 276 | I130: =VLOOKUP(продажи!$B130,товар!$A$1:$C$433,2) -> Йогурт | J130: =VLOOKUP(B130,товар!$A$1:$C$433,3) -> Активиа | K130: =AVERAGEIF(продажи!$I$2:$I$1001,продажи!$I$2:$I$1001,продажи!$C$2:$C$1001) -> 263.25424 | L130: =продажи!$C130/продажи!$K130-1 -> 0.44347154 | M130: =SUMIFS($C$2:$C$1001,$I$2:$I$1001,I130,$J$2:$J$1001,J130) -> 1762 | N130: =Таблица1[[#This Row],[цена за шт в рублях]]/Таблица1[[#This Row],[средняя стоимость в категории по поставщику.]]-1 -> -0.78433598 | O130: =VLOOKUP(Таблица1[[#This Row],[id клиента]],клиенты!$A$2:$E$435,5,0) -> 44632 | P130: =Таблица1[[#This Row],[дата создания чека]]-Таблица1[[#This Row],[Дата регистрации клента]] -> 628 | Q130: =TODAY() -> 46059 | R130: =(TODAY()-Таблица1[[#This Row],[Дата регистрации клента]])/30 -> 47.566667 | S130: =VLOOKUP(Таблица1[[#This Row],[id клиента]],Таблица8[[id клиента]:[Страна]],7,0) -> Таджикистан
A131: 130 | B131: 37 | C131: 313 | D131: 1 | E131: 313 | F131: 45009 | G131: Перекресток | H131: 293 | I131: =VLOOKUP(продажи!$B131,товар!$A$1:$C$433,2) -> Соль | J131: =VLOOKUP(B131,товар!$A$1:$C$433,3) -> Илецкая | K131: =AVERAGEIF(продажи!$I$2:$I$1001,продажи!$I$2:$I$1001,продажи!$C$2:$C$1001) -> 264.86792 | L131: =продажи!$C131/продажи!$K131-1 -> 0.18172104 | M131: =SUMIFS($C$2:$C$1001,$I$2:$I$1001,I131,$J$2:$J$1001,J131) -> 4287 | N131: =Таблица1[[#This Row],[цена за шт в рублях]]/Таблица1[[#This Row],[средняя стоимость в категории по поставщику.]]-1 -> -0.92698857 | O131: =VLOOKUP(Таблица1[[#This Row],[id клиента]],клиенты!$A$2:$E$435,5,0) -> 44573 | P131: =Таблица1[[#This Row],[дата создания чека]]-Таблица1[[#This Row],[Дата регистрации клента]] -> 436 | Q131: =TODAY() -> 46059 | R131: =(TODAY()-Таблица1[[#This Row],[Дата регистрации клента]])/30 -> 49.533333 | S131: =VLOOKUP(Таблица1[[#This Row],[id клиента]],Таблица8[[id клиента]:[Страна]],7,0) -> Беларусь
A132: 131 | B132: 431 | C132: 141 | D132: 5 | E132: 705 | F132: 45029 | G132: Лента | H132: 386 | I132: =VLOOKUP(продажи!$B132,товар!$A$1:$C$433,2) -> Овощи | J132: =VLOOKUP(B132,товар!$A$1:$C$433,3) -> Гавриш | K132: =AVERAGEIF(продажи!$I$2:$I$1001,продажи!$I$2:$I$1001,продажи!$C$2:$C$1001) -> 250.4878 | L132: =продажи!$C132/продажи!$K132-1 -> -0.43709834 | M132: =SUMIFS($C$2:$C$1001,$I$2:$I$1001,I132,$J$2:$J$1001,J132) -> 2229 | N132: =Таблица1[[#This Row],[цена за шт в рублях]]/Таблица1[[#This Row],[средняя стоимость в категории по поставщику.]]-1 -> -0.93674293 | O132: =VLOOKUP(Таблица1[[#This Row],[id клиента]],клиенты!$A$2:$E$435,5,0) -> 44734 | P132: =Таблица1[[#This Row],[дата создания чека]]-Таблица1[[#This Row],[Дата регистрации клента]] -> 295 | Q132: =TODAY() -> 46059 | R132: =(TODAY()-Таблица1[[#This Row],[Дата регистрации клента]])/30 -> 44.166667 | S132: =VLOOKUP(Таблица1[[#This Row],[id клиента]],Таблица8[[id клиента]:[Страна]],7,0) -> Узбекистан
... A142: 141 | B142: 309 | C142: 498 | D142: 1 | E142: 498 | F142: 45372 | G142: Лента | H142: 464 | I142: =VLOOKUP(продажи!$B142,товар!$A$1:$C$433,2) -> Конфеты | J142: =VLOOKUP(B142,товар!$A$1:$C$433,3) -> Рот Фронт | K142: =AVERAGEIF(продажи!$I$2:$I$1001,продажи!$I$2:$I$1001,продажи!$C$2:$C$1001) -> 267.85484 | L142: =продажи!$C142/продажи!$K142-1 -> 0.85921599 | M142: =SUMIFS($C$2:$C$1001,$I$2:$I$1001,I142,$J$2:$J$1001,J142) -> 6053 | N142: =Таблица1[[#This Row],[цена за шт в рублях]]/Таблица1[[#This Row],[средняя стоимость в категории по поставщику.]]-1 -> -0.91772675 | O142: =VLOOKUP(Таблица1[[#This Row],[id клиента]],клиенты!$A$2:$E$435,5,0) -> 44827 | P142: =Таблица1[[#This Row],[дата создания чека]]-Таблица1[[#This Row],[Дата регистрации клента]] -> 545 | Q142: =TODAY() -> 46059 | R142: =(TODAY()-Таблица1[[#This Row],[Дата регистрации клента]])/30 -> 41.066667 | S142: =VLOOKUP(Таблица1[[#This Row],[id клиента]],Таблица8[[id клиента]:[Страна]],7,0) -> Россия
A143: 564 | B143: 274 | C143: 472 | D143: 3 | E143: 1416 | F143: 45408 | G143: Дикси | H143: 272 | I143: =VLOOKUP(продажи!$B565,товар!$A$1:$C$433,2) -> Молоко | J143: =VLOOKUP(B143,товар!$A$1:$C$433,3) -> Простоквашино | K143: =AVERAGEIF(продажи!$I$2:$I$1001,продажи!$I$2:$I$1001,продажи!$C$2:$C$1001) -> 294.95238 | L143: =продажи!$C565/продажи!$K565-1 -> -0.19648046 | M143: =SUMIFS($C$2:$C$1001,$I$2:$I$1001,I143,$J$2:$J$1001,J143) -> 3507 | N143: =Таблица1[[#This Row],[цена за шт в рублях]]/Таблица1[[#This Row],[средняя стоимость в категории по поставщику.]]-1 -> -0.86541203 | O143: =VLOOKUP(Таблица1[[#This Row],[id клиента]],клиенты!$A$2:$E$435,5,0) -> 44668 | P143: =Таблица1[[#This Row],[дата создания чека]]-Таблица1[[#This Row],[Дата регистрации клента]] -> 740 | Q143: =TODAY() -> 46059 | R143: =(TODAY()-Таблица1[[#This Row],[Дата регистрации клента]])/30 -> 46.366667 | S143: =VLOOKUP(Таблица1[[#This Row],[id клиента]],Таблица8[[id клиента]:[Страна]],7,0) -> Таджикистан
A144: 143 | B144: 81 | C144: 116 | D144: 1 | E144: 116 | F144: 45356 | G144: Азбука Вкуса | H144: 247 | I144: =VLOOKUP(продажи!$B144,товар!$A$1:$C$433,2) -> Чай | J144: =VLOOKUP(B144,товар!$A$1:$C$433,3) -> Тесс | K144: =AVERAGEIF(продажи!$I$2:$I$1001,продажи!$I$2:$I$1001,продажи!$C$2:$C$1001) -> 271.18182 | L144: =продажи!$C144/продажи!$K144-1 -> -0.57224271 | M144: =SUMIFS($C$2:$C$1001,$I$2:$I$1001,I144,$J$2:$J$1001,J144) -> 1127 | N144: =Таблица1[[#This Row],[цена за шт в рублях]]/Таблица1[[#This Row],[средняя стоимость в категории по поставщику.]]-1 -> -0.89707187 | O144: =VLOOKUP(Таблица1[[#This Row],[id клиента]],клиенты!$A$2:$E$435,5,0) -> 44762 | P144: =Таблица1[[#This Row],[дата создания чека]]-Таблица1[[#This Row],[Дата регистрации клента]] -> 594 | Q144: =TODAY() -> 46059 | R144: =(TODAY()-Таблица1[[#This Row],[Дата регистрации клента]])/30 -> 43.233333 | S144: =VLOOKUP(Таблица1[[#This Row],[id клиента]],Таблица8[[id клиента]:[Страна]],7,0) -> Узбекистан
A145: 144 | B145: 4 | C145: 314 | D145: 4 | E145: 1256 | F145: 45336 | G145: Мираторг | H145: 380 | I145: =VLOOKUP(продажи!$B145,товар!$A$1:$C$433,2) -> Рис | J145: =VLOOKUP(B145,товар!$A$1:$C$433,3) -> Белый Злат | K145: =AVERAGEIF(продажи!$I$2:$I$1001,продажи!$I$2:$I$1001,продажи!$C$2:$C$1001) -> 258.375 | L145: =продажи!$C145/продажи!$K145-1 -> 0.21528786 | M145: =SUMIFS($C$2:$C$1001,$I$2:$I$1001,I145,$J$2:$J$1001,J145) -> 4585 | N145: =Таблица1[[#This Row],[цена за шт в рублях]]/Таблица1[[#This Row],[средняя стоимость в категории по поставщику.]]-1 -> -0.93151581 | O145: =VLOOKUP(Таблица1[[#This Row],[id клиента]],клиенты!$A$2:$E$435,5,0) -> 44563 | P145: =Таблица1[[#This Row],[дата создания чека]]-Таблица1[[#This Row],[Дата регистрации клента]] -> 773 | Q145: =TODAY() -> 46059 | R145: =(TODAY()-Таблица1[[#This Row],[Дата регистрации клента]])/30 -> 49.866667 | S145: =VLOOKUP(Таблица1[[#This Row],[id клиента]],Таблица8[[id клиента]:[Страна]],7,0) -> Россия
A146: 145 | B146: 209 | C146: 284 | D146: 5 | E146: 1420 | F146: 45167 | G146: Спар | H146: 75 | I146: =VLOOKUP(продажи!$B146,товар!$A$1:$C$433,2) -> Хлеб | J146: =VLOOKUP(B146,товар!$A$1:$C$433,3) -> Русский Хлеб | K146: =AVERAGEIF(продажи!$I$2:$I$1001,продажи!$I$2:$I$1001,продажи!$C$2:$C$1001) -> 300.31818 | L146: =продажи!$C146/продажи!$K146-1 -> -0.05433631 | M146: =SUMIFS($C$2:$C$1001,$I$2:$I$1001,I146,$J$2:$J$1001,J146) -> 3166 | N146: =Таблица1[[#This Row],[цена за шт в рублях]]/Таблица1[[#This Row],[средняя стоимость в категории по поставщику.]]-1 -> -0.9102969 | O146: =VLOOKUP(Таблица1[[#This Row],[id клиента]],клиенты!$A$2:$E$435,5,0) -> 44796 | P146: =Таблица1[[#This Row],[дата создания чека]]-Таблица1[[#This Row],[Дата регистрации клента]] -> 371 | Q146: =TODAY() -> 46059 | R146: =(TODAY()-Таблица1[[#This Row],[Дата регистрации клента]])/30 -> 42.1 | S146: =VLOOKUP(Таблица1[[#This Row],[id клиента]],Таблица8[[id клиента]:[Страна]],7,0) -> Украина
A147: 146 | B147: 156 | C147: 332 | D147: 1 | E147: 332 | F147: 45069 | G147: Гиперглобус | H147: 356 | I147: =VLOOKUP(продажи!$B147,товар!$A$1:$C$433,2) -> Фрукты | J147: =VLOOKUP(B147,товар!$A$1:$C$433,3) -> Фрукты-Ягоды | K147: =AVERAGEIF(продажи!$I$2:$I$1001,продажи!$I$2:$I$1001,продажи!$C$2:$C$1001) -> 274.16279 | L147: =продажи!$C147/продажи!$K147-1 -> 0.21095937 | M147: =SUMIFS($C$2:$C$1001,$I$2:$I$1001,I147,$J$2:$J$1001,J147) -> 2526 | N147: =Таблица1[[#This Row],[цена за шт в рублях]]/Таблица1[[#This Row],[средняя стоимость в категории по поставщику.]]-1 -> -0.8685669 | O147: =VLOOKUP(Таблица1[[#This Row],[id клиента]],клиенты!$A$2:$E$435,5,0) -> 44570 | P147: =Таблица1[[#This Row],[дата создания чека]]-Таблица1[[#This Row],[Дата регистрации клента]] -> 499 | Q147: =TODAY() -> 46059 | R147: =(TODAY()-Таблица1[[#This Row],[Дата регистрации клента]])/30 -> 49.633333 | S147: =VLOOKUP(Таблица1[[#This Row],[id клиента]],Таблица8[[id клиента]:[Страна]],7,0) -> Таджикистан
A148: 147 | B148: 441 | C148: 239 | D148: 2 | E148: 478 | F148: 45103 | G148: Магнит | H148: 487 | I148: =VLOOKUP(продажи!$B148,товар!$A$1:$C$433,2) -> Чай | J148: =VLOOKUP(B148,товар!$A$1:$C$433,3) -> Lipton | K148: =AVERAGEIF(продажи!$I$2:$I$1001,продажи!$I$2:$I$1001,продажи!$C$2:$C$1001) -> 271.18182 | L148: =продажи!$C148/продажи!$K148-1 -> -0.11867248 | M148: =SUMIFS($C$2:$C$1001,$I$2:$I$1001,I148,$J$2:$J$1001,J148) -> 4943 | N148: =Таблица1[[#This Row],[цена за шт в рублях]]/Таблица1[[#This Row],[средняя стоимость в категории по поставщику.]]-1 -> -0.9516488 | O148: =VLOOKUP(Таблица1[[#This Row],[id клиента]],клиенты!$A$2:$E$435,5,0) -> 44815 | P148: =Таблица1[[#This Row],[дата создания чека]]-Таблица1[[#This Row],[Дата регистрации клента]] -> 288 | Q148: =TODAY() -> 46059 | R148: =(TODAY()-Таблица1[[#This Row],[Дата регистрации клента]])/30 -> 41.466667 | S148: =VLOOKUP(Таблица1[[#This Row],[id клиента]],Таблица8[[id клиента]:[Страна]],7,0) -> Россия
A149: 148 | B149: 180 | C149: 86 | D149: 4 | E149: 344 | F149: 45326 | G149: Гиперглобус | H149: 73 | I149: =VLOOKUP(продажи!$B149,товар!$A$1:$C$433,2) -> Чипсы | J149: =VLOOKUP(B149,товар!$A$1:$C$433,3) -> Русская картошка | K149: =AVERAGEIF(продажи!$I$2:$I$1001,продажи!$I$2:$I$1001,продажи!$C$2:$C$1001) -> 273.72549 | L149: =продажи!$C149/продажи!$K149-1 -> -0.68581662 | M149: =SUMIFS($C$2:$C$1001,$I$2:$I$1001,I149,$J$2:$J$1001,J149) -> 2902 | N149: =Таблица1[[#This Row],[цена за шт в рублях]]/Таблица1[[#This Row],[средняя стоимость в категории по поставщику.]]-1 -> -0.97036527 | O149: =VLOOKUP(Таблица1[[#This Row],[id клиента]],клиенты!$A$2:$E$435,5,0) -> 44665 | P149: =Таблица1[[#This Row],[дата создания чека]]-Таблица1[[#This Row],[Дата регистрации клента]] -> 661 | Q149: =TODAY() -> 46059 | R149: =(TODAY()-Таблица1[[#This Row],[Дата регистрации клента]])/30 -> 46.466667 | S149: =VLOOKUP(Таблица1[[#This Row],[id клиента]],Таблица8[[id клиента]:[Страна]],7,0) -> Украина
A150: 149 | B150: 438 | C150: 154 | D150: 4 | E150: 616 | F150: 45264 | G150: Спар | H150: 139 | I150: =VLOOKUP(продажи!$B150,товар!$A$1:$C$433,2) -> Кофе | J150: =VLOOKUP(B150,товар!$A$1:$C$433,3) -> Nescafe | K150: =AVERAGEIF(продажи!$I$2:$I$1001,продажи!$I$2:$I$1001,продажи!$C$2:$C$1001) -> 249.02381 | L150: =продажи!$C150/продажи!$K150-1 -> -0.38158524 | M150: =SUMIFS($C$2:$C$1001,$I$2:$I$1001,I150,$J$2:$J$1001,J150) -> 2569 | N150: =Таблица1[[#This Row],[цена за шт в рублях]]/Таблица1[[#This Row],[средняя стоимость в категории по поставщику.]]-1 -> -0.9400545 | O150: =VLOOKUP(Таблица1[[#This Row],[id клиента]],клиенты!$A$2:$E$435,5,0) -> 44648 | P150: =Таблица1[[#This Row],[дата создания чека]]-Таблица1[[#This Row],[Дата регистрации клента]] -> 616 | Q150: =TODAY() -> 46059 | R150: =(TODAY()-Таблица1[[#This Row],[Дата регистрации клента]])/30 -> 47.033333 | S150: =VLOOKUP(Таблица1[[#This Row],[id клиента]],Таблица8[[id клиента]:[Страна]],7,0) -> Беларусь
A151: 692 | B151: 474 | C151: 252 | D151: 3 | E151: 756 | F151: 45425 | G151: Карусель | H151: 470 | I151: =VLOOKUP(продажи!$B693,товар!$A$1:$C$433,2) -> Молоко | J151: =VLOOKUP(B151,товар!$A$1:$C$433,3) -> Простоквашино | K151: =AVERAGEIF(продажи!$I$2:$I$1001,продажи!$I$2:$I$1001,продажи!$C$2:$C$1001) -> 294.95238 | L151: =продажи!$C693/продажи!$K693-1 -> -0.75250242 | M151: =SUMIFS($C$2:$C$1001,$I$2:$I$1001,I151,$J$2:$J$1001,J151) -> 3507 | N151: =Таблица1[[#This Row],[цена за шт в рублях]]/Таблица1[[#This Row],[средняя стоимость в категории по поставщику.]]-1 -> -0.92814371 | O151: =VLOOKUP(Таблица1[[#This Row],[id клиента]],клиенты!$A$2:$E$435,5,0) -> 44690 | P151: =Таблица1[[#This Row],[дата создания чека]]-Таблица1[[#This Row],[Дата регистрации клента]] -> 735 | Q151: =TODAY() -> 46059 | R151: =(TODAY()-Таблица1[[#This Row],[Дата регистрации клента]])/30 -> 45.633333 | S151: =VLOOKUP(Таблица1[[#This Row],[id клиента]],Таблица8[[id клиента]:[Страна]],7,0) -> Таджикистан
A152: 119 | B152: 164 | C152: 229 | D152: 3 | E152: 687 | F152: 45343 | G152: О'кей | H152: 16 | I152: =VLOOKUP(продажи!$B120,товар!$A$1:$C$433,2) -> Молоко | J152: =VLOOKUP(B152,товар!$A$1:$C$433,3) -> Беллакт | K152: =AVERAGEIF(продажи!$I$2:$I$1001,продажи!$I$2:$I$1001,продажи!$C$2:$C$1001) -> 294.95238 | L152: =продажи!$C120/продажи!$K120-1 -> -0.1151114 | M152: =SUMIFS($C$2:$C$1001,$I$2:$I$1001,I152,$J$2:$J$1001,J152) -> 3548 | N152: =Таблица1[[#This Row],[цена за шт в рублях]]/Таблица1[[#This Row],[средняя стоимость в категории по поставщику.]]-1 -> -0.9354566 | O152: =VLOOKUP(Таблица1[[#This Row],[id клиента]],клиенты!$A$2:$E$435,5,0) -> 44713 | P152: =Таблица1[[#This Row],[дата создания чека]]-Таблица1[[#This Row],[Дата регистрации клента]] -> 630 | Q152: =TODAY() -> 46059 | R152: =(TODAY()-Таблица1[[#This Row],[Дата регистрации клента]])/30 -> 44.866667 | S152: =VLOOKUP(Таблица1[[#This Row],[id клиента]],Таблица8[[id клиента]:[Страна]],7,0) -> Украина
A153: 152 | B153: 295 | C153: 230 | D153: 4 | E153: 920 | F153: 44990 | G153: Спар | H153: 258 | I153: =VLOOKUP(продажи!$B153,товар!$A$1:$C$433,2) -> Печенье | J153: =VLOOKUP(B153,товар!$A$1:$C$433,3) -> Белогорье | K153: =AVERAGEIF(продажи!$I$2:$I$1001,продажи!$I$2:$I$1001,продажи!$C$2:$C$1001) -> 283.46809 | L153: =продажи!$C153/продажи!$K153-1 -> -0.18862118 | M153: =SUMIFS($C$2:$C$1001,$I$2:$I$1001,I153,$J$2:$J$1001,J153) -> 3493 | N153: =Таблица1[[#This Row],[цена за шт в рублях]]/Таблица1[[#This Row],[средняя стоимость в категории по поставщику.]]-1 -> -0.93415402 | O153: =VLOOKUP(Таблица1[[#This Row],[id клиента]],клиенты!$A$2:$E$435,5,0) -> 44717 | P153: =Таблица1[[#This Row],[дата создания чека]]-Таблица1[[#This Row],[Дата регистрации клента]] -> 273 | Q153: =TODAY() -> 46059 | R153: =(TODAY()-Таблица1[[#This Row],[Дата регистрации клента]])/30 -> 44.733333 | S153: =VLOOKUP(Таблица1[[#This Row],[id клиента]],Таблица8[[id клиента]:[Страна]],7,0) -> Украина
A154: 153 | B154: 204 | C154: 88 | D154: 4 | E154: 352 | F154: 44990 | G154: Магнит | H154: 349 | I154: =VLOOKUP(продажи!$B154,товар!$A$1:$C$433,2) -> Печенье | J154: =VLOOKUP(B154,товар!$A$1:$C$433,3) -> Юбилейное | K154: =AVERAGEIF(продажи!$I$2:$I$1001,продажи!$I$2:$I$1001,продажи!$C$2:$C$1001) -> 283.46809 | L154: =продажи!$C154/продажи!$K154-1 -> -0.68955941 | M154: =SUMIFS($C$2:$C$1001,$I$2:$I$1001,I154,$J$2:$J$1001,J154) -> 2092 | N154: =Таблица1[[#This Row],[цена за шт в рублях]]/Таблица1[[#This Row],[средняя стоимость в категории по поставщику.]]-1 -> -0.95793499 | O154: =VLOOKUP(Таблица1[[#This Row],[id клиента]],клиенты!$A$2:$E$435,5,0) -> 44673 | P154: =Таблица1[[#This Row],[дата создания чека]]-Таблица1[[#This Row],[Дата регистрации клента]] -> 317 | Q154: =TODAY() -> 46059 | R154: =(TODAY()-Таблица1[[#This Row],[Дата регистрации клента]])/30 -> 46.2 | S154: =VLOOKUP(Таблица1[[#This Row],[id клиента]],Таблица8[[id клиента]:[Страна]],7,0) -> Россия
A155: 154 | B155: 399 | C155: 231 | D155: 2 | E155: 462 | F155: 45290 | G155: Ароматный Мир | H155: 325 | I155: =VLOOKUP(продажи!$B155,товар!$A$1:$C$433,2) -> Хлеб | J155: =VLOOKUP(B155,товар!$A$1:$C$433,3) -> Хлебный Дом | K155: =AVERAGEIF(продажи!$I$2:$I$1001,продажи!$I$2:$I$1001,продажи!$C$2:$C$1001) -> 300.31818 | L155: =продажи!$C155/продажи!$K155-1 -> -0.2308158 | M155: =SUMIFS($C$2:$C$1001,$I$2:$I$1001,I155,$J$2:$J$1001,J155) -> 4226 | N155: =Таблица1[[#This Row],[цена за шт в рублях]]/Таблица1[[#This Row],[средняя стоимость в категории по поставщику.]]-1 -> -0.94533838 | O155: =VLOOKUP(Таблица1[[#This Row],[id клиента]],клиенты!$A$2:$E$435,5,0) -> 44875 | P155: =Таблица1[[#This Row],[дата создания чека]]-Таблица1[[#This Row],[Дата регистрации клента]] -> 415 | Q155: =TODAY() -> 46059 | R155: =(TODAY()-Таблица1[[#This Row],[Дата регистрации клента]])/30 -> 39.466667 | S155: =VLOOKUP(Таблица1[[#This Row],[id клиента]],Таблица8[[id клиента]:[Страна]],7,0) -> Таджикистан
A156: 155 | B156: 221 | C156: 477 | D156: 4 | E156: 1908 | F156: 45185 | G156: Мосмарт | H156: 276 | I156: =VLOOKUP(продажи!$B156,товар!$A$1:$C$433,2) -> Чипсы | J156: =VLOOKUP(B156,товар!$A$1:$C$433,3) -> Pringles | K156: =AVERAGEIF(продажи!$I$2:$I$1001,продажи!$I$2:$I$1001,продажи!$C$2:$C$1001) -> 273.72549 | L156: =продажи!$C156/продажи!$K156-1 -> 0.74262178 | M156: =SUMIFS($C$2:$C$1001,$I$2:$I$1001,I156,$J$2:$J$1001,J156) -> 5885 | N156: =Таблица1[[#This Row],[цена за шт в рублях]]/Таблица1[[#This Row],[средняя стоимость в категории по поставщику.]]-1 -> -0.91894647 | O156: =VLOOKUP(Таблица1[[#This Row],[id клиента]],клиенты!$A$2:$E$435,5,0) -> 44632 | P156: =Таблица1[[#This Row],[дата создания чека]]-Таблица1[[#This Row],[Дата регистрации клента]] -> 553 | Q156: =TODAY() -> 46059 | R156: =(TODAY()-Таблица1[[#This Row],[Дата регистрации клента]])/30 -> 47.566667 | S156: =VLOOKUP(Таблица1[[#This Row],[id клиента]],Таблица8[[id клиента]:[Страна]],7,0) -> Таджикистан
A157: 156 | B157: 333 | C157: 74 | D157: 2 | E157: 148 | F157: 45153 | G157: Перекресток | H157: 328 | I157: =VLOOKUP(продажи!$B157,товар!$A$1:$C$433,2) -> Рыба | J157: =VLOOKUP(B157,товар!$A$1:$C$433,3) -> Санта Бремор | K157: =AVERAGEIF(продажи!$I$2:$I$1001,продажи!$I$2:$I$1001,продажи!$C$2:$C$1001) -> 258.51282 | L157: =продажи!$C157/продажи!$K157-1 -> -0.71374727 | M157: =SUMIFS($C$2:$C$1001,$I$2:$I$1001,I157,$J$2:$J$1001,J157) -> 2164 | N157: =Таблица1[[#This Row],[цена за шт в рублях]]/Таблица1[[#This Row],[средняя стоимость в категории по поставщику.]]-1 -> -0.96580407 | O157: =VLOOKUP(Таблица1[[#This Row],[id клиента]],клиенты!$A$2:$E$435,5,0) -> 44568 | P157: =Таблица1[[#This Row],[дата создания чека]]-Таблица1[[#This Row],[Дата регистрации клента]] -> 585 | Q157: =TODAY() -> 46059 | R157: =(TODAY()-Таблица1[[#This Row],[Дата регистрации клента]])/30 -> 49.7 | S157: =VLOOKUP(Таблица1[[#This Row],[id клиента]],Таблица8[[id клиента]:[Страна]],7,0) -> Россия
A158: 926 | B158: 222 | C158: 168 | D158: 3 | E158: 504 | F158: 45313 | G158: Пятерочка | H158: 79 | I158: =VLOOKUP(продажи!$B927,товар!$A$1:$C$433,2) -> Молоко | J158: =VLOOKUP(B158,товар!$A$1:$C$433,3) -> Простоквашино | K158: =AVERAGEIF(продажи!$I$2:$I$1001,продажи!$I$2:$I$1001,продажи!$C$2:$C$1001) -> 294.95238 | L158: =продажи!$C927/продажи!$K927-1 -> 0.45786245 | M158: =SUMIFS($C$2:$C$1001,$I$2:$I$1001,I158,$J$2:$J$1001,J158) -> 3507 | N158: =Таблица1[[#This Row],[цена за шт в рублях]]/Таблица1[[#This Row],[средняя стоимость в категории по поставщику.]]-1 -> -0.95209581 | O158: =VLOOKUP(Таблица1[[#This Row],[id клиента]],клиенты!$A$2:$E$435,5,0) -> 44716 | P158: =Таблица1[[#This Row],[дата создания чека]]-Таблица1[[#This Row],[Дата регистрации клента]] -> 597 | Q158: =TODAY() -> 46059 | R158: =(TODAY()-Таблица1[[#This Row],[Дата регистрации клента]])/30 -> 44.766667 | S158: =VLOOKUP(Таблица1[[#This Row],[id клиента]],Таблица8[[id клиента]:[Страна]],7,0) -> Таджикистан
A159: 158 | B159: 476 | C159: 286 | D159: 2 | E159: 572 | F159: 44973 | G159: Метро | H159: 397 | I159: =VLOOKUP(продажи!$B159,товар!$A$1:$C$433,2) -> Рыба | J159: =VLOOKUP(B159,товар!$A$1:$C$433,3) -> Балтийский берег | K159: =AVERAGEIF(продажи!$I$2:$I$1001,продажи!$I$2:$I$1001,продажи!$C$2:$C$1001) -> 258.51282 | L159: =продажи!$C159/продажи!$K159-1 -> 0.10632811 | M159: =SUMIFS($C$2:$C$1001,$I$2:$I$1001,I159,$J$2:$J$1001,J159) -> 2609 | N159: =Таблица1[[#This Row],[цена за шт в рублях]]/Таблица1[[#This Row],[средняя стоимость в категории по поставщику.]]-1 -> -0.89037946 | O159: =VLOOKUP(Таблица1[[#This Row],[id клиента]],клиенты!$A$2:$E$435,5,0) -> 44728 | P159: =Таблица1[[#This Row],[дата создания чека]]-Таблица1[[#This Row],[Дата регистрации клента]] -> 245 | Q159: =TODAY() -> 46059 | R159: =(TODAY()-Таблица1[[#This Row],[Дата регистрации клента]])/30 -> 44.366667 | S159: =VLOOKUP(Таблица1[[#This Row],[id клиента]],Таблица8[[id клиента]:[Страна]],7,0) -> Беларусь
A160: 159 | B160: 126 | C160: 273 | D160: 3 | E160: 819 | F160: 45051 | G160: Перекресток | H160: 153 | I160: =VLOOKUP(продажи!$B160,товар!$A$1:$C$433,2) -> Сахар | J160: =VLOOKUP(B160,товар!$A$1:$C$433,3) -> Русский сахар | K160: =AVERAGEIF(продажи!$I$2:$I$1001,продажи!$I$2:$I$1001,продажи!$C$2:$C$1001) -> 254.58333 | L160: =продажи!$C160/продажи!$K160-1 -> 0.072340426 | M160: =SUMIFS($C$2:$C$1001,$I$2:$I$1001,I160,$J$2:$J$1001,J160) -> 4988 | N160: =Таблица1[[#This Row],[цена за шт в рублях]]/Таблица1[[#This Row],[средняя стоимость в категории по поставщику.]]-1 -> -0.94526864 | O160: =VLOOKUP(Таблица1[[#This Row],[id клиента]],клиенты!$A$2:$E$435,5,0) -> 44802 | P160: =Таблица1[[#This Row],[дата создания чека]]-Таблица1[[#This Row],[Дата регистрации клента]] -> 249 | Q160: =TODAY() -> 46059 | R160: =(TODAY()-Таблица1[[#This Row],[Дата регистрации клента]])/30 -> 41.9 | S160: =VLOOKUP(Таблица1[[#This Row],[id клиента]],Таблица8[[id клиента]:[Страна]],7,0) -> Россия
A161: 160 | B161: 255 | C161: 279 | D161: 3 | E161: 837 | F161: 45081 | G161: Городской Супермаркет | H161: 286 | I161: =VLOOKUP(продажи!$B161,товар!$A$1:$C$433,2) -> Кофе | J161: =VLOOKUP(B161,товар!$A$1:$C$433,3) -> Nescafe | K161: =AVERAGEIF(продажи!$I$2:$I$1001,продажи!$I$2:$I$1001,продажи!$C$2:$C$1001) -> 249.02381 | L161: =продажи!$C161/продажи!$K161-1 -> 0.1203748 | M161: =SUMIFS($C$2:$C$1001,$I$2:$I$1001,I161,$J$2:$J$1001,J161) -> 2569 | N161: =Таблица1[[#This Row],[цена за шт в рублях]]/Таблица1[[#This Row],[средняя стоимость в категории по поставщику.]]-1 -> -0.89139743 | O161: =VLOOKUP(Таблица1[[#This Row],[id клиента]],клиенты!$A$2:$E$435,5,0) -> 44563 | P161: =Таблица1[[#This Row],[дата создания чека]]-Таблица1[[#This Row],[Дата регистрации клента]] -> 518 | Q161: =TODAY() -> 46059 | R161: =(TODAY()-Таблица1[[#This Row],[Дата регистрации клента]])/30 -> 49.866667 | S161: =VLOOKUP(Таблица1[[#This Row],[id клиента]],Таблица8[[id клиента]:[Страна]],7,0) -> Таджикистан
A162: 161 | B162: 138 | C162: 210 | D162: 2 | E162: 420 | F162: 45012 | G162: Карусель | H162: 14 | I162: =VLOOKUP(продажи!$B162,товар!$A$1:$C$433,2) -> Сыр | J162: =VLOOKUP(B162,товар!$A$1:$C$433,3) -> Сырная долина | K162: =AVERAGEIF(продажи!$I$2:$I$1001,продажи!$I$2:$I$1001,продажи!$C$2:$C$1001) -> 261.03226 | L162: =продажи!$C162/продажи!$K162-1 -> -0.19550173 | M162: =SUMIFS($C$2:$C$1001,$I$2:$I$1001,I162,$J$2:$J$1001,J162) -> 8943 | N162: =Таблица1[[#This Row],[цена за шт в рублях]]/Таблица1[[#This Row],[средняя стоимость в категории по поставщику.]]-1 -> -0.97651795 | O162: =VLOOKUP(Таблица1[[#This Row],[id клиента]],клиенты!$A$2:$E$435,5,0) -> 44775 | P162: =Таблица1[[#This Row],[дата создания чека]]-Таблица1[[#This Row],[Дата регистрации клента]] -> 237 | Q162: =TODAY() -> 46059 | R162: =(TODAY()-Таблица1[[#This Row],[Дата регистрации клента]])/30 -> 42.8 | S162: =VLOOKUP(Таблица1[[#This Row],[id клиента]],Таблица8[[id клиента]:[Страна]],7,0) -> Таджикистан
A163: 162 | B163: 403 | C163: 229 | D163: 1 | E163: 229 | F163: 44991 | G163: Гиперглобус | H163: 32 | I163: =VLOOKUP(продажи!$B163,товар!$A$1:$C$433,2) -> Чай | J163: =VLOOKUP(B163,товар!$A$1:$C$433,3) -> Ахмад | K163: =AVERAGEIF(продажи!$I$2:$I$1001,продажи!$I$2:$I$1001,продажи!$C$2:$C$1001) -> 271.18182 | L163: =продажи!$C163/продажи!$K163-1 -> -0.15554811 | M163: =SUMIFS($C$2:$C$1001,$I$2:$I$1001,I163,$J$2:$J$1001,J163) -> 2433 | N163: =Таблица1[[#This Row],[цена за шт в рублях]]/Таблица1[[#This Row],[средняя стоимость в категории по поставщику.]]-1 -> -0.90587752 | O163: =VLOOKUP(Таблица1[[#This Row],[id клиента]],клиенты!$A$2:$E$435,5,0) -> 44922 | P163: =Таблица1[[#This Row],[дата создания чека]]-Таблица1[[#This Row],[Дата регистрации клента]] -> 69 | Q163: =TODAY() -> 46059 | R163: =(TODAY()-Таблица1[[#This Row],[Дата регистрации клента]])/30 -> 37.9 | S163: =VLOOKUP(Таблица1[[#This Row],[id клиента]],Таблица8[[id клиента]:[Страна]],7,0) -> Узбекистан
A164: 163 | B164: 280 | C164: 192 | D164: 2 | E164: 384 | F164: 45283 | G164: Бристоль | H164: 49 | I164: =VLOOKUP(продажи!$B164,товар!$A$1:$C$433,2) -> Сыр | J164: =VLOOKUP(B164,товар!$A$1:$C$433,3) -> President | K164: =AVERAGEIF(продажи!$I$2:$I$1001,продажи!$I$2:$I$1001,продажи!$C$2:$C$1001) -> 261.03226 | L164: =продажи!$C164/продажи!$K164-1 -> -0.26445872 | M164: =SUMIFS($C$2:$C$1001,$I$2:$I$1001,I164,$J$2:$J$1001,J164) -> 3935 | N164: =Таблица1[[#This Row],[цена за шт в рублях]]/Таблица1[[#This Row],[средняя стоимость в категории по поставщику.]]-1 -> -0.95120712 | O164: =VLOOKUP(Таблица1[[#This Row],[id клиента]],клиенты!$A$2:$E$435,5,0) -> 44672 | P164: =Таблица1[[#This Row],[дата создания чека]]-Таблица1[[#This Row],[Дата регистрации клента]] -> 611 | Q164: =TODAY() -> 46059 | R164: =(TODAY()-Таблица1[[#This Row],[Дата регистрации клента]])/30 -> 46.233333 | S164: =VLOOKUP(Таблица1[[#This Row],[id клиента]],Таблица8[[id клиента]:[Страна]],7,0) -> Таджикистан
A165: 164 | B165: 356 | C165: 373 | D165: 1 | E165: 373 | F165: 45291 | G165: Городской Супермаркет | H165: 115 | I165: =VLOOKUP(продажи!$B165,товар!$A$1:$C$433,2) -> Печенье | J165: =VLOOKUP(B165,товар!$A$1:$C$433,3) -> Посиделкино | K165: =AVERAGEIF(продажи!$I$2:$I$1001,продажи!$I$2:$I$1001,продажи!$C$2:$C$1001) -> 283.46809 | L165: =продажи!$C165/продажи!$K165-1 -> 0.31584478 | M165: =SUMIFS($C$2:$C$1001,$I$2:$I$1001,I165,$J$2:$J$1001,J165) -> 3538 | N165: =Таблица1[[#This Row],[цена за шт в рублях]]/Таблица1[[#This Row],[средняя стоимость в категории по поставщику.]]-1 -> -0.89457321 | O165: =VLOOKUP(Таблица1[[#This Row],[id клиента]],клиенты!$A$2:$E$435,5,0) -> 44832 | P165: =Таблица1[[#This Row],[дата создания чека]]-Таблица1[[#This Row],[Дата регистрации клента]] -> 459 | Q165: =TODAY() -> 46059 | R165: =(TODAY()-Таблица1[[#This Row],[Дата регистрации клента]])/30 -> 40.9 | S165: =VLOOKUP(Таблица1[[#This Row],[id клиента]],Таблица8[[id клиента]:[Страна]],7,0) -> Беларусь
A166: 165 | B166: 41 | C166: 315 | D166: 3 | E166: 945 | F166: 45202 | G166: Пятерочка | H166: 420 | I166: =VLOOKUP(продажи!$B166,товар!$A$1:$C$433,2) -> Рис | J166: =VLOOKUP(B166,товар!$A$1:$C$433,3) -> Агро-Альянс | K166: =AVERAGEIF(продажи!$I$2:$I$1001,продажи!$I$2:$I$1001,продажи!$C$2:$C$1001) -> 258.375 | L166: =продажи!$C166/продажи!$K166-1 -> 0.2191582 | M166: =SUMIFS($C$2:$C$1001,$I$2:$I$1001,I166,$J$2:$J$1001,J166) -> 2225 | N166: =Таблица1[[#This Row],[цена за шт в рублях]]/Таблица1[[#This Row],[средняя стоимость в категории по поставщику.]]-1 -> -0.85842697 | O166: =VLOOKUP(Таблица1[[#This Row],[id клиента]],клиенты!$A$2:$E$435,5,0) -> 44698 | P166: =Таблица1[[#This Row],[дата создания чека]]-Таблица1[[#This Row],[Дата регистрации клента]] -> 504 | Q166: =TODAY() -> 46059 | R166: =(TODAY()-Таблица1[[#This Row],[Дата регистрации клента]])/30 -> 45.366667 | S166: =VLOOKUP(Таблица1[[#This Row],[id клиента]],Таблица8[[id клиента]:[Страна]],7,0) -> Украина
A167: 166 | B167: 379 | C167: 321 | D167: 5 | E167: 1605 | F167: 45032 | G167: Гиперглобус | H167: 47 | I167: =VLOOKUP(продажи!$B167,товар!$A$1:$C$433,2) -> Йогурт | J167: =VLOOKUP(B167,товар!$A$1:$C$433,3) -> Активиа | K167: =AVERAGEIF(продажи!$I$2:$I$1001,продажи!$I$2:$I$1001,продажи!$C$2:$C$1001) -> 263.25424 | L167: =продажи!$C167/продажи!$K167-1 -> 0.21935359 | M167: =SUMIFS($C$2:$C$1001,$I$2:$I$1001,I167,$J$2:$J$1001,J167) -> 1762 | N167: =Таблица1[[#This Row],[цена за шт в рублях]]/Таблица1[[#This Row],[средняя стоимость в категории по поставщику.]]-1 -> -0.81782066 | O167: =VLOOKUP(Таблица1[[#This Row],[id клиента]],клиенты!$A$2:$E$435,5,0) -> 44693 | P167: =Таблица1[[#This Row],[дата создания чека]]-Таблица1[[#This Row],[Дата регистрации клента]] -> 339 | Q167: =TODAY() -> 46059 | R167: =(TODAY()-Таблица1[[#This Row],[Дата регистрации клента]])/30 -> 45.533333 | S167: =VLOOKUP(Таблица1[[#This Row],[id клиента]],Таблица8[[id клиента]:[Страна]],7,0) -> Беларусь
A168: 167 | B168: 282 | C168: 189 | D168: 2 | E168: 378 | F168: 45158 | G168: Гиперглобус | H168: 202 | I168: =VLOOKUP(продажи!$B168,товар!$A$1:$C$433,2) -> Рис | J168: =VLOOKUP(B168,товар!$A$1:$C$433,3) -> Агро-Альянс | K168: =AVERAGEIF(продажи!$I$2:$I$1001,продажи!$I$2:$I$1001,продажи!$C$2:$C$1001) -> 258.375 | L168: =продажи!$C168/продажи!$K168-1 -> -0.26850508 | M168: =SUMIFS($C$2:$C$1001,$I$2:$I$1001,I168,$J$2:$J$1001,J168) -> 2225 | N168: =Таблица1[[#This Row],[цена за шт в рублях]]/Таблица1[[#This Row],[средняя стоимость в категории по поставщику.]]-1 -> -0.91505618 | O168: =VLOOKUP(Таблица1[[#This Row],[id клиента]],клиенты!$A$2:$E$435,5,0) -> 44766 | P168: =Таблица1[[#This Row],[дата создания чека]]-Таблица1[[#This Row],[Дата регистрации клента]] -> 392 | Q168: =TODAY() -> 46059 | R168: =(TODAY()-Таблица1[[#This Row],[Дата регистрации клента]])/30 -> 43.1 | S168: =VLOOKUP(Таблица1[[#This Row],[id клиента]],Таблица8[[id клиента]:[Страна]],7,0) -> Беларусь
A169: 168 | B169: 459 | C169: 405 | D169: 3 | E169: 1215 | F169: 44949 | G169: Городской Супермаркет | H169: 37 | I169: =VLOOKUP(продажи!$B169,товар!$A$1:$C$433,2) -> Крупа | J169: =VLOOKUP(B169,товар!$A$1:$C$433,3) -> Националь | K169: =AVERAGEIF(продажи!$I$2:$I$1001,продажи!$I$2:$I$1001,продажи!$C$2:$C$1001) -> 255.11628 | L169: =продажи!$C169/продажи!$K169-1 -> 0.58751139 | M169: =SUMIFS($C$2:$C$1001,$I$2:$I$1001,I169,$J$2:$J$1001,J169) -> 1920 | N169: =Таблица1[[#This Row],[цена за шт в рублях]]/Таблица1[[#This Row],[средняя стоимость в категории по поставщику.]]-1 -> -0.7890625 | O169: =VLOOKUP(Таблица1[[#This Row],[id клиента]],клиенты!$A$2:$E$435,5,0) -> 44728 | P169: =Таблица1[[#This Row],[дата создания чека]]-Таблица1[[#This Row],[Дата регистрации клента]] -> 221 | Q169: =TODAY() -> 46059 | R169: =(TODAY()-Таблица1[[#This Row],[Дата регистрации клента]])/30 -> 44.366667 | S169: =VLOOKUP(Таблица1[[#This Row],[id клиента]],Таблица8[[id клиента]:[Страна]],7,0) -> Украина
A170: 169 | B170: 402 | C170: 426 | D170: 2 | E170: 852 | F170: 45099 | G170: Седьмой Континент | H170: 366 | I170: =VLOOKUP(продажи!$B170,товар!$A$1:$C$433,2) -> Хлеб | J170: =VLOOKUP(B170,товар!$A$1:$C$433,3) -> Каравай | K170: =AVERAGEIF(продажи!$I$2:$I$1001,продажи!$I$2:$I$1001,продажи!$C$2:$C$1001) -> 300.31818 | L170: =продажи!$C170/продажи!$K170-1 -> 0.41849554 | M170: =SUMIFS($C$2:$C$1001,$I$2:$I$1001,I170,$J$2:$J$1001,J170) -> 3974 | N170: =Таблица1[[#This Row],[цена за шт в рублях]]/Таблица1[[#This Row],[средняя стоимость в категории по поставщику.]]-1 -> -0.89280322 | O170: =VLOOKUP(Таблица1[[#This Row],[id клиента]],клиенты!$A$2:$E$435,5,0) -> 44827 | P170: =Таблица1[[#This Row],[дата создания чека]]-Таблица1[[#This Row],[Дата регистрации клента]] -> 272 | Q170: =TODAY() -> 46059 | R170: =(TODAY()-Таблица1[[#This Row],[Дата регистрации клента]])/30 -> 41.066667 | S170: =VLOOKUP(Таблица1[[#This Row],[id клиента]],Таблица8[[id клиента]:[Страна]],7,0) -> Узбекистан
... A203: 202 | B203: 436 | C203: 291 | D203: 2 | E203: 582 | F203: 45095 | G203: Пятерочка | H203: 385 | I203: =VLOOKUP(продажи!$B203,товар!$A$1:$C$433,2) -> Овощи | J203: =VLOOKUP(B203,товар!$A$1:$C$433,3) -> Гавриш | K203: =AVERAGEIF(продажи!$I$2:$I$1001,продажи!$I$2:$I$1001,продажи!$C$2:$C$1001) -> 250.4878 | L203: =продажи!$C203/продажи!$K203-1 -> 0.1617332 | M203: =SUMIFS($C$2:$C$1001,$I$2:$I$1001,I203,$J$2:$J$1001,J203) -> 2229 | N203: =Таблица1[[#This Row],[цена за шт в рублях]]/Таблица1[[#This Row],[средняя стоимость в категории по поставщику.]]-1 -> -0.86944818 | O203: =VLOOKUP(Таблица1[[#This Row],[id клиента]],клиенты!$A$2:$E$435,5,0) -> 44753 | P203: =Таблица1[[#This Row],[дата создания чека]]-Таблица1[[#This Row],[Дата регистрации клента]] -> 342 | Q203: =TODAY() -> 46059 | R203: =(TODAY()-Таблица1[[#This Row],[Дата регистрации клента]])/30 -> 43.533333 | S203: =VLOOKUP(Таблица1[[#This Row],[id клиента]],Таблица8[[id клиента]:[Страна]],7,0) -> Украина
A204: 847 | B204: 206 | C204: 93 | D204: 2 | E204: 186 | F204: 45154 | G204: Гиперглобус | H204: 155 | I204: =VLOOKUP(продажи!$B848,товар!$A$1:$C$433,2) -> Молоко | J204: =VLOOKUP(B204,товар!$A$1:$C$433,3) -> Домик в деревне | K204: =AVERAGEIF(продажи!$I$2:$I$1001,продажи!$I$2:$I$1001,продажи!$C$2:$C$1001) -> 294.95238 | L204: =продажи!$C848/продажи!$K848-1 -> -0.31514369 | M204: =SUMIFS($C$2:$C$1001,$I$2:$I$1001,I204,$J$2:$J$1001,J204) -> 4946 | N204: =Таблица1[[#This Row],[цена за шт в рублях]]/Таблица1[[#This Row],[средняя стоимость в категории по поставщику.]]-1 -> -0.98119693 | O204: =VLOOKUP(Таблица1[[#This Row],[id клиента]],клиенты!$A$2:$E$435,5,0) -> 44564 | P204: =Таблица1[[#This Row],[дата создания чека]]-Таблица1[[#This Row],[Дата регистрации клента]] -> 590 | Q204: =TODAY() -> 46059 | R204: =(TODAY()-Таблица1[[#This Row],[Дата регистрации клента]])/30 -> 49.833333 | S204: =VLOOKUP(Таблица1[[#This Row],[id клиента]],Таблица8[[id клиента]:[Страна]],7,0) -> Украина
A205: 204 | B205: 361 | C205: 245 | D205: 1 | E205: 245 | F205: 45178 | G205: Магнит | H205: 259 | I205: =VLOOKUP(продажи!$B205,товар!$A$1:$C$433,2) -> Мясо | J205: =VLOOKUP(B205,товар!$A$1:$C$433,3) -> Сава | K205: =AVERAGEIF(продажи!$I$2:$I$1001,продажи!$I$2:$I$1001,продажи!$C$2:$C$1001) -> 271.74545 | L205: =продажи!$C205/продажи!$K205-1 -> -0.098420982 | M205: =SUMIFS($C$2:$C$1001,$I$2:$I$1001,I205,$J$2:$J$1001,J205) -> 3405 | N205: =Таблица1[[#This Row],[цена за шт в рублях]]/Таблица1[[#This Row],[средняя стоимость в категории по поставщику.]]-1 -> -0.92804699 | O205: =VLOOKUP(Таблица1[[#This Row],[id клиента]],клиенты!$A$2:$E$435,5,0) -> 44707 | P205: =Таблица1[[#This Row],[дата создания чека]]-Таблица1[[#This Row],[Дата регистрации клента]] -> 471 | Q205: =TODAY() -> 46059 | R205: =(TODAY()-Таблица1[[#This Row],[Дата регистрации клента]])/30 -> 45.066667 | S205: =VLOOKUP(Таблица1[[#This Row],[id клиента]],Таблица8[[id клиента]:[Страна]],7,0) -> Беларусь
A206: 205 | B206: 226 | C206: 339 | D206: 4 | E206: 1356 | F206: 45251 | G206: Мосмарт | H206: 337 | I206: =VLOOKUP(продажи!$B206,товар!$A$1:$C$433,2) -> Сыр | J206: =VLOOKUP(B206,товар!$A$1:$C$433,3) -> Карат | K206: =AVERAGEIF(продажи!$I$2:$I$1001,продажи!$I$2:$I$1001,продажи!$C$2:$C$1001) -> 261.03226 | L206: =продажи!$C206/продажи!$K206-1 -> 0.29869006 | M206: =SUMIFS($C$2:$C$1001,$I$2:$I$1001,I206,$J$2:$J$1001,J206) -> 2802 | N206: =Таблица1[[#This Row],[цена за шт в рублях]]/Таблица1[[#This Row],[средняя стоимость в категории по поставщику.]]-1 -> -0.87901499 | O206: =VLOOKUP(Таблица1[[#This Row],[id клиента]],клиенты!$A$2:$E$435,5,0) -> 44875 | P206: =Таблица1[[#This Row],[дата создания чека]]-Таблица1[[#This Row],[Дата регистрации клента]] -> 376 | Q206: =TODAY() -> 46059 | R206: =(TODAY()-Таблица1[[#This Row],[Дата регистрации клента]])/30 -> 39.466667 | S206: =VLOOKUP(Таблица1[[#This Row],[id клиента]],Таблица8[[id клиента]:[Страна]],7,0) -> Россия
A207: 206 | B207: 87 | C207: 487 | D207: 1 | E207: 487 | F207: 45019 | G207: Гиперглобус | H207: 172 | I207: =VLOOKUP(продажи!$B207,товар!$A$1:$C$433,2) -> Кофе | J207: =VLOOKUP(B207,товар!$A$1:$C$433,3) -> Jacobs | K207: =AVERAGEIF(продажи!$I$2:$I$1001,продажи!$I$2:$I$1001,продажи!$C$2:$C$1001) -> 249.02381 | L207: =продажи!$C207/продажи!$K207-1 -> 0.95563629 | M207: =SUMIFS($C$2:$C$1001,$I$2:$I$1001,I207,$J$2:$J$1001,J207) -> 5248 | N207: =Таблица1[[#This Row],[цена за шт в рублях]]/Таблица1[[#This Row],[средняя стоимость в категории по поставщику.]]-1 -> -0.90720274 | O207: =VLOOKUP(Таблица1[[#This Row],[id клиента]],клиенты!$A$2:$E$435,5,0) -> 44737 | P207: =Таблица1[[#This Row],[дата создания чека]]-Таблица1[[#This Row],[Дата регистрации клента]] -> 282 | Q207: =TODAY() -> 46059 | R207: =(TODAY()-Таблица1[[#This Row],[Дата регистрации клента]])/30 -> 44.066667 | S207: =VLOOKUP(Таблица1[[#This Row],[id клиента]],Таблица8[[id клиента]:[Страна]],7,0) -> Россия
A208: 207 | B208: 376 | C208: 335 | D208: 5 | E208: 1675 | F208: 44983 | G208: Гиперглобус | H208: 130 | I208: =VLOOKUP(продажи!$B208,товар!$A$1:$C$433,2) -> Конфеты | J208: =VLOOKUP(B208,товар!$A$1:$C$433,3) -> Красный Октябрь | K208: =AVERAGEIF(продажи!$I$2:$I$1001,продажи!$I$2:$I$1001,продажи!$C$2:$C$1001) -> 267.85484 | L208: =продажи!$C208/продажи!$K208-1 -> 0.25067743 | M208: =SUMIFS($C$2:$C$1001,$I$2:$I$1001,I208,$J$2:$J$1001,J208) -> 2189 | N208: =Таблица1[[#This Row],[цена за шт в рублях]]/Таблица1[[#This Row],[средняя стоимость в категории по поставщику.]]-1 -> -0.84696208 | O208: =VLOOKUP(Таблица1[[#This Row],[id клиента]],клиенты!$A$2:$E$435,5,0) -> 44863 | P208: =Таблица1[[#This Row],[дата создания чека]]-Таблица1[[#This Row],[Дата регистрации клента]] -> 120 | Q208: =TODAY() -> 46059 | R208: =(TODAY()-Таблица1[[#This Row],[Дата регистрации клента]])/30 -> 39.866667 | S208: =VLOOKUP(Таблица1[[#This Row],[id клиента]],Таблица8[[id клиента]:[Страна]],7,0) -> Таджикистан
A209: 208 | B209: 255 | C209: 214 | D209: 2 | E209: 428 | F209: 45031 | G209: Спар | H209: 354 | I209: =VLOOKUP(продажи!$B209,товар!$A$1:$C$433,2) -> Кофе | J209: =VLOOKUP(B209,товар!$A$1:$C$433,3) -> Nescafe | K209: =AVERAGEIF(продажи!$I$2:$I$1001,продажи!$I$2:$I$1001,продажи!$C$2:$C$1001) -> 249.02381 | L209: =продажи!$C209/продажи!$K209-1 -> -0.14064442 | M209: =SUMIFS($C$2:$C$1001,$I$2:$I$1001,I209,$J$2:$J$1001,J209) -> 2569 | N209: =Таблица1[[#This Row],[цена за шт в рублях]]/Таблица1[[#This Row],[средняя стоимость в категории по поставщику.]]-1 -> -0.9166991 | O209: =VLOOKUP(Таблица1[[#This Row],[id клиента]],клиенты!$A$2:$E$435,5,0) -> 44811 | P209: =Таблица1[[#This Row],[дата создания чека]]-Таблица1[[#This Row],[Дата регистрации клента]] -> 220 | Q209: =TODAY() -> 46059 | R209: =(TODAY()-Таблица1[[#This Row],[Дата регистрации клента]])/30 -> 41.6 | S209: =VLOOKUP(Таблица1[[#This Row],[id клиента]],Таблица8[[id клиента]:[Страна]],7,0) -> Узбекистан
A210: 209 | B210: 111 | C210: 452 | D210: 4 | E210: 1808 | F210: 44927 | G210: Мосмарт | H210: 329 | I210: =VLOOKUP(продажи!$B210,товар!$A$1:$C$433,2) -> Сахар | J210: =VLOOKUP(B210,товар!$A$1:$C$433,3) -> Сладов | K210: =AVERAGEIF(продажи!$I$2:$I$1001,продажи!$I$2:$I$1001,продажи!$C$2:$C$1001) -> 254.58333 | L210: =продажи!$C210/продажи!$K210-1 -> 0.77545008 | M210: =SUMIFS($C$2:$C$1001,$I$2:$I$1001,I210,$J$2:$J$1001,J210) -> 3604 | N210: =Таблица1[[#This Row],[цена за шт в рублях]]/Таблица1[[#This Row],[средняя стоимость в категории по поставщику.]]-1 -> -0.8745838 | O210: =VLOOKUP(Таблица1[[#This Row],[id клиента]],клиенты!$A$2:$E$435,5,0) -> 44653 | P210: =Таблица1[[#This Row],[дата создания чека]]-Таблица1[[#This Row],[Дата регистрации клента]] -> 274 | Q210: =TODAY() -> 46059 | R210: =(TODAY()-Таблица1[[#This Row],[Дата регистрации клента]])/30 -> 46.866667 | S210: =VLOOKUP(Таблица1[[#This Row],[id клиента]],Таблица8[[id клиента]:[Страна]],7,0) -> Беларусь
A211: 210 | B211: 344 | C211: 172 | D211: 5 | E211: 860 | F211: 45092 | G211: Лента | H211: 186 | I211: =VLOOKUP(продажи!$B211,товар!$A$1:$C$433,2) -> Сок | J211: =VLOOKUP(B211,товар!$A$1:$C$433,3) -> Сады Придонья | K211: =AVERAGEIF(продажи!$I$2:$I$1001,продажи!$I$2:$I$1001,продажи!$C$2:$C$1001) -> 268.60345 | L211: =продажи!$C211/продажи!$K211-1 -> -0.35965081 | M211: =SUMIFS($C$2:$C$1001,$I$2:$I$1001,I211,$J$2:$J$1001,J211) -> 2796 | N211: =Таблица1[[#This Row],[цена за шт в рублях]]/Таблица1[[#This Row],[средняя стоимость в категории по поставщику.]]-1 -> -0.93848355 | O211: =VLOOKUP(Таблица1[[#This Row],[id клиента]],клиенты!$A$2:$E$435,5,0) -> 44914 | P211: =Таблица1[[#This Row],[дата создания чека]]-Таблица1[[#This Row],[Дата регистрации клента]] -> 178 | Q211: =TODAY() -> 46059 | R211: =(TODAY()-Таблица1[[#This Row],[Дата регистрации клента]])/30 -> 38.166667 | S211: =VLOOKUP(Таблица1[[#This Row],[id клиента]],Таблица8[[id клиента]:[Страна]],7,0) -> Беларусь
A212: 211 | B212: 462 | C212: 104 | D212: 4 | E212: 416 | F212: 45105 | G212: Билла | H212: 448 | I212: =VLOOKUP(продажи!$B212,товар!$A$1:$C$433,2) -> Рис | J212: =VLOOKUP(B212,товар!$A$1:$C$433,3) -> Белый Злат | K212: =AVERAGEIF(продажи!$I$2:$I$1001,продажи!$I$2:$I$1001,продажи!$C$2:$C$1001) -> 258.375 | L212: =продажи!$C212/продажи!$K212-1 -> -0.59748428 | M212: =SUMIFS($C$2:$C$1001,$I$2:$I$1001,I212,$J$2:$J$1001,J212) -> 4585 | N212: =Таблица1[[#This Row],[цена за шт в рублях]]/Таблица1[[#This Row],[средняя стоимость в категории по поставщику.]]-1 -> -0.97731734 | O212: =VLOOKUP(Таблица1[[#This Row],[id клиента]],клиенты!$A$2:$E$435,5,0) -> 44770 | P212: =Таблица1[[#This Row],[дата создания чека]]-Таблица1[[#This Row],[Дата регистрации клента]] -> 335 | Q212: =TODAY() -> 46059 | R212: =(TODAY()-Таблица1[[#This Row],[Дата регистрации клента]])/30 -> 42.966667 | S212: =VLOOKUP(Таблица1[[#This Row],[id клиента]],Таблица8[[id клиента]:[Страна]],7,0) -> Россия
A213: 212 | B213: 279 | C213: 433 | D213: 4 | E213: 1732 | F213: 45265 | G213: Седьмой Континент | H213: 377 | I213: =VLOOKUP(продажи!$B213,товар!$A$1:$C$433,2) -> Крупа | J213: =VLOOKUP(B213,товар!$A$1:$C$433,3) -> Увелка | K213: =AVERAGEIF(продажи!$I$2:$I$1001,продажи!$I$2:$I$1001,продажи!$C$2:$C$1001) -> 255.11628 | L213: =продажи!$C213/продажи!$K213-1 -> 0.69726527 | M213: =SUMIFS($C$2:$C$1001,$I$2:$I$1001,I213,$J$2:$J$1001,J213) -> 3023 | N213: =Таблица1[[#This Row],[цена за шт в рублях]]/Таблица1[[#This Row],[средняя стоимость в категории по поставщику.]]-1 -> -0.8567648 | O213: =VLOOKUP(Таблица1[[#This Row],[id клиента]],клиенты!$A$2:$E$435,5,0) -> 44794 | P213: =Таблица1[[#This Row],[дата создания чека]]-Таблица1[[#This Row],[Дата регистрации клента]] -> 471 | Q213: =TODAY() -> 46059 | R213: =(TODAY()-Таблица1[[#This Row],[Дата регистрации клента]])/30 -> 42.166667 | S213: =VLOOKUP(Таблица1[[#This Row],[id клиента]],Таблица8[[id клиента]:[Страна]],7,0) -> Узбекистан
A214: 213 | B214: 322 | C214: 79 | D214: 5 | E214: 395 | F214: 45108 | G214: Карусель | H214: 316 | I214: =VLOOKUP(продажи!$B214,товар!$A$1:$C$433,2) -> Крупа | J214: =VLOOKUP(B214,товар!$A$1:$C$433,3) -> Увелка | K214: =AVERAGEIF(продажи!$I$2:$I$1001,продажи!$I$2:$I$1001,продажи!$C$2:$C$1001) -> 255.11628 | L214: =продажи!$C214/продажи!$K214-1 -> -0.69033728 | M214: =SUMIFS($C$2:$C$1001,$I$2:$I$1001,I214,$J$2:$J$1001,J214) -> 3023 | N214: =Таблица1[[#This Row],[цена за шт в рублях]]/Таблица1[[#This Row],[средняя стоимость в категории по поставщику.]]-1 -> -0.97386702 | O214: =VLOOKUP(Таблица1[[#This Row],[id клиента]],клиенты!$A$2:$E$435,5,0) -> 44787 | P214: =Таблица1[[#This Row],[дата создания чека]]-Таблица1[[#This Row],[Дата регистрации клента]] -> 321 | Q214: =TODAY() -> 46059 | R214: =(TODAY()-Таблица1[[#This Row],[Дата регистрации клента]])/30 -> 42.4 | S214: =VLOOKUP(Таблица1[[#This Row],[id клиента]],Таблица8[[id клиента]:[Страна]],7,0) -> Таджикистан
...

Sheet товар
A1: id товара | B1: категория товара | C1: поставщик
A2: 1 | B2: Крупа | C2: Ярмарка
A3: 3 | B3: Крупа | C3: Ярмарка
A4: 4 | B4: Рис | C4: Белый Злат
A5: 5 | B5: Макароны | C5: Роллтон
A6: 6 | B6: Фрукты | C6: Фрукты-Ягоды
A7: 7 | B7: Сыр | C7: President
A8: 8 | B8: Макароны | C8: Паста Зара
A9: 9 | B9: Йогурт | C9: Чудо
A10: 10 | B10: Сок | C10: Фруктовый сад
A11: 11 | B11: Хлеб | C11: Русский Хлеб
A12: 12 | B12: Макароны | C12: Макфа
A13: 13 | B13: Макароны | C13: Паста Зара
... A433: 499 | B433: Печенье | C433: Посиделкино

Sheet География клиентов
A1: Названия строк | B1: Количество по полю id клиента
A2: Россия | B2: 146
A3: Узбекистан | B3: 85
A4: Украина | B4: 78
A5: Таджикистан | B5: 74
A6: Беларусь | B6: 51
A7: Общий итог | B7: 434
E17: Большинство клиентов из России, меньшинство из Беларси

Sheet Программа лояльности
A3: Названия строк | B3: Количество по полю Программа лояльности клиента
A4: да | B4: 215
A5: нет | B5: 219
A6: Общий итог | B6: 434

Sheet Имена
A3: Названия строк | B3: Количество по полю Имя
A4: (пусто)
A5: Август | B5: 5
A6: Алексей | B6: 5
A7: Аверьян | B7: 5
A8: Алина | B8: 5
A9: Алевтина | B9: 5
A10: Амос | B10: 5
A11: Амвросий | B11: 5
A12: Андрон | B12: 5
A13: Ангелина | B13: 5
A14: Анжелика | B14: 5
A15: Анжелика | B15: 5
A16: Анна | B16: 5
... A18: Анна | B18: 5
A19: Антонина | B19: 5 | G19: 70% имен использутся п 5 раз
A20: Антонина | B20: 5
A21: Арефий | B21: 5
A22: Артемьева | B22: 5
A23: Богдан | B23: 5
A24: Афанасьев | B24: 5
A25: Борислав | B25: 5
A26: Бажен | B26: 5
A27: Вадим | B27: 5
A28: Боян | B28: 5
A29: Викентий | B29: 5
A30: Вадим | B30: 5
A31: Геннадий | B31: 5
... A308: Алевтина | B308: 1

Sheet клиенты
A1: id клиента | B1: номер телефона клиента | C1: ФИО | D1: Программа лояльности клиента | E1: Дата регистрации клиента | F1: Код телефона | G1: Страна | H1: Столбец1 | I1: Имя | J1: Фамилия | K1: Отч | M1: 1 пробел | N1: Втор | O1: Длина | Q1: Имя | R1: Фамилия | S1: Отчество
A2: 249 | B2: +7 974-088-4889 | C2: Абрамов Адриан Фролович | D2: да | E2: 44781 | F2: =LEFT(B2,LEN(B2)-13) -> +7 | G2: =INDEX('коды стран'!$A$2:$A$7, MATCH(F2, 'коды стран'!$B$2:$B$7, 0)) -> Россия | H2: Россия | I2: =LEFT(Таблица8[[#This Row],[ФИО]],(M2-1)) -> Абрамов | J2: =MID(Таблица8[[#This Row],[ФИО]],M2,(N2-M2)) -> Адриан | K2: =RIGHT(Таблица8[[#This Row],[ФИО]],(O2-N2)) -> Фролович | M2: =FIND(" ",Таблица8[[#This Row],[ФИО]],2) -> 8 | N2: =FIND(" ",Таблица8[[#This Row],[ФИО]],(M2+1)) -> 15 | O2: =LEN(Таблица8[[#This Row],[ФИО]]) -> 23 | Q2: =MID(Таблица8[[#This Row],[ФИО]],M2,(N2-M2)) -> Адриан | R2: Абрамов | S2: Фролович
A3: 343 | B3: +380 606-168-8976 | C3: Абрамов Амвросий Богданович | D3: нет | E3: 44874 | F3: =LEFT(B3,LEN(B3)-13) -> +380 | G3: =INDEX('коды стран'!$A$2:$A$7, MATCH(F3, 'коды стран'!$B$2:$B$7, 0)) -> Украина | H3: Украина | I3: =LEFT(Таблица8[[#This Row],[ФИО]],(M3-1)) -> Абрамов | J3: =MID(Таблица8[[#This Row],[ФИО]],M3,(N3-M3)) -> Амвросий | K3: =RIGHT(Таблица8[[#This Row],[ФИО]],(O3-N3)) -> Богданович | M3: =FIND(" ",Таблица8[[#This Row],[ФИО]],2) -> 8 | N3: =FIND(" ",Таблица8[[#This Row],[ФИО]],(M3+1)) -> 17 | O3: =LEN(Таблица8[[#This Row],[ФИО]]) -> 27 | Q3: =MID(Таблица8[[#This Row],[ФИО]],M3,(N3-M3)) -> Амвросий | R3: Абрамов | S3: Богданович
A4: 34 | B4: +992 266-481-3942 | C4: Абрамова Евдокия Егоровна | D4: нет | E4: 44654 | F4: =LEFT(B4,LEN(B4)-13) -> +992 | G4: =INDEX('коды стран'!$A$2:$A$7, MATCH(F4, 'коды стран'!$B$2:$B$7, 0)) -> Таджикистан | H4: Таджикистан | I4: =LEFT(Таблица8[[#This Row],[ФИО]],(M4-1)) -> Абрамова | J4: =MID(Таблица8[[#This Row],[ФИО]],M4,(N4-M4)) -> Евдокия | K4: =RIGHT(Таблица8[[#This Row],[ФИО]],(O4-N4)) -> Егоровна | M4: =FIND(" ",Таблица8[[#This Row],[ФИО]],2) -> 9 | N4: =FIND(" ",Таблица8[[#This Row],[ФИО]],(M4+1)) -> 17 | O4: =LEN(Таблица8[[#This Row],[ФИО]]) -> 25 | Q4: =MID(Таблица8[[#This Row],[ФИО]],M4,(N4-M4)) -> Евдокия | R4: Абрамова | S4: Егоровна
A5: 365 | B5: +375 260-927-0999 | C5: Абрамова Елизавета Эдуардовна | D5: нет | E5: 44841 | F5: =LEFT(B5,LEN(B5)-13) -> +375 | G5: =INDEX('коды стран'!$A$2:$A$7, MATCH(F5, 'коды стран'!$B$2:$B$7, 0)) -> Беларусь | H5: Беларусь | I5: =LEFT(Таблица8[[#This Row],[ФИО]],(M5-1)) -> Абрамова | J5: =MID(Таблица8[[#This Row],[ФИО]],M5,(N5-M5)) -> Елизавета | K5: =RIGHT(Таблица8[[#This Row],[ФИО]],(O5-N5)) -> Эдуардовна | M5: =FIND(" ",Таблица8[[#This Row],[ФИО]],2) -> 9 | N5: =FIND(" ",Таблица8[[#This Row],[ФИО]],(M5+1)) -> 19 | O5: =LEN(Таблица8[[#This Row],[ФИО]]) -> 29 | Q5: =MID(Таблица8[[#This Row],[ФИО]],M5,(N5-M5)) -> Елизавета | R5: Абрамова | S5: Эдуардовна
A6: 413 | B6: +7 063-931-5918 | C6: Август Вячеславович Брагин | D6: нет | E6: 44699 | F6: =LEFT(B6,LEN(B6)-13) -> +7 | G6: =INDEX('коды стран'!$A$2:$A$7, MATCH(F6, 'коды стран'!$B$2:$B$7, 0)) -> Россия | H6: Россия | I6: =LEFT(Таблица8[[#This Row],[ФИО]],(M6-1)) -> Август | J6: =MID(Таблица8[[#This Row],[ФИО]],M6,(N6-M6)) -> Вячеславович | K6: =RIGHT(Таблица8[[#This Row],[ФИО]],(O6-N6)) -> Брагин | M6: =FIND(" ",Таблица8[[#This Row],[ФИО]],2) -> 7 | N6: =FIND(" ",Таблица8[[#This Row],[ФИО]],(M6+1)) -> 20 | O6: =LEN(Таблица8[[#This Row],[ФИО]]) -> 26 | Q6: =LEFT(Таблица8[[#This Row],[ФИО]],(M6-1)) -> Август | R6: Брагин | S6: Вячеславович
A7: 93 | B7: +380 686-730-6702 | C7: Авдеев Олимпий Жанович | D7: нет | E7: 44905 | F7: =LEFT(B7,LEN(B7)-13) -> +380 | G7: =INDEX('коды стран'!$A$2:$A$7, MATCH(F7, 'коды стран'!$B$2:$B$7, 0)) -> Украина | H7: Украина | I7: =LEFT(Таблица8[[#This Row],[ФИО]],(M7-1)) -> Авдеев | J7: =MID(Таблица8[[#This Row],[ФИО]],M7,(N7-M7)) -> Олимпий | K7: =RIGHT(Таблица8[[#This Row],[ФИО]],(O7-N7)) -> Жанович | M7: =FIND(" ",Таблица8[[#This Row],[ФИО]],2) -> 7 | N7: =FIND(" ",Таблица8[[#This Row],[ФИО]],(M7+1)) -> 15 | O7: =LEN(Таблица8[[#This Row],[ФИО]]) -> 22 | Q7: =MID(Таблица8[[#This Row],[ФИО]],M7,(N7-M7)) -> Олимпий | R7: Авдеев | S7: Жанович
A8: 349 | B8: +7 048-020-5515 | C8: Авдеев Филипп Елисеевич | D8: нет | E8: 44673 | F8: =LEFT(B8,LEN(B8)-13) -> +7 | G8: =INDEX('коды стран'!$A$2:$A$7, MATCH(F8, 'коды стран'!$B$2:$B$7, 0)) -> Россия | H8: Россия | I8: =LEFT(Таблица8[[#This Row],[ФИО]],(M8-1)) -> Авдеев | J8: =MID(Таблица8[[#This Row],[ФИО]],M8,(N8-M8)) -> Филипп | K8: =RIGHT(Таблица8[[#This Row],[ФИО]],(O8-N8)) -> Елисеевич | M8: =FIND(" ",Таблица8[[#This Row],[ФИО]],2) -> 7 | N8: =FIND(" ",Таблица8[[#This Row],[ФИО]],(M8+1)) -> 14 | O8: =LEN(Таблица8[[#This Row],[ФИО]]) -> 23 | Q8: =MID(Таблица8[[#This Row],[ФИО]],M8,(N8-M8)) -> Филипп | R8: Авдеев | S8: Елисеевич
A9: 362 | B9: +7 739-924-9444 | C9: Авдей Брониславович Владимиров | D9: нет | E9: 44916 | F9: =LEFT(B9,LEN(B9)-13) -> +7 | G9: =INDEX('коды стран'!$A$2:$A$7, MATCH(F9, 'коды стран'!$B$2:$B$7, 0)) -> Россия | H9: Россия | I9: =LEFT(Таблица8[[#This Row],[ФИО]],(M9-1)) -> Авдей | J9: =MID(Таблица8[[#This Row],[ФИО]],M9,(N9-M9)) -> Брониславович | K9: =RIGHT(Таблица8[[#This Row],[ФИО]],(O9-N9)) -> Владимиров | M9: =FIND(" ",Таблица8[[#This Row],[ФИО]],2) -> 6 | N9: =FIND(" ",Таблица8[[#This Row],[ФИО]],(M9+1)) -> 20 | O9: =LEN(Таблица8[[#This Row],[ФИО]]) -> 30 | Q9: =LEFT(Таблица8[[#This Row],[ФИО]],(M9-1)) -> Авдей | R9: Владимиров | S9: Брониславович
A10: 389 | B10: +7 524-093-8464 | C10: Автоном Терентьевич Филиппов | D10: да | E10: 44876 | F10: =LEFT(B10,LEN(B10)-13) -> +7 | G10: =INDEX('коды стран'!$A$2:$A$7, MATCH(F10, 'коды стран'!$B$2:$B$7, 0)) -> Россия | H10: Россия | I10: =LEFT(Таблица8[[#This Row],[ФИО]],(M10-1)) -> Автоном | J10: =MID(Таблица8[[#This Row],[ФИО]],M10,(N10-M10)) -> Терентьевич | K10: =RIGHT(Таблица8[[#This Row],[ФИО]],(O10-N10)) -> Филиппов | M10: =FIND(" ",Таблица8[[#This Row],[ФИО]],2) -> 8 | N10: =FIND(" ",Таблица8[[#This Row],[ФИО]],(M10+1)) -> 20 | O10: =LEN(Таблица8[[#This Row],[ФИО]]) -> 28 | Q10: =LEFT(Таблица8[[#This Row],[ФИО]],(M10-1)) -> Автоном | R10: Филиппов | S10: Терентьевич
A11: 226 | B11: +7 685-361-2926 | C11: Агап Валерьевич Логинов | D11: да | E11: 44702 | F11: =LEFT(B11,LEN(B11)-13) -> +7 | G11: =INDEX('коды стран'!$A$2:$A$7, MATCH(F11, 'коды стран'!$B$2:$B$7, 0)) -> Россия | H11: Россия | I11: =LEFT(Таблица8[[#This Row],[ФИО]],(M11-1)) -> Агап | J11: =MID(Таблица8[[#This Row],[ФИО]],M11,(N11-M11)) -> Валерьевич | K11: =RIGHT(Таблица8[[#This Row],[ФИО]],(O11-N11)) -> Логинов | M11: =FIND(" ",Таблица8[[#This Row],[ФИО]],2) -> 5 | N11: =FIND(" ",Таблица8[[#This Row],[ФИО]],(M11+1)) -> 16 | O11: =LEN(Таблица8[[#This Row],[ФИО]]) -> 23 | Q11: =LEFT(Таблица8[[#This Row],[ФИО]],(M11-1)) -> Агап | R11: Логинов | S11: Валерьевич
A12: 142 | B12: +7 600-803-0627 | C12: Агата Геннадьевна Колесникова | D12: нет | E12: 44683 | F12: =LEFT(B12,LEN(B12)-13) -> +7 | G12: =INDEX('коды стран'!$A$2:$A$7, MATCH(F12, 'коды стран'!$B$2:$B$7, 0)) -> Россия | H12: Россия | I12: =LEFT(Таблица8[[#This Row],[ФИО]],(M12-1)) -> Агата | J12: =MID(Таблица8[[#This Row],[ФИО]],M12,(N12-M12)) -> Геннадьевна | K12: =RIGHT(Таблица8[[#This Row],[ФИО]],(O12-N12)) -> Колесникова | M12: =FIND(" ",Таблица8[[#This Row],[ФИО]],2) -> 6 | N12: =FIND(" ",Таблица8[[#This Row],[ФИО]],(M12+1)) -> 18 | O12: =LEN(Таблица8[[#This Row],[ФИО]]) -> 29 | Q12: =LEFT(Таблица8[[#This Row],[ФИО]],(M12-1)) -> Агата | R12: Колесникова | S12: Геннадьевна
A13: 443 | B13: +7 210-575-0459 | C13: Агата Олеговна Мартынова | D13: да | E13: 44649 | F13: =LEFT(B13,LEN(B13)-13) -> +7 | G13: =INDEX('коды стран'!$A$2:$A$7, MATCH(F13, 'коды стран'!$B$2:$B$7, 0)) -> Россия | H13: Россия | I13: =LEFT(Таблица8[[#This Row],[ФИО]],(M13-1)) -> Агата | J13: =MID(Таблица8[[#This Row],[ФИО]],M13,(N13-M13)) -> Олеговна | K13: =RIGHT(Таблица8[[#This Row],[ФИО]],(O13-N13)) -> Мартынова | M13: =FIND(" ",Таблица8[[#This Row],[ФИО]],2) -> 6 | N13: =FIND(" ",Таблица8[[#This Row],[ФИО]],(M13+1)) -> 15 | O13: =LEN(Таблица8[[#This Row],[ФИО]]) -> 24 | Q13: =LEFT(Таблица8[[#This Row],[ФИО]],(M13-1)) -> Агата | R13: Мартынова | S13: Олеговна
A14: 332 | B14: +998 350-816-0031 | C14: Агата Юрьевна Галкина | D14: нет | E14: 44858 | F14: =LEFT(B14,LEN(B14)-13) -> +998 | G14: =INDEX('коды стран'!$A$2:$A$7, MATCH(F14, 'коды стран'!$B$2:$B$7, 0)) -> Узбекистан | H14: Узбекистан | I14: =LEFT(Таблица8[[#This Row],[ФИО]],(M14-1)) -> Агата | J14: =MID(Таблица8[[#This Row],[ФИО]],M14,(N14-M14)) -> Юрьевна | K14: =RIGHT(Таблица8[[#This Row],[ФИО]],(O14-N14)) -> Галкина | M14: =FIND(" ",Таблица8[[#This Row],[ФИО]],2) -> 6 | N14: =FIND(" ",Таблица8[[#This Row],[ФИО]],(M14+1)) -> 14 | O14: =LEN(Таблица8[[#This Row],[ФИО]]) -> 21 | Q14: =LEFT(Таблица8[[#This Row],[ФИО]],(M14-1)) -> Агата | R14: Галкина | S14: Юрьевна
A15: 27 | B15: +380 922-338-1312 | C15: Аггей Валентинович Артемьев | D15: нет | E15: 44586 | F15: =LEFT(B15,LEN(B15)-13) -> +380 | G15: =INDEX('коды стран'!$A$2:$A$7, MATCH(F15, 'коды стран'!$B$2:$B$7, 0)) -> Украина | H15: Украина | I15: =LEFT(Таблица8[[#This Row],[ФИО]],(M15-1)) -> Аггей | J15: =MID(Таблица8[[#This Row],[ФИО]],M15,(N15-M15)) -> Валентинович | K15: =RIGHT(Таблица8[[#This Row],[ФИО]],(O15-N15)) -> Артемьев | M15: =FIND(" ",Таблица8[[#This Row],[ФИО]],2) -> 6 | N15: =FIND(" ",Таблица8[[#This Row],[ФИО]],(M15+1)) -> 19 | O15: =LEN(Таблица8[[#This Row],[ФИО]]) -> 27 | Q15: =LEFT(Таблица8[[#This Row],[ФИО]],(M15-1)) -> Аггей | R15: Артемьев | S15: Валентинович
A16: 25 | B16: +992 508-269-1094 | C16: Аггей Терентьевич Волков | D16: да | E16: 44582 | F16: =LEFT(B16,LEN(B16)-13) -> +992 | G16: =INDEX('коды стран'!$A$2:$A$7, MATCH(F16, 'коды стран'!$B$2:$B$7, 0)) -> Таджикистан | H16: Таджикистан | I16: =LEFT(Таблица8[[#This Row],[ФИО]],(M16-1)) -> Аггей | J16: =MID(Таблица8[[#This Row],[ФИО]],M16,(N16-M16)) -> Терентьевич | K16: =RIGHT(Таблица8[[#This Row],[ФИО]],(O16-N16)) -> Волков | M16: =FIND(" ",Таблица8[[#This Row],[ФИО]],2) -> 6 | N16: =FIND(" ",Таблица8[[#This Row],[ФИО]],(M16+1)) -> 18 | O16: =LEN(Таблица8[[#This Row],[ФИО]]) -> 24 | Q16: =LEFT(Таблица8[[#This Row],[ФИО]],(M16-1)) -> Аггей | R16: Волков | S16: Терентьевич
A17: 218 | B17: +998 692-163-4083 | C17: Алевтина Алексеевна Исакова | D17: нет | E17: 44721 | F17: =LEFT(B17,LEN(B17)-13) -> +998 | G17: =INDEX('коды стран'!$A$2:$A$7, MATCH(F17, 'коды стран'!$B$2:$B$7, 0)) -> Узбекистан | H17: Узбекистан | I17: =LEFT(Таблица8[[#This Row],[ФИО]],(M17-1)) -> Алевтина | J17: =MID(Таблица8[[#This Row],[ФИО]],M17,(N17-M17)) -> Алексеевна | K17: =RIGHT(Таблица8[[#This Row],[ФИО]],(O17-N17)) -> Исакова | M17: =FIND(" ",Таблица8[[#This Row],[ФИО]],2) -> 9 | N17: =FIND(" ",Таблица8[[#This Row],[ФИО]],(M17+1)) -> 20 | O17: =LEN(Таблица8[[#This Row],[ФИО]]) -> 27 | Q17: =LEFT(Таблица8[[#This Row],[ФИО]],(M17-1)) -> Алевтина | R17: Исакова | S17: Алексеевна
A18: 341 | B18: +7 456-978-0873 | C18: Алевтина Архиповна Ефимова | D18: нет | E18: 44724 | F18: =LEFT(B18,LEN(B18)-13) -> +7 | G18: =INDEX('коды стран'!$A$2:$A$7, MATCH(F18, 'коды стран'!$B$2:$B$7, 0)) -> Россия | H18: Россия | I18: =LEFT(Таблица8[[#This Row],[ФИО]],(M18-1)) -> Алевтина | J18: =MID(Таблица8[[#This Row],[ФИО]],M18,(N18-M18)) -> Архиповна | K18: =RIGHT(Таблица8[[#This Row],[ФИО]],(O18-N18)) -> Ефимова | M18: =FIND(" ",Таблица8[[#This Row],[ФИО]],2) -> 9 | N18: =FIND(" ",Таблица8[[#This Row],[ФИО]],(M18+1)) -> 19 | O18: =LEN(Таблица8[[#This Row],[ФИО]]) -> 26 | Q18: =LEFT(Таблица8[[#This Row],[ФИО]],(M18-1)) -> Алевтина | R18: Ефимова | S18: Архиповна
A19: 460 | B19: +7 981-245-0102 | C19: Алевтина Егоровна Кузнецова | D19: нет | E19: 44821 | F19: =LEFT(B19,LEN(B19)-13) -> +7 | G19: =INDEX('коды стран'!$A$2:$A$7, MATCH(F19, 'коды стран'!$B$2:$B$7, 0)) -> Россия | H19: Россия | I19: =LEFT(Таблица8[[#This Row],[ФИО]],(M19-1)) -> Алевтина | J19: =MID(Таблица8[[#This Row],[ФИО]],M19,(N19-M19)) -> Егоровна | K19: =RIGHT(Таблица8[[#This Row],[ФИО]],(O19-N19)) -> Кузнецова | M19: =FIND(" ",Таблица8[[#This Row],[ФИО]],2) -> 9 | N19: =FIND(" ",Таблица8[[#This Row],[ФИО]],(M19+1)) -> 18 | O19: =LEN(Таблица8[[#This Row],[ФИО]]) -> 27 | Q19: =LEFT(Таблица8[[#This Row],[ФИО]],(M19-1)) -> Алевтина | R19: Кузнецова | S19: Егоровна
A20: 425 | B20: +998 965-511-3258 | C20: Алевтина Ефимовна Белякова | D20: нет | E20: 44782 | F20: =LEFT(B20,LEN(B20)-13) -> +998 | G20: =INDEX('коды стран'!$A$2:$A$7, MATCH(F20, 'коды стран'!$B$2:$B$7, 0)) -> Узбекистан | H20: Узбекистан | I20: =LEFT(Таблица8[[#This Row],[ФИО]],(M20-1)) -> Алевтина | J20: =MID(Таблица8[[#This Row],[ФИО]],M20,(N20-M20)) -> Ефимовна | K20: =RIGHT(Таблица8[[#This Row],[ФИО]],(O20-N20)) -> Белякова | M20: =FIND(" ",Таблица8[[#This Row],[ФИО]],2) -> 9 | N20: =FIND(" ",Таблица8[[#This Row],[ФИО]],(M20+1)) -> 18 | O20: =LEN(Таблица8[[#This Row],[ФИО]]) -> 26 | Q20: =LEFT(Таблица8[[#This Row],[ФИО]],(M20-1)) -> Алевтина | R20: Белякова | S20: Ефимовна
... A25: 471 | B25: +380 669-437-2066 | C25: Александра Матвеевна Артемьева | D25: да | E25: 44577 | F25: =LEFT(B25,LEN(B25)-13) -> +380 | G25: =INDEX('коды стран'!$A$2:$A$7, MATCH(F25, 'коды стран'!$B$2:$B$7, 0)) -> Украина | H25: Украина | I25: =LEFT(Таблица8[[#This Row],[ФИО]],(M25-1)) -> Александра | J25: =MID(Таблица8[[#This Row],[ФИО]],M25,(N25-M25)) -> Матвеевна | K25: =RIGHT(Таблица8[[#This Row],[ФИО]],(O25-N25)) -> Артемьева | M25: =FIND(" ",Таблица8[[#This Row],[ФИО]],2) -> 11 | N25: =FIND(" ",Таблица8[[#This Row],[ФИО]],(M25+1)) -> 21 | O25: =LEN(Таблица8[[#This Row],[ФИО]]) -> 30 | Q25: =LEFT(Таблица8[[#This Row],[ФИО]],(M25-1)) -> Александра | R25: Артемьева | S25: Матвеевна
A26: 324 | B26: +998 752-893-8536 | C26: Алексеев Касьян Ефимович | D26: нет | E26: 44761 | F26: =LEFT(B26,LEN(B26)-13) -> +998 | G26: =INDEX('коды стран'!$A$2:$A$7, MATCH(F26, 'коды стран'!$B$2:$B$7, 0)) -> Узбекистан | H26: Узбекистан | I26: =LEFT(Таблица8[[#This Row],[ФИО]],(M26-1)) -> Алексеев | J26: =MID(Таблица8[[#This Row],[ФИО]],M26,(N26-M26)) -> Касьян | K26: =RIGHT(Таблица8[[#This Row],[ФИО]],(O26-N26)) -> Ефимович | M26: =FIND(" ",Таблица8[[#This Row],[ФИО]],2) -> 9 | N26: =FIND(" ",Таблица8[[#This Row],[ФИО]],(M26+1)) -> 16 | O26: =LEN(Таблица8[[#This Row],[ФИО]]) -> 24 | Q26: =MID(Таблица8[[#This Row],[ФИО]],M26,(N26-M26)) -> Касьян | R26: Ефимович | S26: Ефимович
A27: 15 | B27: +380 001-347-5456 | C27: Алексей Трифонович Блинов | D27: нет | E27: 44711 | F27: =LEFT(B27,LEN(B27)-13) -> +380 | G27: =INDEX('коды стран'!$A$2:$A$7, MATCH(F27, 'коды стран'!$B$2:$B$7, 0)) -> Украина | H27: Украина | I27: =LEFT(Таблица8[[#This Row],[ФИО]],(M27-1)) -> Алексей | J27: =MID(Таблица8[[#This Row],[ФИО]],M27,(N27-M27)) -> Трифонович | K27: =RIGHT(Таблица8[[#This Row],[ФИО]],(O27-N27)) -> Блинов | M27: =FIND(" ",Таблица8[[#This Row],[ФИО]],2) -> 8 | N27: =FIND(" ",Таблица8[[#This Row],[ФИО]],(M27+1)) -> 19 | O27: =LEN(Таблица8[[#This Row],[ФИО]]) -> 25 | Q27: =LEFT(Таблица8[[#This Row],[ФИО]],(M27-1)) -> Алексей | R27: Блинов | S27: Трифонович
A28: 382 | B28: +375 960-328-1316 | C28: Алина Михайловна Шестакова | D28: да | E28: 44850 | F28: =LEFT(B28,LEN(B28)-13) -> +375 | G28: =INDEX('коды стран'!$A$2:$A$7, MATCH(F28, 'коды стран'!$B$2:$B$7, 0)) -> Беларусь | H28: Беларусь | I28: =LEFT(Таблица8[[#This Row],[ФИО]],(M28-1)) -> Алина | J28: =MID(Таблица8[[#This Row],[ФИО]],M28,(N28-M28)) -> Михайловна | K28: =RIGHT(Таблица8[[#This Row],[ФИО]],(O28-N28)) -> Шестакова | M28: =FIND(" ",Таблица8[[#This Row],[ФИО]],2) -> 6 | N28: =FIND(" ",Таблица8[[#This Row],[ФИО]],(M28+1)) -> 17 | O28: =LEN(Таблица8[[#This Row],[ФИО]]) -> 26 | Q28: =LEFT(Таблица8[[#This Row],[ФИО]],(M28-1)) -> Алина | R28: Шестакова | S28: Михайловна
A29: 67 | B29: +998 090-420-2619 | C29: Алла Геннадьевна Фомина | D29: да | E29: 44731 | F29: =LEFT(B29,LEN(B29)-13) -> +998 | G29: =INDEX('коды стран'!$A$2:$A$7, MATCH(F29, 'коды стран'!$B$2:$B$7, 0)) -> Узбекистан | H29: Узбекистан | I29: =LEFT(Таблица8[[#This Row],[ФИО]],(M29-1)) -> Алла | J29: =MID(Таблица8[[#This Row],[ФИО]],M29,(N29-M29)) -> Геннадьевна | K29: =RIGHT(Таблица8[[#This Row],[ФИО]],(O29-N29)) -> Фомина | M29: =FIND(" ",Таблица8[[#This Row],[ФИО]],2) -> 5 | N29: =FIND(" ",Таблица8[[#This Row],[ФИО]],(M29+1)) -> 17 | O29: =LEN(Таблица8[[#This Row],[ФИО]]) -> 23 | Q29: =LEFT(Таблица8[[#This Row],[ФИО]],(M29-1)) -> Алла | R29: Фомина | S29: Геннадьевна
A30: 108 | B30: +998 313-336-2516 | C30: Алла Рудольфовна Сидорова | D30: да | E30: 44835 | F30: =LEFT(B30,LEN(B30)-13) -> +998 | G30: =INDEX('коды стран'!$A$2:$A$7, MATCH(F30, 'коды стран'!$B$2:$B$7, 0)) -> Узбекистан | H30: Узбекистан | I30: =LEFT(Таблица8[[#This Row],[ФИО]],(M30-1)) -> Алла | J30: =MID(Таблица8[[#This Row],[ФИО]],M30,(N30-M30)) -> Рудольфовна | K30: =RIGHT(Таблица8[[#This Row],[ФИО]],(O30-N30)) -> Сидорова | M30: =FIND(" ",Таблица8[[#This Row],[ФИО]],2) -> 5 | N30: =FIND(" ",Таблица8[[#This Row],[ФИО]],(M30+1)) -> 17 | O30: =LEN(Таблица8[[#This Row],[ФИО]]) -> 25 | Q30: =LEFT(Таблица8[[#This Row],[ФИО]],(M30-1)) -> Алла | R30: Сидорова | S30: Рудольфовна
A31: 40 | B31: +7 875-362-2366 | C31: Амвросий Артемьевич Гаврилов | D31: нет | E31: 44855 | F31: =LEFT(B31,LEN(B31)-13) -> +7 | G31: =INDEX('коды стран'!$A$2:$A$7, MATCH(F31, 'коды стран'!$B$2:$B$7, 0)) -> Россия | H31: Россия | I31: =LEFT(Таблица8[[#This Row],[ФИО]],(M31-1)) -> Амвросий | J31: =MID(Таблица8[[#This Row],[ФИО]],M31,(N31-M31)) -> Артемьевич | K31: =RIGHT(Таблица8[[#This Row],[ФИО]],(O31-N31)) -> Гаврилов | M31: =FIND(" ",Таблица8[[#This Row],[ФИО]],2) -> 9 | N31: =FIND(" ",Таблица8[[#This Row],[ФИО]],(M31+1)) -> 20 | O31: =LEN(Таблица8[[#This Row],[ФИО]]) -> 28 | Q31: =LEFT(Таблица8[[#This Row],[ФИО]],(M31-1)) -> Амвросий | R31: Гаврилов | S31: Артемьевич
A32: 20 | B32: +998 678-480-0704 | C32: Амвросий Игнатович Юдин | D32: нет | E32: 44691 | F32: =LEFT(B32,LEN(B32)-13) -> +998 | G32: =INDEX('коды стран'!$A$2:$A$7, MATCH(F32, 'коды стран'!$B$2:$B$7, 0)) -> Узбекистан | H32: Узбекистан | I32: =LEFT(Таблица8[[#This Row],[ФИО]],(M32-1)) -> Амвросий | J32: =MID(Таблица8[[#This Row],[ФИО]],M32,(N32-M32)) -> Игнатович | K32: =RIGHT(Таблица8[[#This Row],[ФИО]],(O32-N32)) -> Юдин | M32: =FIND(" ",Таблица8[[#This Row],[ФИО]],2) -> 9 | N32: =FIND(" ",Таблица8[[#This Row],[ФИО]],(M32+1)) -> 19 | O32: =LEN(Таблица8[[#This Row],[ФИО]]) -> 23 | Q32: =LEFT(Таблица8[[#This Row],[ФИО]],(M32-1)) -> Амвросий | R32: Юдин | S32: Игнатович
A33: 212 | B33: +998 662-959-7800 | C33: Амос Гордеевич Евсеев | D33: нет | E33: 44815 | F33: =LEFT(B33,LEN(B33)-13) -> +998 | G33: =INDEX('коды стран'!$A$2:$A$7, MATCH(F33, 'коды стран'!$B$2:$B$7, 0)) -> Узбекистан | H33: Узбекистан | I33: =LEFT(Таблица8[[#This Row],[ФИО]],(M33-1)) -> Амос | J33: =MID(Таблица8[[#This Row],[ФИО]],M33,(N33-M33)) -> Гордеевич | K33: =RIGHT(Таблица8[[#This Row],[ФИО]],(O33-N33)) -> Евсеев | M33: =FIND(" ",Таблица8[[#This Row],[ФИО]],2) -> 5 | N33: =FIND(" ",Таблица8[[#This Row],[ФИО]],(M33+1)) -> 15 | O33: =LEN(Таблица8[[#This Row],[ФИО]]) -> 21 | Q33: =LEFT(Таблица8[[#This Row],[ФИО]],(M33-1)) -> Амос | R33: Евсеев | S33: Гордеевич
A34: 144 | B34: +380 960-351-2387 | C34: Анастасия Альбертовна Фролова | D34: да | E34: 44705 | F34: =LEFT(B34,LEN(B34)-13) -> +380 | G34: =INDEX('коды стран'!$A$2:$A$7, MATCH(F34, 'коды стран'!$B$2:$B$7, 0)) -> Украина | H34: Украина | I34: =LEFT(Таблица8[[#This Row],[ФИО]],(M34-1)) -> Анастасия | J34: =MID(Таблица8[[#This Row],[ФИО]],M34,(N34-M34)) -> Альбертовна | K34: =RIGHT(Таблица8[[#This Row],[ФИО]],(O34-N34)) -> Фролова | M34: =FIND(" ",Таблица8[[#This Row],[ФИО]],2) -> 10 | N34: =FIND(" ",Таблица8[[#This Row],[ФИО]],(M34+1)) -> 22 | O34: =LEN(Таблица8[[#This Row],[ФИО]]) -> 29 | Q34: =LEFT(Таблица8[[#This Row],[ФИО]],(M34-1)) -> Анастасия | R34: Фролова | S34: Альбертовна
A35: 432 | B35: +992 976-290-1474 | C35: Анастасия Игоревна Белова | D35: нет | E35: 44718 | F35: =LEFT(B35,LEN(B35)-13) -> +992 | G35: =INDEX('коды стран'!$A$2:$A$7, MATCH(F35, 'коды стран'!$B$2:$B$7, 0)) -> Таджикистан | H35: Таджикистан | I35: =LEFT(Таблица8[[#This Row],[ФИО]],(M35-1)) -> Анастасия | J35: =MID(Таблица8[[#This Row],[ФИО]],M35,(N35-M35)) -> Игоревна | K35: =RIGHT(Таблица8[[#This Row],[ФИО]],(O35-N35)) -> Белова | M35: =FIND(" ",Таблица8[[#This Row],[ФИО]],2) -> 10 | N35: =FIND(" ",Таблица8[[#This Row],[ФИО]],(M35+1)) -> 19 | O35: =LEN(Таблица8[[#This Row],[ФИО]]) -> 25 | Q35: =LEFT(Таблица8[[#This Row],[ФИО]],(M35-1)) -> Анастасия | R35: Белова | S35: Игоревна
A36: 275 | B36: +992 403-930-8580 | C36: Андрон Валерьевич Морозов | D36: нет | E36: 44651 | F36: =LEFT(B36,LEN(B36)-13) -> +992 | G36: =INDEX('коды стран'!$A$2:$A$7, MATCH(F36, 'коды стран'!$B$2:$B$7, 0)) -> Таджикистан | H36: Таджикистан | I36: =LEFT(Таблица8[[#This Row],[ФИО]],(M36-1)) -> Андрон | J36: =MID(Таблица8[[#This Row],[ФИО]],M36,(N36-M36)) -> Валерьевич | K36: =RIGHT(Таблица8[[#This Row],[ФИО]],(O36-N36)) -> Морозов | M36: =FIND(" ",Таблица8[[#This Row],[ФИО]],2) -> 7 | N36: =FIND(" ",Таблица8[[#This Row],[ФИО]],(M36+1)) -> 18 | O36: =LEN(Таблица8[[#This Row],[ФИО]]) -> 25 | Q36: =LEFT(Таблица8[[#This Row],[ФИО]],(M36-1)) -> Андрон | R36: Морозов | S36: Валерьевич
A37: 354 | B37: +998 777-844-5783 | C37: Анжела Ивановна Григорьева | D37: нет | E37: 44811 | F37: =LEFT(B37,LEN(B37)-13) -> +998 | G37: =INDEX('коды стран'!$A$2:$A$7, MATCH(F37, 'коды стран'!$B$2:$B$7, 0)) -> Узбекистан | H37: Узбекистан | I37: =LEFT(Таблица8[[#This Row],[ФИО]],(M37-1)) -> Анжела | J37: =MID(Таблица8[[#This Row],[ФИО]],M37,(N37-M37)) -> Ивановна | K37: =RIGHT(Таблица8[[#This Row],[ФИО]],(O37-N37)) -> Григорьева | M37: =FIND(" ",Таблица8[[#This Row],[ФИО]],2) -> 7 | N37: =FIND(" ",Таблица8[[#This Row],[ФИО]],(M37+1)) -> 16 | O37: =LEN(Таблица8[[#This Row],[ФИО]]) -> 26 | Q37: =LEFT(Таблица8[[#This Row],[ФИО]],(M37-1)) -> Анжела | R37: Григорьева | S37: Ивановна
A38: 269 | B38: +7 858-333-4042 | C38: Анжела Филипповна Новикова | D38: нет | E38: 44720 | F38: =LEFT(B38,LEN(B38)-13) -> +7 | G38: =INDEX('коды стран'!$A$2:$A$7, MATCH(F38, 'коды стран'!$B$2:$B$7, 0)) -> Россия | H38: Россия | I38: =LEFT(Таблица8[[#This Row],[ФИО]],(M38-1)) -> Анжела | J38: =MID(Таблица8[[#This Row],[ФИО]],M38,(N38-M38)) -> Филипповна | K38: =RIGHT(Таблица8[[#This Row],[ФИО]],(O38-N38)) -> Новикова | M38: =FIND(" ",Таблица8[[#This Row],[ФИО]],2) -> 7 | N38: =FIND(" ",Таблица8[[#This Row],[ФИО]],(M38+1)) -> 18 | O38: =LEN(Таблица8[[#This Row],[ФИО]]) -> 26 | Q38: =LEFT(Таблица8[[#This Row],[ФИО]],(M38-1)) -> Анжела | R38: Новикова | S38: Филипповна
... A46: 171 | B46: +7 638-478-8735 | C46: Бажен Дмитриевич Исаков | D46: да | E46: 44710 | F46: =LEFT(B46,LEN(B46)-13) -> +7 | G46: =INDEX('коды стран'!$A$2:$A$7, MATCH(F46, 'коды стран'!$B$2:$B$7, 0)) -> Россия | H46: Россия | I46: =LEFT(Таблица8[[#This Row],[ФИО]],(M46-1)) -> Бажен | J46: =MID(Таблица8[[#This Row],[ФИО]],M46,(N46-M46)) -> Дмитриевич | K46: =RIGHT(Таблица8[[#This Row],[ФИО]],(O46-N46)) -> Исаков | M46: =FIND(" ",Таблица8[[#This Row],[ФИО]],2) -> 6 | N46: =FIND(" ",Таблица8[[#This Row],[ФИО]],(M46+1)) -> 17 | O46: =LEN(Таблица8[[#This Row],[ФИО]]) -> 23 | Q46: =LEFT(Таблица8[[#This Row],[ФИО]],(M46-1)) -> Бажен | R46: Исаков | S46: Дмитриевич
A47: 265 | B47: +998 438-329-1521 | C47: Баранов Эраст Терентьевич | D47: нет | E47: 44756 | F47: =LEFT(B47,LEN(B47)-13) -> +998 | G47: =INDEX('коды стран'!$A$2:$A$7, MATCH(F47, 'коды стран'!$B$2:$B$7, 0)) -> Узбекистан | H47: Узбекистан | I47: =LEFT(Таблица8[[#This Row],[ФИО]],(M47-1)) -> Баранов | J47: =MID(Таблица8[[#This Row],[ФИО]],M47,(N47-M47)) -> Эраст | K47: =RIGHT(Таблица8[[#This Row],[ФИО]],(O47-N47)) -> Терентьевич | M47: =FIND(" ",Таблица8[[#This Row],[ФИО]],2) -> 8 | N47: =FIND(" ",Таблица8[[#This Row],[ФИО]],(M47+1)) -> 14 | O47: =LEN(Таблица8[[#This Row],[ФИО]]) -> 25 | Q47: =MID(Таблица8[[#This Row],[ФИО]],M47,(N47-M47)) -> Эраст | R47: Баранов | S47: Терентьевич
A48: 7 | B48: +7 022-690-6735 | C48: Баранова Раиса Эльдаровна | D48: да | E48: 44893 | F48: =LEFT(B48,LEN(B48)-13) -> +7 | G48: =INDEX('коды стран'!$A$2:$A$7, MATCH(F48, 'коды стран'!$B$2:$B$7, 0)) -> Россия | H48: Россия | I48: =LEFT(Таблица8[[#This Row],[ФИО]],(M48-1)) -> Баранова | J48: =MID(Таблица8[[#This Row],[ФИО]],M48,(N48-M48)) -> Раиса | K48: =RIGHT(Таблица8[[#This Row],[ФИО]],(O48-N48)) -> Эльдаровна | M48: =FIND(" ",Таблица8[[#This Row],[ФИО]],2) -> 9 | N48: =FIND(" ",Таблица8[[#This Row],[ФИО]],(M48+1)) -> 15 | O48: =LEN(Таблица8[[#This Row],[ФИО]]) -> 25 | Q48: =MID(Таблица8[[#This Row],[ФИО]],M48,(N48-M48)) -> Раиса | R48: Баранова | S48: Эльдаровна
A49: 156 | B49: +380 270-120-1119 | C49: Белов Симон Иосипович | D49: да | E49: 44905 | F49: =LEFT(B49,LEN(B49)-13) -> +380 | G49: =INDEX('коды стран'!$A$2:$A$7, MATCH(F49, 'коды стран'!$B$2:$B$7, 0)) -> Украина | H49: Украина | I49: =LEFT(Таблица8[[#This Row],[ФИО]],(M49-1)) -> Белов | J49: =MID(Таблица8[[#This Row],[ФИО]],M49,(N49-M49)) -> Симон | K49: =RIGHT(Таблица8[[#This Row],[ФИО]],(O49-N49)) -> Иосипович | M49: =FIND(" ",Таблица8[[#This Row],[ФИО]],2) -> 6 | N49: =FIND(" ",Таблица8[[#This Row],[ФИО]],(M49+1)) -> 12 | O49: =LEN(Таблица8[[#This Row],[ФИО]]) -> 21 | Q49: =MID(Таблица8[[#This Row],[ФИО]],M49,(N49-M49)) -> Симон | R49: Белов | S49: Иосипович
A50: 16 | B50: +380 828-307-7136 | C50: Белозеров Лука Харлампьевич | D50: нет | E50: 44713 | F50: =LEFT(B50,LEN(B50)-13) -> +380 | G50: =INDEX('коды стран'!$A$2:$A$7, MATCH(F50, 'коды стран'!$B$2:$B$7, 0)) -> Украина | H50: Украина | I50: =LEFT(Таблица8[[#This Row],[ФИО]],(M50-1)) -> Белозеров | J50: =MID(Таблица8[[#This Row],[ФИО]],M50,(N50-M50)) -> Лука | K50: =RIGHT(Таблица8[[#This Row],[ФИО]],(O50-N50)) -> Харлампьевич | M50: =FIND(" ",Таблица8[[#This Row],[ФИО]],2) -> 10 | N50: =FIND(" ",Таблица8[[#This Row],[ФИО]],(M50+1)) -> 15 | O50: =LEN(Таблица8[[#This Row],[ФИО]]) -> 27 | Q50: =MID(Таблица8[[#This Row],[ФИО]],M50,(N50-M50)) -> Лука | R50: Белозеров | S50: Харлампьевич
A51: 95 | B51: +998 662-556-3959 | C51: Белоусова Жанна Кузьминична | D51: нет | E51: 44704 | F51: =LEFT(B51,LEN(B51)-13) -> +998 | G51: =INDEX('коды стран'!$A$2:$A$7, MATCH(F51, 'коды стран'!$B$2:$B$7, 0)) -> Узбекистан | H51: Узбекистан | I51: =LEFT(Таблица8[[#This Row],[ФИО]],(M51-1)) -> Белоусова | J51: =MID(Таблица8[[#This Row],[ФИО]],M51,(N51-M51)) -> Жанна | K51: =RIGHT(Таблица8[[#This Row],[ФИО]],(O51-N51)) -> Кузьминична | M51: =FIND(" ",Таблица8[[#This Row],[ФИО]],2) -> 10 | N51: =FIND(" ",Таблица8[[#This Row],[ФИО]],(M51+1)) -> 16 | O51: =LEN(Таблица8[[#This Row],[ФИО]]) -> 27 | Q51: =MID(Таблица8[[#This Row],[ФИО]],M51,(N51-M51)) -> Жанна | R51: Белоусова | S51: Кузьминична
A52: 39 | B52: +375 226-887-4565 | C52: Бирюков Олимпий Иосифович | D52: да | E52: 44653 | F52: =LEFT(B52,LEN(B52)-13) -> +375 | G52: =INDEX('коды стран'!$A$2:$A$7, MATCH(F52, 'коды стран'!$B$2:$B$7, 0)) -> Беларусь | H52: Беларусь | I52: =LEFT(Таблица8[[#This Row],[ФИО]],(M52-1)) -> Бирюков | J52: =MID(Таблица8[[#This Row],[ФИО]],M52,(N52-M52)) -> Олимпий | K52: =RIGHT(Таблица8[[#This Row],[ФИО]],(O52-N52)) -> Иосифович | M52: =FIND(" ",Таблица8[[#This Row],[ФИО]],2) -> 8 | N52: =FIND(" ",Таблица8[[#This Row],[ФИО]],(M52+1)) -> 16 | O52: =LEN(Таблица8[[#This Row],[ФИО]]) -> 25 | Q52: =MID(Таблица8[[#This Row],[ФИО]],M52,(N52-M52)) -> Олимпий | R52: Бирюков | S52: Иосифович
A53: 147 | B53: +7 412-542-8365 | C53: Бирюкова Агафья Артемовна | D53: да | E53: 44827 | F53: =LEFT(B53,LEN(B53)-13) -> +7 | G53: =INDEX('коды стран'!$A$2:$A$7, MATCH(F53, 'коды стран'!$B$2:$B$7, 0)) -> Россия | H53: Россия | I53: =LEFT(Таблица8[[#This Row],[ФИО]],(M53-1)) -> Бирюкова | J53: =MID(Таблица8[[#This Row],[ФИО]],M53,(N53-M53)) -> Агафья | K53: =RIGHT(Таблица8[[#This Row],[ФИО]],(O53-N53)) -> Артемовна | M53: =FIND(" ",Таблица8[[#This Row],[ФИО]],2) -> 9 | N53: =FIND(" ",Таблица8[[#This Row],[ФИО]],(M53+1)) -> 16 | O53: =LEN(Таблица8[[#This Row],[ФИО]]) -> 25 | Q53: =MID(Таблица8[[#This Row],[ФИО]],M53,(N53-M53)) -> Агафья | R53: Бирюкова | S53: Артемовна
A54: 321 | B54: +992 861-842-9595 | C54: Блинов Натан Всеволодович | D54: нет | E54: 44756 | F54: =LEFT(B54,LEN(B54)-13) -> +992 | G54: =INDEX('коды стран'!$A$2:$A$7, MATCH(F54, 'коды стран'!$B$2:$B$7, 0)) -> Таджикистан | H54: Таджикистан | I54: =LEFT(Таблица8[[#This Row],[ФИО]],(M54-1)) -> Блинов | J54: =MID(Таблица8[[#This Row],[ФИО]],M54,(N54-M54)) -> Натан | K54: =RIGHT(Таблица8[[#This Row],[ФИО]],(O54-N54)) -> Всеволодович | M54: =FIND(" ",Таблица8[[#This Row],[ФИО]],2) -> 7 | N54: =FIND(" ",Таблица8[[#This Row],[ФИО]],(M54+1)) -> 13 | O54: =LEN(Таблица8[[#This Row],[ФИО]]) -> 25 | Q54: =MID(Таблица8[[#This Row],[ФИО]],M54,(N54-M54)) -> Натан | R54: Блинов | S54: Всеволодович
A55: 333 | B55: +7 962-495-5040 | C55: Бобылев Никодим Виленович | D55: да | E55: 44857 | F55: =LEFT(B55,LEN(B55)-13) -> +7 | G55: =INDEX('коды стран'!$A$2:$A$7, MATCH(F55, 'коды стран'!$B$2:$B$7, 0)) -> Россия | H55: Россия | I55: =LEFT(Таблица8[[#This Row],[ФИО]],(M55-1)) -> Бобылев | J55: =MID(Таблица8[[#This Row],[ФИО]],M55,(N55-M55)) -> Никодим | K55: =RIGHT(Таблица8[[#This Row],[ФИО]],(O55-N55)) -> Виленович | M55: =FIND(" ",Таблица8[[#This Row],[ФИО]],2) -> 8 | N55: =FIND(" ",Таблица8[[#This Row],[ФИО]],(M55+1)) -> 16 | O55: =LEN(Таблица8[[#This Row],[ФИО]]) -> 25 | Q55: =MID(Таблица8[[#This Row],[ФИО]],M55,(N55-M55)) -> Никодим | R55: Бобылев | S55: Виленович
A56: 36 | B56: +7 894-636-1225 | C56: Бобылева Анна Мироновна | D56: нет | E56: 44700 | F56: =LEFT(B56,LEN(B56)-13) -> +7 | G56: =INDEX('коды стран'!$A$2:$A$7, MATCH(F56, 'коды стран'!$B$2:$B$7, 0)) -> Россия | H56: Россия | I56: =LEFT(Таблица8[[#This Row],[ФИО]],(M56-1)) -> Бобылева | J56: =MID(Таблица8[[#This Row],[ФИО]],M56,(N56-M56)) -> Анна | K56: =RIGHT(Таблица8[[#This Row],[ФИО]],(O56-N56)) -> Мироновна | M56: =FIND(" ",Таблица8[[#This Row],[ФИО]],2) -> 9 | N56: =FIND(" ",Таблица8[[#This Row],[ФИО]],(M56+1)) -> 14 | O56: =LEN(Таблица8[[#This Row],[ФИО]]) -> 23 | Q56: =MID(Таблица8[[#This Row],[ФИО]],M56,(N56-M56)) -> Анна | R56: Бобылева | S56: Мироновна
A57: 107 | B57: +992 943-140-9489 | C57: Большаков Антип Тихонович | D57: нет | E57: 44744 | F57: =LEFT(B57,LEN(B57)-13) -> +992 | G57: =INDEX('коды стран'!$A$2:$A$7, MATCH(F57, 'коды стран'!$B$2:$B$7, 0)) -> Таджикистан | H57: Таджикистан | I57: =LEFT(Таблица8[[#This Row],[ФИО]],(M57-1)) -> Большаков | J57: =MID(Таблица8[[#This Row],[ФИО]],M57,(N57-M57)) -> Антип | K57: =RIGHT(Таблица8[[#This Row],[ФИО]],(O57-N57)) -> Тихонович | M57: =FIND(" ",Таблица8[[#This Row],[ФИО]],2) -> 10 | N57: =FIND(" ",Таблица8[[#This Row],[ФИО]],(M57+1)) -> 16 | O57: =LEN(Таблица8[[#This Row],[ФИО]]) -> 25 | Q57: =MID(Таблица8[[#This Row],[ФИО]],M57,(N57-M57)) -> Антип | R57: Большаков | S57: Тихонович
A58: 375 | B58: +7 231-022-9731 | C58: Боян Дорофеевич Калашников | D58: да | E58: 44674 | F58: =LEFT(B58,LEN(B58)-13) -> +7 | G58: =INDEX('коды стран'!$A$2:$A$7, MATCH(F58, 'коды стран'!$B$2:$B$7, 0)) -> Россия | H58: Россия | I58: =LEFT(Таблица8[[#This Row],[ФИО]],(M58-1)) -> Боян | J58: =MID(Таблица8[[#This Row],[ФИО]],M58,(N58-M58)) -> Дорофеевич | K58: =RIGHT(Таблица8[[#This Row],[ФИО]],(O58-N58)) -> Калашников | M58: =FIND(" ",Таблица8[[#This Row],[ФИО]],2) -> 5 | N58: =FIND(" ",Таблица8[[#This Row],[ФИО]],(M58+1)) -> 16 | O58: =LEN(Таблица8[[#This Row],[ФИО]]) -> 26 | Q58: =LEFT(Таблица8[[#This Row],[ФИО]],(M58-1)) -> Боян | R58: Калашников | S58: Дорофеевич
A59: 293 | B59: +375 156-538-5529 | C59: Брагин Любомир Гертрудович | D59: да | E59: 44573 | F59: =LEFT(B59,LEN(B59)-13) -> +375 | G59: =INDEX('коды стран'!$A$2:$A$7, MATCH(F59, 'коды стран'!$B$2:$B$7, 0)) -> Беларусь | H59: Беларусь | I59: =LEFT(Таблица8[[#This Row],[ФИО]],(M59-1)) -> Брагин | J59: =MID(Таблица8[[#This Row],[ФИО]],M59,(N59-M59)) -> Любомир | K59: =RIGHT(Таблица8[[#This Row],[ФИО]],(O59-N59)) -> Гертрудович | M59: =FIND(" ",Таблица8[[#This Row],[ФИО]],2) -> 7 | N59: =FIND(" ",Таблица8[[#This Row],[ФИО]],(M59+1)) -> 15 | O59: =LEN(Таблица8[[#This Row],[ФИО]]) -> 26 | Q59: =MID(Таблица8[[#This Row],[ФИО]],M59,(N59-M59)) -> Любомир | R59: Брагин | S59: Гертрудович
A60: 316 | B60: +992 330-173-6947 | C60: Брагина Полина Евгеньевна | D60: да | E60: 44787 | F60: =LEFT(B60,LEN(B60)-13) -> +992 | G60: =INDEX('коды стран'!$A$2:$A$7, MATCH(F60, 'коды стран'!$B$2:$B$7, 0)) -> Таджикистан | H60: Таджикистан | I60: =LEFT(Таблица8[[#This Row],[ФИО]],(M60-1)) -> Брагина | J60: =MID(Таблица8[[#This Row],[ФИО]],M60,(N60-M60)) -> Полина | K60: =RIGHT(Таблица8[[#This Row],[ФИО]],(O60-N60)) -> Евгеньевна | M60: =FIND(" ",Таблица8[[#This Row],[ФИО]],2) -> 8 | N60: =FIND(" ",Таблица8[[#This Row],[ФИО]],(M60+1)) -> 15 | O60: =LEN(Таблица8[[#This Row],[ФИО]]) -> 25 | Q60: =MID(Таблица8[[#This Row],[ФИО]],M60,(N60-M60)) -> Полина | R60: Брагина | S60: Евгеньевна
A61: 380 | B61: +7 669-661-5797 | C61: Бурова Марфа Игоревна | D61: да | E61: 44563 | F61: =LEFT(B61,LEN(B61)-13) -> +7 | G61: =INDEX('коды стран'!$A$2:$A$7, MATCH(F61, 'коды стран'!$B$2:$B$7, 0)) -> Россия | H61: Россия | I61: =LEFT(Таблица8[[#This Row],[ФИО]],(M61-1)) -> Бурова | J61: =MID(Таблица8[[#This Row],[ФИО]],M61,(N61-M61)) -> Марфа | K61: =RIGHT(Таблица8[[#This Row],[ФИО]],(O61-N61)) -> Игоревна | M61: =FIND(" ",Таблица8[[#This Row],[ФИО]],2) -> 7 | N61: =FIND(" ",Таблица8[[#This Row],[ФИО]],(M61+1)) -> 13 | O61: =LEN(Таблица8[[#This Row],[ФИО]]) -> 21 | Q61: =MID(Таблица8[[#This Row],[ФИО]],M61,(N61-M61)) -> Марфа | R61: Бурова | S61: Игоревна
A62: 165 | B62: +992 204-182-8433 | C62: Вадим Артёмович Анисимов | D62: да | E62: 44599 | F62: =LEFT(B62,LEN(B62)-13) -> +992 | G62: =INDEX('коды стран'!$A$2:$A$7, MATCH(F62, 'коды стран'!$B$2:$B$7, 0)) -> Таджикистан | H62: Таджикистан | I62: =LEFT(Таблица8[[#This Row],[ФИО]],(M62-1)) -> Вадим | J62: =MID(Таблица8[[#This Row],[ФИО]],M62,(N62-M62)) -> Артёмович | K62: =RIGHT(Таблица8[[#This Row],[ФИО]],(O62-N62)) -> Анисимов | M62: =FIND(" ",Таблица8[[#This Row],[ФИО]],2) -> 6 | N62: =FIND(" ",Таблица8[[#This Row],[ФИО]],(M62+1)) -> 16 | O62: =LEN(Таблица8[[#This Row],[ФИО]]) -> 24 | Q62: =LEFT(Таблица8[[#This Row],[ФИО]],(M62-1)) -> Вадим | R62: Анисимов | S62: Артёмович
A63: 190 | B63: +375 284-418-1233 | C63: Валентина Захаровна Боброва | D63: нет | E63: 44689 | F63: =LEFT(B63,LEN(B63)-13) -> +375 | G63: =INDEX('коды стран'!$A$2:$A$7, MATCH(F63, 'коды стран'!$B$2:$B$7, 0)) -> Беларусь | H63: Беларусь | I63: =LEFT(Таблица8[[#This Row],[ФИО]],(M63-1)) -> Валентина | J63: =MID(Таблица8[[#This Row],[ФИО]],M63,(N63-M63)) -> Захаровна | K63: =RIGHT(Таблица8[[#This Row],[ФИО]],(O63-N63)) -> Боброва | M63: =FIND(" ",Таблица8[[#This Row],[ФИО]],2) -> 10 | N63: =FIND(" ",Таблица8[[#This Row],[ФИО]],(M63+1)) -> 20 | O63: =LEN(Таблица8[[#This Row],[ФИО]]) -> 27 | Q63: =LEFT(Таблица8[[#This Row],[ФИО]],(M63-1)) -> Валентина | R63: Боброва | S63: Захаровна
A64: 17 | B64: +992 124-441-2478 | C64: Валентина Кирилловна Семенова | D64: нет | E64: 44877 | F64: =LEFT(B64,LEN(B64)-13) -> +992 | G64: =INDEX('коды стран'!$A$2:$A$7, MATCH(F64, 'коды стран'!$B$2:$B$7, 0)) -> Таджикистан | H64: Таджикистан | I64: =LEFT(Таблица8[[#This Row],[ФИО]],(M64-1)) -> Валентина | J64: =MID(Таблица8[[#This Row],[ФИО]],M64,(N64-M64)) -> Кирилловна | K64: =RIGHT(Таблица8[[#This Row],[ФИО]],(O64-N64)) -> Семенова | M64: =FIND(" ",Таблица8[[#This Row],[ФИО]],2) -> 10 | N64: =FIND(" ",Таблица8[[#This Row],[ФИО]],(M64+1)) -> 21 | O64: =LEN(Таблица8[[#This Row],[ФИО]]) -> 29 | Q64: =LEFT(Таблица8[[#This Row],[ФИО]],(M64-1)) -> Валентина | R64: Семенова | S64: Кирилловна
A65: 457 | B65: +992 644-743-9326 | C65: Валерия Владимировна Медведева | D65: нет | E65: 44595 | F65: =LEFT(B65,LEN(B65)-13) -> +992 | G65: =INDEX('коды стран'!$A$2:$A$7, MATCH(F65, 'коды стран'!$B$2:$B$7, 0)) -> Таджикистан | H65: Таджикистан | I65: =LEFT(Таблица8[[#This Row],[ФИО]],(M65-1)) -> Валерия | J65: =MID(Таблица8[[#This Row],[ФИО]],M65,(N65-M65)) -> Владимировна | K65: =RIGHT(Таблица8[[#This Row],[ФИО]],(O65-N65)) -> Медведева | M65: =FIND(" ",Таблица8[[#This Row],[ФИО]],2) -> 8 | N65: =FIND(" ",Таблица8[[#This Row],[ФИО]],(M65+1)) -> 21 | O65: =LEN(Таблица8[[#This Row],[ФИО]]) -> 30 | Q65: =LEFT(Таблица8[[#This Row],[ФИО]],(M65-1)) -> Валерия | R65: Медведева | S65: Владимировна
A66: 175 | B66: +7 670-667-8381 | C66: Валерия Семеновна Потапова | D66: нет | E66: 44565 | F66: =LEFT(B66,LEN(B66)-13) -> +7 | G66: =INDEX('коды стран'!$A$2:$A$7, MATCH(F66, 'коды стран'!$B$2:$B$7, 0)) -> Россия | H66: Россия | I66: =LEFT(Таблица8[[#This Row],[ФИО]],(M66-1)) -> Валерия | J66: =MID(Таблица8[[#This Row],[ФИО]],M66,(N66-M66)) -> Семеновна | K66: =RIGHT(Таблица8[[#This Row],[ФИО]],(O66-N66)) -> Потапова | M66: =FIND(" ",Таблица8[[#This Row],[ФИО]],2) -> 8 | N66: =FIND(" ",Таблица8[[#This Row],[ФИО]],(M66+1)) -> 18 | O66: =LEN(Таблица8[[#This Row],[ФИО]]) -> 26 | Q66: =LEFT(Таблица8[[#This Row],[ФИО]],(M66-1)) -> Валерия | R66: Потапова | S66: Семеновна
A67: 497 | B67: +998 247-862-3690 | C67: Валерьян Федосеевич Цветков | D67: нет | E67: 44826 | F67: =LEFT(B67,LEN(B67)-13) -> +998 | G67: =INDEX('коды стран'!$A$2:$A$7, MATCH(F67, 'коды стран'!$B$2:$B$7, 0)) -> Узбекистан | H67: Узбекистан | I67: =LEFT(Таблица8[[#This Row],[ФИО]],(M67-1)) -> Валерьян | J67: =MID(Таблица8[[#This Row],[ФИО]],M67,(N67-M67)) -> Федосеевич | K67: =RIGHT(Таблица8[[#This Row],[ФИО]],(O67-N67)) -> Цветков | M67: =FIND(" ",Таблица8[[#This Row],[ФИО]],2) -> 9 | N67: =FIND(" ",Таблица8[[#This Row],[ФИО]],(M67+1)) -> 20 | O67: =LEN(Таблица8[[#This Row],[ФИО]]) -> 27 | Q67: =LEFT(Таблица8[[#This Row],[ФИО]],(M67-1)) -> Валерьян | R67: Цветков | S67: Федосеевич
A68: 258 | B68: +380 174-160-6456 | C68: Василиса Леоновна Назарова | D68: да | E68: 44717 | F68: =LEFT(B68,LEN(B68)-13) -> +380 | G68: =INDEX('коды стран'!$A$2:$A$7, MATCH(F68, 'коды стран'!$B$2:$B$7, 0)) -> Украина | H68: Украина | I68: =LEFT(Таблица8[[#This Row],[ФИО]],(M68-1)) -> Василиса | J68: =MID(Таблица8[[#This Row],[ФИО]],M68,(N68-M68)) -> Леоновна | K68: =RIGHT(Таблица8[[#This Row],[ФИО]],(O68-N68)) -> Назарова | M68: =FIND(" ",Таблица8[[#This Row],[ФИО]],2) -> 9 | N68: =FIND(" ",Таблица8[[#This Row],[ФИО]],(M68+1)) -> 18 | O68: =LEN(Таблица8[[#This Row],[ФИО]]) -> 26 | Q68: =LEFT(Таблица8[[#This Row],[ФИО]],(M68-1)) -> Василиса | R68: Назарова | S68: Леоновна
A69: 325 | B69: +992 979-262-5049 | C69: Васильев Милован Георгиевич | D69: нет | E69: 44875 | F69: =LEFT(B69,LEN(B69)-13) -> +992 | G69: =INDEX('коды стран'!$A$2:$A$7, MATCH(F69, 'коды стран'!$B$2:$B$7, 0)) -> Таджикистан | H69: Таджикистан | I69: =LEFT(Таблица8[[#This Row],[ФИО]],(M69-1)) -> Васильев | J69: =MID(Таблица8[[#This Row],[ФИО]],M69,(N69-M69)) -> Милован | K69: =RIGHT(Таблица8[[#This Row],[ФИО]],(O69-N69)) -> Георгиевич | M69: =FIND(" ",Таблица8[[#This Row],[ФИО]],2) -> 9 | N69: =FIND(" ",Таблица8[[#This Row],[ФИО]],(M69+1)) -> 17 | O69: =LEN(Таблица8[[#This Row],[ФИО]]) -> 27 | Q69: =MID(Таблица8[[#This Row],[ФИО]],M69,(N69-M69)) -> Милован | R69: Васильев | S69: Георгиевич
A70: 79 | B70: +992 654-311-2893 | C70: Васильева Анжелика Наумовна | D70: нет | E70: 44716 | F70: =LEFT(B70,LEN(B70)-13) -> +992 | G70: =INDEX('коды стран'!$A$2:$A$7, MATCH(F70, 'коды стран'!$B$2:$B$7, 0)) -> Таджикистан | H70: Таджикистан | I70: =LEFT(Таблица8[[#This Row],[ФИО]],(M70-1)) -> Васильева | J70: =MID(Таблица8[[#This Row],[ФИО]],M70,(N70-M70)) -> Анжелика | K70: =RIGHT(Таблица8[[#This Row],[ФИО]],(O70-N70)) -> Наумовна | M70: =FIND(" ",Таблица8[[#This Row],[ФИО]],2) -> 10 | N70: =FIND(" ",Таблица8[[#This Row],[ФИО]],(M70+1)) -> 19 | O70: =LEN(Таблица8[[#This Row],[ФИО]]) -> 27 | Q70: =MID(Таблица8[[#This Row],[ФИО]],M70,(N70-M70)) -> Анжелика | R70: Васильева | S70: Наумовна
A71: 120 | B71: +7 225-063-9920 | C71: Велимир Игоревич Макаров | D71: да | E71: 44691 | F71: =LEFT(B71,LEN(B71)-13) -> +7 | G71: =INDEX('коды стран'!$A$2:$A$7, MATCH(F71, 'коды стран'!$B$2:$B$7, 0)) -> Россия | H71: Россия | I71: =LEFT(Таблица8[[#This Row],[ФИО]],(M71-1)) -> Велимир | J71: =MID(Таблица8[[#This Row],[ФИО]],M71,(N71-M71)) -> Игоревич | K71: =RIGHT(Таблица8[[#This Row],[ФИО]],(O71-N71)) -> Макаров | M71: =FIND(" ",Таблица8[[#This Row],[ФИО]],2) -> 8 | N71: =FIND(" ",Таблица8[[#This Row],[ФИО]],(M71+1)) -> 17 | O71: =LEN(Таблица8[[#This Row],[ФИО]]) -> 24 | Q71: =LEFT(Таблица8[[#This Row],[ФИО]],(M71-1)) -> Велимир | R71: Макаров | S71: Игоревич
A72: 253 | B72: +375 796-304-7865 | C72: Вера Георгиевна Некрасова | D72: да | E72: 44750 | F72: =LEFT(B72,LEN(B72)-13) -> +375 | G72: =INDEX('коды стран'!$A$2:$A$7, MATCH(F72, 'коды стран'!$B$2:$B$7, 0)) -> Беларусь | H72: Беларусь | I72: =LEFT(Таблица8[[#This Row],[ФИО]],(M72-1)) -> Вера | J72: =MID(Таблица8[[#This Row],[ФИО]],M72,(N72-M72)) -> Георгиевна | K72: =RIGHT(Таблица8[[#This Row],[ФИО]],(O72-N72)) -> Некрасова | M72: =FIND(" ",Таблица8[[#This Row],[ФИО]],2) -> 5 | N72: =FIND(" ",Таблица8[[#This Row],[ФИО]],(M72+1)) -> 16 | O72: =LEN(Таблица8[[#This Row],[ФИО]]) -> 25 | Q72: =LEFT(Таблица8[[#This Row],[ФИО]],(M72-1)) -> Вера | R72: Некрасова | S72: Георгиевна
A73: 391 | B73: +992 638-653-7931 | C73: Вероника Геннадьевна Воронова | D73: да | E73: 44675 | F73: =LEFT(B73,LEN(B73)-13) -> +992 | G73: =INDEX('коды стран'!$A$2:$A$7, MATCH(F73, 'коды стран'!$B$2:$B$7, 0)) -> Таджикистан | H73: Таджикистан | I73: =LEFT(Таблица8[[#This Row],[ФИО]],(M73-1)) -> Вероника | J73: =MID(Таблица8[[#This Row],[ФИО]],M73,(N73-M73)) -> Геннадьевна | K73: =RIGHT(Таблица8[[#This Row],[ФИО]],(O73-N73)) -> Воронова | M73: =FIND(" ",Таблица8[[#This Row],[ФИО]],2) -> 9 | N73: =FIND(" ",Таблица8[[#This Row],[ФИО]],(M73+1)) -> 21 | O73: =LEN(Таблица8[[#This Row],[ФИО]]) -> 29 | Q73: =LEFT(Таблица8[[#This Row],[ФИО]],(M73-1)) -> Вероника | R73: Воронова | S73: Геннадьевна
A74: 223 | B74: +380 835-708-4433 | C74: Вероника Евгеньевна Федосеева | D74: да | E74: 44893 | F74: =LEFT(B74,LEN(B74)-13) -> +380 | G74: =INDEX('коды стран'!$A$2:$A$7, MATCH(F74, 'коды стран'!$B$2:$B$7, 0)) -> Украина | H74: Украина | I74: =LEFT(Таблица8[[#This Row],[ФИО]],(M74-1)) -> Вероника | J74: =MID(Таблица8[[#This Row],[ФИО]],M74,(N74-M74)) -> Евгеньевна | K74: =RIGHT(Таблица8[[#This Row],[ФИО]],(O74-N74)) -> Федосеева | M74: =FIND(" ",Таблица8[[#This Row],[ФИО]],2) -> 9 | N74: =FIND(" ",Таблица8[[#This Row],[ФИО]],(M74+1)) -> 20 | O74: =LEN(Таблица8[[#This Row],[ФИО]]) -> 29 | Q74: =LEFT(Таблица8[[#This Row],[ФИО]],(M74-1)) -> Вероника | R74: Федосеева | S74: Евгеньевна
A75: 463 | B75: +380 286-003-5332 | C75: Вероника Руслановна Ефремова | D75: нет | E75: 44869 | F75: =LEFT(B75,LEN(B75)-13) -> +380 | G75: =INDEX('коды стран'!$A$2:$A$7, MATCH(F75, 'коды стран'!$B$2:$B$7, 0)) -> Украина | H75: Украина | I75: =LEFT(Таблица8[[#This Row],[ФИО]],(M75-1)) -> Вероника | J75: =MID(Таблица8[[#This Row],[ФИО]],M75,(N75-M75)) -> Руслановна | K75: =RIGHT(Таблица8[[#This Row],[ФИО]],(O75-N75)) -> Ефремова | M75: =FIND(" ",Таблица8[[#This Row],[ФИО]],2) -> 9 | N75: =FIND(" ",Таблица8[[#This Row],[ФИО]],(M75+1)) -> 20 | O75: =LEN(Таблица8[[#This Row],[ФИО]]) -> 28 | Q75: =LEFT(Таблица8[[#This Row],[ФИО]],(M75-1)) -> Вероника | R75: Ефремова | S75: Руслановна
A76: 152 | B76: +375 678-304-0891 | C76: Вероника Сергеевна Блинова | D76: нет | E76: 44791 | F76: =LEFT(B76,LEN(B76)-13) -> +375 | G76: =INDEX('коды стран'!$A$2:$A$7, MATCH(F76, 'коды стран'!$B$2:$B$7, 0)) -> Беларусь | H76: Беларусь | I76: =LEFT(Таблица8[[#This Row],[ФИО]],(M76-1)) -> Вероника | J76: =MID(Таблица8[[#This Row],[ФИО]],M76,(N76-M76)) -> Сергеевна | K76: =RIGHT(Таблица8[[#This Row],[ФИО]],(O76-N76)) -> Блинова | M76: =FIND(" ",Таблица8[[#This Row],[ФИО]],2) -> 9 | N76: =FIND(" ",Таблица8[[#This Row],[ФИО]],(M76+1)) -> 19 | O76: =LEN(Таблица8[[#This Row],[ФИО]]) -> 26 | Q76: =LEFT(Таблица8[[#This Row],[ФИО]],(M76-1)) -> Вероника | R76: Блинова | S76: Сергеевна
A77: 130 | B77: +992 326-136-2416 | C77: Виктор Жанович Никифоров | D77: нет | E77: 44863 | F77: =LEFT(B77,LEN(B77)-13) -> +992 | G77: =INDEX('коды стран'!$A$2:$A$7, MATCH(F77, 'коды стран'!$B$2:$B$7, 0)) -> Таджикистан | H77: Таджикистан | I77: =LEFT(Таблица8[[#This Row],[ФИО]],(M77-1)) -> Виктор | J77: =MID(Таблица8[[#This Row],[ФИО]],M77,(N77-M77)) -> Жанович | K77: =RIGHT(Таблица8[[#This Row],[ФИО]],(O77-N77)) -> Никифоров | M77: =FIND(" ",Таблица8[[#This Row],[ФИО]],2) -> 7 | N77: =FIND(" ",Таблица8[[#This Row],[ФИО]],(M77+1)) -> 15 | O77: =LEN(Таблица8[[#This Row],[ФИО]]) -> 24 | Q77: =LEFT(Таблица8[[#This Row],[ФИО]],(M77-1)) -> Виктор | R77: Никифоров | S77: Жанович
A78: 423 | B78: +375 074-074-0170 | C78: Виктор Марсович Игнатов | D78: нет | E78: 44841 | F78: =LEFT(B78,LEN(B78)-13) -> +375 | G78: =INDEX('коды стран'!$A$2:$A$7, MATCH(F78, 'коды стран'!$B$2:$B$7, 0)) -> Беларусь | H78: Беларусь | I78: =LEFT(Таблица8[[#This Row],[ФИО]],(M78-1)) -> Виктор | J78: =MID(Таблица8[[#This Row],[ФИО]],M78,(N78-M78)) -> Марсович | K78: =RIGHT(Таблица8[[#This Row],[ФИО]],(O78-N78)) -> Игнатов | M78: =FIND(" ",Таблица8[[#This Row],[ФИО]],2) -> 7 | N78: =FIND(" ",Таблица8[[#This Row],[ФИО]],(M78+1)) -> 16 | O78: =LEN(Таблица8[[#This Row],[ФИО]]) -> 23 | Q78: =LEFT(Таблица8[[#This Row],[ФИО]],(M78-1)) -> Виктор | R78: Игнатов | S78: Марсович
A79: 163 | B79: +998 436-367-6830 | C79: Виктория Ильинична Соколова | D79: да | E79: 44571 | F79: =LEFT(B79,LEN(B79)-13) -> +998 | G79: =INDEX('коды стран'!$A$2:$A$7, MATCH(F79, 'коды стран'!$B$2:$B$7, 0)) -> Узбекистан | H79: Узбекистан | I79: =LEFT(Таблица8[[#This Row],[ФИО]],(M79-1)) -> Виктория | J79: =MID(Таблица8[[#This Row],[ФИО]],M79,(N79-M79)) -> Ильинична | K79: =RIGHT(Таблица8[[#This Row],[ФИО]],(O79-N79)) -> Соколова | M79: =FIND(" ",Таблица8[[#This Row],[ФИО]],2) -> 9 | N79: =FIND(" ",Таблица8[[#This Row],[ФИО]],(M79+1)) -> 19 | O79: =LEN(Таблица8[[#This Row],[ФИО]]) -> 27 | Q79: =LEFT(Таблица8[[#This Row],[ФИО]],(M79-1)) -> Виктория | R79: Соколова | S79: Ильинична
A80: 377 | B80: +998 643-985-0175 | C80: Виктория Наумовна Никитина | D80: нет | E80: 44794 | F80: =LEFT(B80,LEN(B80)-13) -> +998 | G80: =INDEX('коды стран'!$A$2:$A$7, MATCH(F80, 'коды стран'!$B$2:$B$7, 0)) -> Узбекистан | H80: Узбекистан | I80: =LEFT(Таблица8[[#This Row],[ФИО]],(M80-1)) -> Виктория | J80: =MID(Таблица8[[#This Row],[ФИО]],M80,(N80-M80)) -> Наумовна | K80: =RIGHT(Таблица8[[#This Row],[ФИО]],(O80-N80)) -> Никитина | M80: =FIND(" ",Таблица8[[#This Row],[ФИО]],2) -> 9 | N80: =FIND(" ",Таблица8[[#This Row],[ФИО]],(M80+1)) -> 18 | O80: =LEN(Таблица8[[#This Row],[ФИО]]) -> 26 | Q80: =LEFT(Таблица8[[#This Row],[ФИО]],(M80-1)) -> Виктория | R80: Никитина | S80: Наумовна
A81: 422 | B81: +380 633-205-1404 | C81: Виноградов Карл Алексеевич | D81: нет | E81: 44784 | F81: =LEFT(B81,LEN(B81)-13) -> +380 | G81: =INDEX('коды стран'!$A$2:$A$7, MATCH(F81, 'коды стран'!$B$2:$B$7, 0)) -> Украина | H81: Украина | I81: =LEFT(Таблица8[[#This Row],[ФИО]],(M81-1)) -> Виноградов | J81: =MID(Таблица8[[#This Row],[ФИО]],M81,(N81-M81)) -> Карл | K81: =RIGHT(Таблица8[[#This Row],[ФИО]],(O81-N81)) -> Алексеевич | M81: =FIND(" ",Таблица8[[#This Row],[ФИО]],2) -> 11 | N81: =FIND(" ",Таблица8[[#This Row],[ФИО]],(M81+1)) -> 16 | O81: =LEN(Таблица8[[#This Row],[ФИО]]) -> 26 | Q81: =MID(Таблица8[[#This Row],[ФИО]],M81,(N81-M81)) -> Карл | R81: Виноградов | S81: Алексеевич
A82: 496 | B82: +380 030-138-6532 | C82: Вишняков Фома Викентьевич | D82: да | E82: 44867 | F82: =LEFT(B82,LEN(B82)-13) -> +380 | G82: =INDEX('коды стран'!$A$2:$A$7, MATCH(F82, 'коды стран'!$B$2:$B$7, 0)) -> Украина | H82: Украина | I82: =LEFT(Таблица8[[#This Row],[ФИО]],(M82-1)) -> Вишняков | J82: =MID(Таблица8[[#This Row],[ФИО]],M82,(N82-M82)) -> Фома | K82: =RIGHT(Таблица8[[#This Row],[ФИО]],(O82-N82)) -> Викентьевич | M82: =FIND(" ",Таблица8[[#This Row],[ФИО]],2) -> 9 | N82: =FIND(" ",Таблица8[[#This Row],[ФИО]],(M82+1)) -> 14 | O82: =LEN(Таблица8[[#This Row],[ФИО]]) -> 25 | Q82: =MID(Таблица8[[#This Row],[ФИО]],M82,(N82-M82)) -> Фома | R82: Вишняков | S82: Викентьевич
A83: 29 | B83: +7 028-813-4020 | C83: Вишняков Ярослав Анатольевич | D83: да | E83: 44704 | F83: =LEFT(B83,LEN(B83)-13) -> +7 | G83: =INDEX('коды стран'!$A$2:$A$7, MATCH(F83, 'коды стран'!$B$2:$B$7, 0)) -> Россия | H83: Россия | I83: =LEFT(Таблица8[[#This Row],[ФИО]],(M83-1)) -> Вишняков | J83: =MID(Таблица8[[#This Row],[ФИО]],M83,(N83-M83)) -> Ярослав | K83: =RIGHT(Таблица8[[#This Row],[ФИО]],(O83-N83)) -> Анатольевич | M83: =FIND(" ",Таблица8[[#This Row],[ФИО]],2) -> 9 | N83: =FIND(" ",Таблица8[[#This Row],[ФИО]],(M83+1)) -> 17 | O83: =LEN(Таблица8[[#This Row],[ФИО]]) -> 28 | Q83: =MID(Таблица8[[#This Row],[ФИО]],M83,(N83-M83)) -> Ярослав | R83: Вишняков | S83: Анатольевич
A84: 462 | B84: +7 915-487-8205 | C84: Владилен Иосифович Третьяков | D84: да | E84: 44751 | F84: =LEFT(B84,LEN(B84)-13) -> +7 | G84: =INDEX('коды стран'!$A$2:$A$7, MATCH(F84, 'коды стран'!$B$2:$B$7, 0)) -> Россия | H84: Россия | I84: =LEFT(Таблица8[[#This Row],[ФИО]],(M84-1)) -> Владилен | J84: =MID(Таблица8[[#This Row],[ФИО]],M84,(N84-M84)) -> Иосифович | K84: =RIGHT(Таблица8[[#This Row],[ФИО]],(O84-N84)) -> Третьяков | M84: =FIND(" ",Таблица8[[#This Row],[ФИО]],2) -> 9 | N84: =FIND(" ",Таблица8[[#This Row],[ФИО]],(M84+1)) -> 19 | O84: =LEN(Таблица8[[#This Row],[ФИО]]) -> 28 | Q84: =LEFT(Таблица8[[#This Row],[ФИО]],(M84-1)) -> Владилен | R84: Третьяков | S84: Иосифович
A85: 141 | B85: +7 731-326-3751 | C85: Владимиров Орест Артемьевич | D85: да | E85: 44743 | F85: =LEFT(B85,LEN(B85)-13) -> +7 | G85: =INDEX('коды стран'!$A$2:$A$7, MATCH(F85, 'коды стран'!$B$2:$B$7, 0)) -> Россия | H85: Россия | I85: =LEFT(Таблица8[[#This Row],[ФИО]],(M85-1)) -> Владимиров | J85: =MID(Таблица8[[#This Row],[ФИО]],M85,(N85-M85)) -> Орест | K85: =RIGHT(Таблица8[[#This Row],[ФИО]],(O85-N85)) -> Артемьевич | M85: =FIND(" ",Таблица8[[#This Row],[ФИО]],2) -> 11 | N85: =FIND(" ",Таблица8[[#This Row],[ФИО]],(M85+1)) -> 17 | O85: =LEN(Таблица8[[#This Row],[ФИО]]) -> 27 | Q85: =MID(Таблица8[[#This Row],[ФИО]],M85,(N85-M85)) -> Орест | R85: Владимиров | S85: Артемьевич
A86: 58 | B86: +375 524-220-8374 | C86: Владимирова Алина Феликсовна | D86: нет | E86: 44628 | F86: =LEFT(B86,LEN(B86)-13) -> +375 | G86: =INDEX('коды стран'!$A$2:$A$7, MATCH(F86, 'коды стран'!$B$2:$B$7, 0)) -> Беларусь | H86: Беларусь | I86: =LEFT(Таблица8[[#This Row],[ФИО]],(M86-1)) -> Владимирова | J86: =MID(Таблица8[[#This Row],[ФИО]],M86,(N86-M86)) -> Алина | K86: =RIGHT(Таблица8[[#This Row],[ФИО]],(O86-N86)) -> Феликсовна | M86: =FIND(" ",Таблица8[[#This Row],[ФИО]],2) -> 12 | N86: =FIND(" ",Таблица8[[#This Row],[ФИО]],(M86+1)) -> 18 | O86: =LEN(Таблица8[[#This Row],[ФИО]]) -> 28 | Q86: =MID(Таблица8[[#This Row],[ФИО]],M86,(N86-M86)) -> Алина | R86: Владимирова | S86: Феликсовна
A87: 213 | B87: +998 437-737-9329 | C87: Власов Адриан Чеславович | D87: нет | E87: 44733 | F87: =LEFT(B87,LEN(B87)-13) -> +998 | G87: =INDEX('коды стран'!$A$2:$A$7, MATCH(F87, 'коды стран'!$B$2:$B$7, 0)) -> Узбекистан | H87: Узбекистан | I87: =LEFT(Таблица8[[#This Row],[ФИО]],(M87-1)) -> Власов | J87: =MID(Таблица8[[#This Row],[ФИО]],M87,(N87-M87)) -> Адриан | K87: =RIGHT(Таблица8[[#This Row],[ФИО]],(O87-N87)) -> Чеславович | M87: =FIND(" ",Таблица8[[#This Row],[ФИО]],2) -> 7 | N87: =FIND(" ",Таблица8[[#This Row],[ФИО]],(M87+1)) -> 14 | O87: =LEN(Таблица8[[#This Row],[ФИО]]) -> 24 | Q87: =MID(Таблица8[[#This Row],[ФИО]],M87,(N87-M87)) -> Адриан | R87: Власов | S87: Чеславович
A88: 486 | B88: +7 056-712-2591 | C88: Волков Викентий Герасимович | D88: да | E88: 44723 | F88: =LEFT(B88,LEN(B88)-13) -> +7 | G88: =INDEX('коды стран'!$A$2:$A$7, MATCH(F88, 'коды стран'!$B$2:$B$7, 0)) -> Россия | H88: Россия | I88: =LEFT(Таблица8[[#This Row],[ФИО]],(M88-1)) -> Волков | J88: =MID(Таблица8[[#This Row],[ФИО]],M88,(N88-M88)) -> Викентий | K88: =RIGHT(Таблица8[[#This Row],[ФИО]],(O88-N88)) -> Герасимович | M88: =FIND(" ",Таблица8[[#This Row],[ФИО]],2) -> 7 | N88: =FIND(" ",Таблица8[[#This Row],[ФИО]],(M88+1)) -> 16 | O88: =LEN(Таблица8[[#This Row],[ФИО]]) -> 27 | Q88: =MID(Таблица8[[#This Row],[ФИО]],M88,(N88-M88)) -> Викентий | R88: Волков | S88: Герасимович
A89: 41 | B89: +7 661-552-6669 | C89: Волкова Валентина Николаевна | D89: да | E89: 44842 | F89: =LEFT(B89,LEN(B89)-13) -> +7 | G89: =INDEX('коды стран'!$A$2:$A$7, MATCH(F89, 'коды стран'!$B$2:$B$7, 0)) -> Россия | H89: Россия | I89: =LEFT(Таблица8[[#This Row],[ФИО]],(M89-1)) -> Волкова | J89: =MID(Таблица8[[#This Row],[ФИО]],M89,(N89-M89)) -> Валентина | K89: =RIGHT(Таблица8[[#This Row],[ФИО]],(O89-N89)) -> Николаевна | M89: =FIND(" ",Таблица8[[#This Row],[ФИО]],2) -> 8 | N89: =FIND(" ",Таблица8[[#This Row],[ФИО]],(M89+1)) -> 18 | O89: =LEN(Таблица8[[#This Row],[ФИО]]) -> 28 | Q89: =MID(Таблица8[[#This Row],[ФИО]],M89,(N89-M89)) -> Валентина | R89: Волкова | S89: Николаевна
A90: 200 | B90: +998 342-700-2159 | C90: Воробьева Анжела Аскольдовна | D90: да | E90: 44783 | F90: =LEFT(B90,LEN(B90)-13) -> +998 | G90: =INDEX('коды стран'!$A$2:$A$7, MATCH(F90, 'коды стран'!$B$2:$B$7, 0)) -> Узбекистан | H90: Узбекистан | I90: =LEFT(Таблица8[[#This Row],[ФИО]],(M90-1)) -> Воробьева | J90: =MID(Таблица8[[#This Row],[ФИО]],M90,(N90-M90)) -> Анжела | K90: =RIGHT(Таблица8[[#This Row],[ФИО]],(O90-N90)) -> Аскольдовна | M90: =FIND(" ",Таблица8[[#This Row],[ФИО]],2) -> 10 | N90: =FIND(" ",Таблица8[[#This Row],[ФИО]],(M90+1)) -> 17 | O90: =LEN(Таблица8[[#This Row],[ФИО]]) -> 28 | Q90: =MID(Таблица8[[#This Row],[ФИО]],M90,(N90-M90)) -> Анжела | R90: Воробьева | S90: Аскольдовна
A91: 173 | B91: +7 914-597-1350 | C91: Гаврилов Матвей Трифонович | D91: нет | E91: 44673 | F91: =LEFT(B91,LEN(B91)-13) -> +7 | G91: =INDEX('коды стран'!$A$2:$A$7, MATCH(F91, 'коды стран'!$B$2:$B$7, 0)) -> Россия | H91: Россия | I91: =LEFT(Таблица8[[#This Row],[ФИО]],(M91-1)) -> Гаврилов | J91: =MID(Таблица8[[#This Row],[ФИО]],M91,(N91-M91)) -> Матвей | K91: =RIGHT(Таблица8[[#This Row],[ФИО]],(O91-N91)) -> Трифонович | M91: =FIND(" ",Таблица8[[#This Row],[ФИО]],2) -> 9 | N91: =FIND(" ",Таблица8[[#This Row],[ФИО]],(M91+1)) -> 16 | O91: =LEN(Таблица8[[#This Row],[ФИО]]) -> 26 | Q91: =MID(Таблица8[[#This Row],[ФИО]],M91,(N91-M91)) -> Матвей | R91: Гаврилов | S91: Трифонович
A92: 102 | B92: +998 087-830-4222 | C92: Галактион Жанович Новиков | D92: нет | E92: 44723 | F92: =LEFT(B92,LEN(B92)-13) -> +998 | G92: =INDEX('коды стран'!$A$2:$A$7, MATCH(F92, 'коды стран'!$B$2:$B$7, 0)) -> Узбекистан | H92: Узбекистан | I92: =LEFT(Таблица8[[#This Row],[ФИО]],(M92-1)) -> Галактион | J92: =MID(Таблица8[[#This Row],[ФИО]],M92,(N92-M92)) -> Жанович | K92: =RIGHT(Таблица8[[#This Row],[ФИО]],(O92-N92)) -> Новиков | M92: =FIND(" ",Таблица8[[#This Row],[ФИО]],2) -> 10 | N92: =FIND(" ",Таблица8[[#This Row],[ФИО]],(M92+1)) -> 18 | O92: =LEN(Таблица8[[#This Row],[ФИО]]) -> 25 | Q92: =LEFT(Таблица8[[#This Row],[ФИО]],(M92-1)) -> Галактион | R92: Новиков | S92: Жанович
A93: 115 | B93: +375 523-528-4996 | C93: Галина Кирилловна Прохорова | D93: да | E93: 44832 | F93: =LEFT(B93,LEN(B93)-13) -> +375 | G93: =INDEX('коды стран'!$A$2:$A$7, MATCH(F93, 'коды стран'!$B$2:$B$7, 0)) -> Беларусь | H93: Беларусь | I93: =LEFT(Таблица8[[#This Row],[ФИО]],(M93-1)) -> Галина | J93: =MID(Таблица8[[#This Row],[ФИО]],M93,(N93-M93)) -> Кирилловна | K93: =RIGHT(Таблица8[[#This Row],[ФИО]],(O93-N93)) -> Прохорова | M93: =FIND(" ",Таблица8[[#This Row],[ФИО]],2) -> 7 | N93: =FIND(" ",Таблица8[[#This Row],[ФИО]],(M93+1)) -> 18 | O93: =LEN(Таблица8[[#This Row],[ФИО]]) -> 27 | Q93: =LEFT(Таблица8[[#This Row],[ФИО]],(M93-1)) -> Галина | R93: Прохорова | S93: Кирилловна
A94: 99 | B94: +7 542-005-0327 | C94: Галина Семеновна Петухова | D94: нет | E94: 44886 | F94: =LEFT(B94,LEN(B94)-13) -> +7 | G94: =INDEX('коды стран'!$A$2:$A$7, MATCH(F94, 'коды стран'!$B$2:$B$7, 0)) -> Россия | H94: Россия | I94: =LEFT(Таблица8[[#This Row],[ФИО]],(M94-1)) -> Галина | J94: =MID(Таблица8[[#This Row],[ФИО]],M94,(N94-M94)) -> Семеновна | K94: =RIGHT(Таблица8[[#This Row],[ФИО]],(O94-N94)) -> Петухова | M94: =FIND(" ",Таблица8[[#This Row],[ФИО]],2) -> 7 | N94: =FIND(" ",Таблица8[[#This Row],[ФИО]],(M94+1)) -> 17 | O94: =LEN(Таблица8[[#This Row],[ФИО]]) -> 25 | Q94: =LEFT(Таблица8[[#This Row],[ФИО]],(M94-1)) -> Галина | R94: Петухова | S94: Семеновна
A95: 204 | B95: +7 181-799-6850 | C95: Герасимов Еремей Демидович | D95: да | E95: 44867 | F95: =LEFT(B95,LEN(B95)-13) -> +7 | G95: =INDEX('коды стран'!$A$2:$A$7, MATCH(F95, 'коды стран'!$B$2:$B$7, 0)) -> Россия | H95: Россия | I95: =LEFT(Таблица8[[#This Row],[ФИО]],(M95-1)) -> Герасимов | J95: =MID(Таблица8[[#This Row],[ФИО]],M95,(N95-M95)) -> Еремей | K95: =RIGHT(Таблица8[[#This Row],[ФИО]],(O95-N95)) -> Демидович | M95: =FIND(" ",Таблица8[[#This Row],[ФИО]],2) -> 10 | N95: =FIND(" ",Таблица8[[#This Row],[ФИО]],(M95+1)) -> 17 | O95: =LEN(Таблица8[[#This Row],[ФИО]]) -> 26 | Q95: =MID(Таблица8[[#This Row],[ФИО]],M95,(N95-M95)) -> Еремей | R95: Герасимов | S95: Демидович
A96: 383 | B96: +380 959-961-5281 | C96: Герасимов Родион Харитонович | D96: нет | E96: 44876 | F96: =LEFT(B96,LEN(B96)-13) -> +380 | G96: =INDEX('коды стран'!$A$2:$A$7, MATCH(F96, 'коды стран'!$B$2:$B$7, 0)) -> Украина | H96: Украина | I96: =LEFT(Таблица8[[#This Row],[ФИО]],(M96-1)) -> Герасимов | J96: =MID(Таблица8[[#This Row],[ФИО]],M96,(N96-M96)) -> Родион | K96: =RIGHT(Таблица8[[#This Row],[ФИО]],(O96-N96)) -> Харитонович | M96: =FIND(" ",Таблица8[[#This Row],[ФИО]],2) -> 10 | N96: =FIND(" ",Таблица8[[#This Row],[ФИО]],(M96+1)) -> 17 | O96: =LEN(Таблица8[[#This Row],[ФИО]]) -> 28 | Q96: =MID(Таблица8[[#This Row],[ФИО]],M96,(N96-M96)) -> Родион | R96: Герасимов | S96: Харитонович
A97: 455 | B97: +380 315-815-3268 | C97: Герман Арсеньевич Калинин | D97: да | E97: 44820 | F97: =LEFT(B97,LEN(B97)-13) -> +380 | G97: =INDEX('коды стран'!$A$2:$A$7, MATCH(F97, 'коды стран'!$B$2:$B$7, 0)) -> Украина | H97: Украина | I97: =LEFT(Таблица8[[#This Row],[ФИО]],(M97-1)) -> Герман | J97: =MID(Таблица8[[#This Row],[ФИО]],M97,(N97-M97)) -> Арсеньевич | K97: =RIGHT(Таблица8[[#This Row],[ФИО]],(O97-N97)) -> Калинин | M97: =FIND(" ",Таблица8[[#This Row],[ФИО]],2) -> 7 | N97: =FIND(" ",Таблица8[[#This Row],[ФИО]],(M97+1)) -> 18 | O97: =LEN(Таблица8[[#This Row],[ФИО]]) -> 25 | Q97: =LEFT(Таблица8[[#This Row],[ФИО]],(M97-1)) -> Герман | R97: Калинин | S97: Арсеньевич
A98: 262 | B98: +992 756-085-4605 | C98: г-жа Воробьева Иванна Юрьевна | D98: да | E98: 44778 | F98: =LEFT(B98,LEN(B98)-13) -> +992 | G98: =INDEX('коды стран'!$A$2:$A$7, MATCH(F98, 'коды стран'!$B$2:$B$7, 0)) -> Таджикистан | H98: Таджикистан | I98: =LEFT(Таблица8[[#This Row],[ФИО]],(M98-1)) -> г-жа | J98: =MID(Таблица8[[#This Row],[ФИО]],M98,(N98-M98)) -> Воробьева | K98: =RIGHT(Таблица8[[#This Row],[ФИО]],(O98-N98)) -> Иванна Юрьевна | M98: =FIND(" ",Таблица8[[#This Row],[ФИО]],2) -> 5 | N98: =FIND(" ",Таблица8[[#This Row],[ФИО]],(M98+1)) -> 15 | O98: =LEN(Таблица8[[#This Row],[ФИО]]) -> 29 | Q98: Иванна | R98: Воробьева | S98: Юрьевна
A99: 494 | B99: +375 268-005-4917 | C99: г-жа Ефимова Анна Филипповна | D99: нет | E99: 44738 | F99: =LEFT(B99,LEN(B99)-13) -> +375 | G99: =INDEX('коды стран'!$A$2:$A$7, MATCH(F99, 'коды стран'!$B$2:$B$7, 0)) -> Беларусь | H99: Беларусь | I99: =LEFT(Таблица8[[#This Row],[ФИО]],(M99-1)) -> г-жа | J99: =MID(Таблица8[[#This Row],[ФИО]],M99,(N99-M99)) -> Ефимова | K99: =RIGHT(Таблица8[[#This Row],[ФИО]],(O99-N99)) -> Анна Филипповна | M99: =FIND(" ",Таблица8[[#This Row],[ФИО]],2) -> 5 | N99: =FIND(" ",Таблица8[[#This Row],[ФИО]],(M99+1)) -> 13 | O99: =LEN(Таблица8[[#This Row],[ФИО]]) -> 28 | Q99: Анна | R99: Ефимова | S99: Филипповна
A100: 197 | B100: +380 255-745-0289 | C100: г-жа Миронова Клавдия Феликсовна | D100: нет | E100: 44785 | F100: =LEFT(B100,LEN(B100)-13) -> +380 | G100: =INDEX('коды стран'!$A$2:$A$7, MATCH(F100, 'коды стран'!$B$2:$B$7, 0)) -> Украина | H100: Украина | I100: =LEFT(Таблица8[[#This Row],[ФИО]],(M100-1)) -> г-жа | J100: =MID(Таблица8[[#This Row],[ФИО]],M100,(N100-M100)) -> Миронова | K100: =RIGHT(Таблица8[[#This Row],[ФИО]],(O100-N100)) -> Клавдия Феликсовна | M100: =FIND(" ",Таблица8[[#This Row],[ФИО]],2) -> 5 | N100: =FIND(" ",Таблица8[[#This Row],[ФИО]],(M100+1)) -> 14 | O100: =LEN(Таблица8[[#This Row],[ФИО]]) -> 32 | Q100: Клавдия | R100: Миронова | S100: Феликсовна
A101: 52 | B101: +7 340-358-5907 | C101: Глафира Николаевна Мельникова | D101: да | E101: 44917 | F101: =LEFT(B101,LEN(B101)-13) -> +7 | G101: =INDEX('коды стран'!$A$2:$A$7, MATCH(F101, 'коды стран'!$B$2:$B$7, 0)) -> Россия | H101: Россия | I101: =LEFT(Таблица8[[#This Row],[ФИО]],(M101-1)) -> Глафира | J101: =MID(Таблица8[[#This Row],[ФИО]],M101,(N101-M101)) -> Николаевна | K101: =RIGHT(Таблица8[[#This Row],[ФИО]],(O101-N101)) -> Мельникова | M101: =FIND(" ",Таблица8[[#This Row],[ФИО]],2) -> 8 | N101: =FIND(" ",Таблица8[[#This Row],[ФИО]],(M101+1)) -> 19 | O101: =LEN(Таблица8[[#This Row],[ФИО]]) -> 29 | Q101: =LEFT(Таблица8[[#This Row],[ФИО]],(M101-1)) -> Глафира | R101: Мельникова | S101: Николаевна
A102: 83 | B102: +992 377-961-6550 | C102: г-н Зуев Трифон Зиновьевич | D102: да | E102: 44739 | F102: =LEFT(B102,LEN(B102)-13) -> +992 | G102: =INDEX('коды стран'!$A$2:$A$7, MATCH(F102, 'коды стран'!$B$2:$B$7, 0)) -> Таджикистан | H102: Таджикистан | I102: =LEFT(Таблица8[[#This Row],[ФИО]],(M102-1)) -> г-н | J102: =MID(Таблица8[[#This Row],[ФИО]],M102,(N102-M102)) -> Зуев | K102: =RIGHT(Таблица8[[#This Row],[ФИО]],(O102-N102)) -> Трифон Зиновьевич | M102: =FIND(" ",Таблица8[[#This Row],[ФИО]],2) -> 4 | N102: =FIND(" ",Таблица8[[#This Row],[ФИО]],(M102+1)) -> 9 | O102: =LEN(Таблица8[[#This Row],[ФИО]]) -> 26 | Q102: Трифон | R102: Зуев | S102: Зиновьевич
A103: 250 | B103: +7 981-183-3972 | C103: г-н Копылов Лаврентий Артемьевич | D103: да | E103: 44856 | F103: =LEFT(B103,LEN(B103)-13) -> +7 | G103: =INDEX('коды стран'!$A$2:$A$7, MATCH(F103, 'коды стран'!$B$2:$B$7, 0)) -> Россия | H103: Россия | I103: =LEFT(Таблица8[[#This Row],[ФИО]],(M103-1)) -> г-н | J103: =MID(Таблица8[[#This Row],[ФИО]],M103,(N103-M103)) -> Копылов | K103: =RIGHT(Таблица8[[#This Row],[ФИО]],(O103-N103)) -> Лаврентий Артемьевич | M103: =FIND(" ",Таблица8[[#This Row],[ФИО]],2) -> 4 | N103: =FIND(" ",Таблица8[[#This Row],[ФИО]],(M103+1)) -> 12 | O103: =LEN(Таблица8[[#This Row],[ФИО]]) -> 32 | Q103: Лаврентий | R103: Копылов | S103: Артемьевич
A104: 280 | B104: +7 109-995-2846 | C104: г-н Рыбаков Автоном Антонович | D104: нет | E104: 44563 | F104: =LEFT(B104,LEN(B104)-13) -> +7 | G104: =INDEX('коды стран'!$A$2:$A$7, MATCH(F104, 'коды стран'!$B$2:$B$7, 0)) -> Россия | H104: Россия | I104: =LEFT(Таблица8[[#This Row],[ФИО]],(M104-1)) -> г-н | J104: =MID(Таблица8[[#This Row],[ФИО]],M104,(N104-M104)) -> Рыбаков | K104: =RIGHT(Таблица8[[#This Row],[ФИО]],(O104-N104)) -> Автоном Антонович | M104: =FIND(" ",Таблица8[[#This Row],[ФИО]],2) -> 4 | N104: =FIND(" ",Таблица8[[#This Row],[ФИО]],(M104+1)) -> 12 | O104: =LEN(Таблица8[[#This Row],[ФИО]]) -> 29 | Q104: Автоном | R104: Рыбаков | S104: Антонович
A105: 286 | B105: +992 292-122-7648 | C105: г-н Савельев Федосий Феоктистович | D105: нет | E105: 44563 | F105: =LEFT(B105,LEN(B105)-13) -> +992 | G105: =INDEX('коды стран'!$A$2:$A$7, MATCH(F105, 'коды стран'!$B$2:$B$7, 0)) -> Таджикистан | H105: Таджикистан | I105: =LEFT(Таблица8[[#This Row],[ФИО]],(M105-1)) -> г-н | J105: =MID(Таблица8[[#This Row],[ФИО]],M105,(N105-M105)) -> Савельев | K105: =RIGHT(Таблица8[[#This Row],[ФИО]],(O105-N105)) -> Федосий Феоктистович | M105: =FIND(" ",Таблица8[[#This Row],[ФИО]],2) -> 4 | N105: =FIND(" ",Таблица8[[#This Row],[ФИО]],(M105+1)) -> 13 | O105: =LEN(Таблица8[[#This Row],[ФИО]]) -> 33 | Q105: Федосий | R105: Савельев | S105: Феоктистович
A106: 199 | B106: +998 455-746-0633 | C106: Горбунова Алевтина Максимовна | D106: да | E106: 44715 | F106: =LEFT(B106,LEN(B106)-13) -> +998 | G106: =INDEX('коды стран'!$A$2:$A$7, MATCH(F106, 'коды стран'!$B$2:$B$7, 0)) -> Узбекистан | H106: Узбекистан | I106: =LEFT(Таблица8[[#This Row],[ФИО]],(M106-1)) -> Горбунова | J106: =MID(Таблица8[[#This Row],[ФИО]],M106,(N106-M106)) -> Алевтина | K106: =RIGHT(Таблица8[[#This Row],[ФИО]],(O106-N106)) -> Максимовна | M106: =FIND(" ",Таблица8[[#This Row],[ФИО]],2) -> 10 | N106: =FIND(" ",Таблица8[[#This Row],[ФИО]],(M106+1)) -> 19 | O106: =LEN(Таблица8[[#This Row],[ФИО]]) -> 29 | Q106: =MID(Таблица8[[#This Row],[ФИО]],M106,(N106-M106)) -> Алевтина | R106: Горбунова | S106: Максимовна
A107: 273 | B107: +998 876-305-1700 | C107: Горбунова Наина Филипповна | D107: нет | E107: 44599 | F107: =LEFT(B107,LEN(B107)-13) -> +998 | G107: =INDEX('коды стран'!$A$2:$A$7, MATCH(F107, 'коды стран'!$B$2:$B$7, 0)) -> Узбекистан | H107: Узбекистан | I107: =LEFT(Таблица8[[#This Row],[ФИО]],(M107-1)) -> Горбунова | J107: =MID(Таблица8[[#This Row],[ФИО]],M107,(N107-M107)) -> Наина | K107: =RIGHT(Таблица8[[#This Row],[ФИО]],(O107-N107)) -> Филипповна | M107: =FIND(" ",Таблица8[[#This Row],[ФИО]],2) -> 10 | N107: =FIND(" ",Таблица8[[#This Row],[ФИО]],(M107+1)) -> 16 | O107: =LEN(Таблица8[[#This Row],[ФИО]]) -> 26 | Q107: =MID(Таблица8[[#This Row],[ФИО]],M107,(N107-M107)) -> Наина | R107: Горбунова | S107: Филипповна
A108: 442 | B108: +992 774-047-4624 | C108: Гордей Матвеевич Медведев | D108: нет | E108: 44746 | F108: =LEFT(B108,LEN(B108)-13) -> +992 | G108: =INDEX('коды стран'!$A$2:$A$7, MATCH(F108, 'коды стран'!$B$2:$B$7, 0)) -> Таджикистан | H108: Таджикистан | I108: =LEFT(Таблица8[[#This Row],[ФИО]],(M108-1)) -> Гордей | J108: =MID(Таблица8[[#This Row],[ФИО]],M108,(N108-M108)) -> Матвеевич | K108: =RIGHT(Таблица8[[#This Row],[ФИО]],(O108-N108)) -> Медведев | M108: =FIND(" ",Таблица8[[#This Row],[ФИО]],2) -> 7 | N108: =FIND(" ",Таблица8[[#This Row],[ФИО]],(M108+1)) -> 17 | O108: =LEN(Таблица8[[#This Row],[ФИО]]) -> 25 | Q108: =LEFT(Таблица8[[#This Row],[ФИО]],(M108-1)) -> Гордей | R108: Медведев | S108: Матвеевич
A109: 266 | B109: +7 963-508-8333 | C109: Горшкова Василиса Святославовна | D109: нет | E109: 44795 | F109: =LEFT(B109,LEN(B109)-13) -> +7 | G109: =INDEX('коды стран'!$A$2:$A$7, MATCH(F109, 'коды стран'!$B$2:$B$7, 0)) -> Россия | H109: Россия | I109: =LEFT(Таблица8[[#This Row],[ФИО]],(M109-1)) -> Горшкова | J109: =MID(Таблица8[[#This Row],[ФИО]],M109,(N109-M109)) -> Василиса | K109: =RIGHT(Таблица8[[#This Row],[ФИО]],(O109-N109)) -> Святославовна | M109: =FIND(" ",Таблица8[[#This Row],[ФИО]],2) -> 9 | N109: =FIND(" ",Таблица8[[#This Row],[ФИО]],(M109+1)) -> 18 | O109: =LEN(Таблица8[[#This Row],[ФИО]]) -> 31 | Q109: =MID(Таблица8[[#This Row],[ФИО]],M109,(N109-M109)) -> Василиса | R109: Горшкова | S109: Святославовна
A110: 63 | B110: +380 668-055-3546 | C110: Горшкова Клавдия Борисовна | D110: да | E110: 44684 | F110: =LEFT(B110,LEN(B110)-13) -> +380 | G110: =INDEX('коды стран'!$A$2:$A$7, MATCH(F110, 'коды стран'!$B$2:$B$7, 0)) -> Украина | H110: Украина | I110: =LEFT(Таблица8[[#This Row],[ФИО]],(M110-1)) -> Горшкова | J110: =MID(Таблица8[[#This Row],[ФИО]],M110,(N110-M110)) -> Клавдия | K110: =RIGHT(Таблица8[[#This Row],[ФИО]],(O110-N110)) -> Борисовна | M110: =FIND(" ",Таблица8[[#This Row],[ФИО]],2) -> 9 | N110: =FIND(" ",Таблица8[[#This Row],[ФИО]],(M110+1)) -> 17 | O110: =LEN(Таблица8[[#This Row],[ФИО]]) -> 26 | Q110: =MID(Таблица8[[#This Row],[ФИО]],M110,(N110-M110)) -> Клавдия | R110: Горшкова | S110: Борисовна
A111: 50 | B111: +998 220-798-0143 | C111: Гостомысл Фомич Одинцов | D111: да | E111: 44576 | F111: =LEFT(B111,LEN(B111)-13) -> +998 | G111: =INDEX('коды стран'!$A$2:$A$7, MATCH(F111, 'коды стран'!$B$2:$B$7, 0)) -> Узбекистан | H111: Узбекистан | I111: =LEFT(Таблица8[[#This Row],[ФИО]],(M111-1)) -> Гостомысл | J111: =MID(Таблица8[[#This Row],[ФИО]],M111,(N111-M111)) -> Фомич | K111: =RIGHT(Таблица8[[#This Row],[ФИО]],(O111-N111)) -> Одинцов | M111: =FIND(" ",Таблица8[[#This Row],[ФИО]],2) -> 10 | N111: =FIND(" ",Таблица8[[#This Row],[ФИО]],(M111+1)) -> 16 | O111: =LEN(Таблица8[[#This Row],[ФИО]]) -> 23 | Q111: =LEFT(Таблица8[[#This Row],[ФИО]],(M111-1)) -> Гостомысл | R111: Одинцов | S111: Фомич
...

Sheet коды стран
A1: Страна | B1: Код
A2: Россия | B2: +7
A3: Казахстан | B3: +7
A4: Беларусь | B4: +375
A5: Узбекистан | B5: +998
A6: Таджикистан | B6: +992
A7: Украина | B7: +380
